Workbook
Name New: #REF!
Name New: SupportData!$A$8:$E$32
Name ProductLines: #REF!
Name ProductLines: SupportData!$A$53:$E$65
Name qrySwatchLine6cCurrent: '3x5 Leather'!$A$15:$G$166
Name qrySwatchLine6cDrop: '3x5 Leather'!#REF!
Name qrySwatchLine6iCurrent: '6x6 Fabric'!$A$10:$G$443
Name qrySwatchLineClCurrent: 'Select Stationary Leather'!$A$14:$L$18
Name qrySwatchLineCsCurrent: 'Select Fabrics 12 x 12'!$A$25:$M$27
Name qrySwatchLineDcCurrent: 'Design Center'!$A$11:$P$542
Name qrySwatchLineDcDrop: 'Design Center'!#REF!
Name qrySwatchLineExCurrent: 'Custom Leather Plus'!$A$10:$L$17
Name qrySwatchLineExCurrent: 'Specialty Leather Handle'!#REF!
Name qrySwatchLineExCurrent: 'Specialty Leather Ring Page'!$A$10:$L$16
Name qrySwatchLineExDrop: 'Custom Leather'!#REF!
Name qrySwatchLineExDrop: 'Custom Leather Plus'!#REF!
Name qrySwatchLineExDrop: 'Specialty Leather Ring Page'!#REF!
Name qrySwatchLineFcCurrent: 'Fringe and Cord'!$A$11:$K$18
Name qrySwatchLineKwCurrent: 'Cut and Sewn Fabric Waterfalls'!$A$10:$V$75
Name qrySwatchLineKwDrop: 'Cut and Sewn Fabric Waterfalls'!#REF!
Name qrySwatchLineLrCurrent: '2x3 Leather'!$A$9:$G$88
Name qrySwatchLineLrDrop: '2x3 Leather'!#REF!
Name qrySwatchLineLwCurrent: 'Cut and Sewn Leather Waterfalls'!$A$10:$O$71
Name qrySwatchLineLwDrop: 'Cut and Sewn Leather Waterfalls'!#REF!
Name qrySwatchLineMuCurrent: 'Ring Pages - Complete Set'!$A$9:$L$268
Name qrySwatchLineMuCurrent_2: 'MASTER FABRICS'!$A$13:$P$199
Name qrySwatchLineSlCurrent: 'Select Reclining Leather'!$A$11:$H$91
Name qrySwatchLineSlDrop: 'Select Reclining Leather'!#REF!
Name SwatchCovers: #REF!
Name SwatchCovers: #REF!
Name SwatchLines: #REF!
Name SwatchLines: SupportData!$A$8:$E$32
Name SwatchProfiles: #REF!
Name SwatchProfiles: #REF!
Name SwatchTypes: #REF!
Name SwatchTypes: SupportData!$A$37:$D$48

Sheet MASTER FABRICS
A1: All Active Fabric SKU's as of April 2026 Market
A3: Fabric Wearability Descriptions | J3: Pillow Program | K3: Specialty Fabric Descriptions | L3: Key:
A4: Normal | B4: (Black Dot) This fabric is recommended for use on all La-Z-Boy upholstered furniture. | J4: Pillows are NOT available in LL, LS, LM, RL, BU or UE cap codes | K4: I = iClean | L4: Immediate Drop
A5: Medium | B5: (Green Dot) This fabric is recommended for use on sofas, sleep sofas, Duo, La-Z-Boy Classics, | K5: C = Conserve | L5: Phase Outs
B6: and Occasional chairs. It is not allowed for use on recliners, motion sofas or motion modulars. | K6: A = Antimicrobial | L6: New Phase Outs
A7: Performance | B7: (P Dot) This fabric is recommended for use on all La-Z-Boy upholstered furniture. While | K7: PF = Pet Friendly | L7: April 2026 Drops
B8: La-Z-Boy's fabrics are all tested to the highest industry standards, Performance Fabrics must receive | K8: N = Nanobionic
B9: excellent ratings for physical durability. Performance fabrics outperform other fabrics by receiving | K9: W*B = Bleach Cleanable
B10: outstanding results for pilling, abrasion and fraying.
A12: Series Number | B12: Pattern Name | C12: Colors | D12: # of SKU's | E12: Product Line | F12: Intro Date | G12: Horiz. Repeat | H12: Vertical Repeat | I12: CAP Code | J12: Face Contents | K12: Back Contents | L12: Wearability | M12: Specialty Fabric | N12: Welt Pattern | O12: Slip Cover Program | P12: Cleaning Code | Q12: Description(s)
A13: B1538 | B13: Seamount | C13: 76 = Cappuccino 74 = Sable 08 = Burgundy 53 = Silver 85 = Indigo | D13: 5 | E13: CH | F13: 43009 | G13: 0 | H13: 0 | I13: UR | J13: 100% Polyester | L13: N | P13: S | Q13: Seamount is a 100% polyester microfiber that has been processed with a woven backing for stability. Color is applied through a piece dye process to create depth. A subtle herringbone pattern makes this cover a trendy visual for any space.
A14: B1662 | B14: Rodigo | C14: 57 = Stone 78 = Walnut 86 = Navy 76 = Marsh | D14: 4 | E14: MU | F14: 43556 | G14: 0 | H14: 0 | I14: UR | J14: 100% Polyester | L14: P | P14: WS
A15: B1808 | B15: Social Club | C15: 52 = Stone 57 = Charcoal 68 = Pewter 72 = Chalk 76 = Cocoa | D15: 5 | E15: MU | F15: 44287 | G15: 0 | H15: 0 | I15: DR | J15: 100% Polyester | L15: P | P15: S | Q15: A super soft low pile pieced dyed chenille that has a subtle spaced dyed warp which gives a cross hatch like contrast with a speckled black dot design. The product is backed with a standard acrylic latex backing.
A16: B1827 | B16: Brink | C16: 25 = Lentil 86 = Slate | D16: 2 | E16: MU | F16: 44287 | G16: 0 | H16: 0 | I16: DR | J16: 100% Polyester | L16: N | P16: S | Q16: Brink is a multi-color plain with nubby space-dyed yarns, giving Brink both surface and visual texture. Each of the colorways offers enough shade variation to be used as blue, beige, gray, and green. Using 100% polyester yarns, Brink passes heavy duty wearability so it can be used as a new look textural motion cover, as well as a flat weave stationary fabric.
A17: C1371 | B17: Seasons | C17: 66 = Mocha 62 = Khaki 78 = Chocolate 28 = Loden 87 = Charcoal 08 = Redwood | D17: 6 | E17: MU | F17: 42278 | G17: 0 | H17: 0 | I17: DR | J17: 100% Polyester | L17: N | P17: S
A18: C1516 | B18: Merit | C18: 51 = Platinum 31 = Dove 57 = Charcoal | D18: 5 | E18: MU | F18: 42826 | G18: 0 | H18: 0 | I18: DR | J18: 100% Polyester | L18: N | P18: WS
A19: C1525 | B19: Roma | C19: 53 = Storm 78 = Espresso 74 = Mocha 86 = Navy 34 = Cream | D19: 5 | E19: CH | F19: 42826 | G19: 0 | H19: 0 | I19: DR | J19: 100% Polyester | L19: N | P19: S | Q19: Roma is a combination of a classic chenille texture design with a special padded backing to give a very soft, plush effect. The padded backing increases the durability of this 100% polyester fabric. The woven face creates a subtle color effect.
A20: C1584 | B20: Saxon | C20: 97 = Marine 31 = Oyster 48 = Chestnut 50 = Onyx 87 = Indigo | D20: 6 | E20: MU | F20: 43191 | G20: 14.4 | H20: 13.4 | I20: DR | J20: 100% Polyester | L20: N | P20: WS | Q20: Juxtapose this modern design with highly decorative and artful furnishings for a vibrant look. Pops of bold color let bright hues take center stage. The meticulously designed shapes, elegantly proportioned, are etched in full-faced plush chenille.
A21: C1625 | B21: Vance | C21: 32 = Sand 27 = Sage 86 = Eclipse 52 = Ice 76 = Mocha 08 = Garnet | D21: 6 | E21: CH | F21: 43374 | G21: 23.6 | H21: 24.4 | I21: UR | J21: 100% Polyester | L21: N | P21: WS | Q21: A multidimensional print on a textured, knit base cloth, Vance gives the illusion of a chunky woven, while maintaining the durability and plush feeling of a velvet.
A22: C1659 | B22: McKittrick | C22: 67 = Charcoal 72 = Taupe 62 = Smoke 86 = Indigo 92 = Mist | D22: 5 | E22: MU | F22: 43556 | G22: 0.3 | H22: 0.2 | I22: DR | J22: 100% Polyester | L22: N | P22: W
A23: C1670 | B23: Northern Exposure | C23: 76 = Daybreak | D23: 1 | E23: MU | F23: 43556 | G23: 14.37 | H23: 26.93 | I23: DR | J23: 100% Polyester | L23: N | P23: W | Q23: Enter the great outdoors with this detailed, woven tapestry pattern. Bring the wildlife into your home with deer, bears, and moose to give that rustic appeal.
A24: C1700 | B24: Nico | C24: 53 = Ash 57 = Charcoal 33 = Oyster | D24: 3 | E24: MU | F24: 43739 | G24: 0 | H24: 0 | I24: DR | J24: 95.5% Polyester, 4.5% Cotton | L24: N | N24: X | P24: S | Q24: Nico is a beautiful, traditional basket weave design incorporating novelty yarns in both the warp and fill directions for added dimension of color and texture in a classic pattern.
A25: C1754 | B25: Kemet | C25: 32 = Sand 74 = Brownstone 86 = Slate | D25: 3 | E25: MU | F25: 43922 | G25: 0 | H25: 0 | I25: UR | J25: 100% Polyester | L25: P | P25: S | Q25: This is a printed warp knit with an extremely soft hand. The print gives a subtle textured look to create more character on the face. All colors are very applicable for motion and recliners, as well casual stationary frames.
A26: C1757 | B26: Bartaloni | C26: 73 = Twig 33 = Birch 53 = Flannel 31 = Oatmeal | D26: 4 | E26: MU | F26: 43922 | G26: .625 | H26: 1.875 | I26: DR | J26: 100% Polyester | L26: N | P26: S | Q26: Bartaloni is a plush chenille with a fine herringbone pattern colored to live casually in todays’ interiors. Soft to the touch, beautiful and durable for our daily lives, Bartaloni is a great choice for any interior.
A27: C1809 | B27: Donegal | C27: 64 = Linen 69 = Granite 74 = Mushroom 87 = Marine | D27: 4 | E27: MU | F27: 44287 | G27: 0 | H27: 0 | I27: DR | J27: 100% Polyester | L27: N | P27: S | Q27: Pattern Donegal brings fashion to the forefront in your home where traditions start, and everyone is welcome. This bold plain assimilates inspiration from the runways of Paris, London, and Milan. A plain fabric seems like the simplest of textiles, but what goes into the creation of a great plain is really quite complicated. Beauty radiates warmth from the inspired mix of color and texture in pattern Donegal. Plush chenille is the yarn that creates a lofty feel and luxurious soft hand combined into an intricate dimensional plain weave. Donegal is alluring on its own offering exciting new colors each dreamy, natural, and calming. Live well with this chic and casual cover.
A28: C1812 | B28: Damon | C28: 33 = Oyster 54 = Stone 57 = Charcoal 62 = Muslin 86 = Midnight | D28: 5 | E28: MU | F28: 44287 | G28: 0 | H28: 0 | I28: UR | J28: 94% Polyester, 6% Nylon | L28: N | P28: S | Q28: Damon is a super soft padded piece-dyed chenille fabric with a fleece backing meant to accentuate the loft of the face. The fabric consists of a novelty subtle contrast yarn that is meant to give the product a bit more depth.
A29: C1852 | B29: Tiago | C29: 65 = Fawn 55 = Granite 52 = Twilight 76 = Mocha 86 = Navy | D29: 5 | E29: MU | F29: 44470 | G29: 0 | H29: 0 | I29: DR | J29: 100% Polyester | L29: N | P29: W | Q29: Create an environment of warmth and coziness with this soft chenille body cloth Tiago. Its space dyed warp yarns combined with a textured weave effect add depth and dimension to the bi-color chenille body. This gorgeous pattern will bring texture into the home. Offered in a selection of colors – Fawn, Granite, Mocha, Twilight and Navy you will find the right color to create a welcoming space. Tiago is made of 100% polyester and is exceeds over 15,000 double rubs.
A30: C1860 | B30: Persia | C30: 36 = Desert 86 = Lake 08 = Wine 54 = Greystone 76 = Bark | D30: 5 | E30: MU | F30: 44470 | G30: 0 | H30: 0 | I30: DR | J30: 100% Polyester | L30: N | P30: WS | Q30: An exceptionally soft face chenille semi-plain, Persia has both strength and durability because it is rated as a heavy duty wearable fabric. Persia is backed with a padding to give it a more substantial feel, making it perfect for motion applications. With its tonal shades of today’s popular colorations, combined with its soft hand, Persia also is a very saleable stationary cover.
A31: C1861 | B31: Sarah | C31: 86 = Indigo 58 = Slate 53 = Dove 62 = Truffle | D31: 4 | E31: MU | F31: 44652 | G31: 0 | H31: 0 | I31: DR | J31: 100% Polyester | L31: P | O31: X | P31: WS | Q31: a beautifully refined base cloth woven with a sumptuous high-quality chenille yarn on a finely, textured warp. The special warp creates a soft weave interest and enhanced durability.
A32: C1872 | B32: Lynx | C32: 33 = Burlap 76 = Birch 52 = Cement 32 = Cream | D32: 4 | E32: MU | F32: 44652 | G32: 0 | H32: 0 | I32: DR | J32: 100% Polyester | L32: N | P32: WS | Q32: Lynx is a 100% polyester jacquard, woven in tonal coloration combo’s. The mid-sized scaled pattern effect is subtle enough to be used on the body of any stationary group, but also distinctive enough to be used as an accent chair and pillow. A great value for a jacquard weave, Lynx rates as a heavy duty wearable fabric so it is perfect for motion.
A33: C1882 | B33: Lukas | C33: 32 = Khaki 86 = Navy 79 = Fudge 73 = Camel | D33: 4 | E33: MU | F33: 44652 | G33: 0 | H33: 0 | I33: DR | J33: 100% Polyester | L33: P | P33: S | Q33: Lukas is a tremendous fabric, perfect for motion. It is 100% polyester, heavy duty wearable, but with a luxuriously soft hand. Woven in a subtle, semi-plain block pattern, with a come and go strie twist yarn, the texture behind the plushness adds great eye appeal to the soft touch of LUKAS.
A34: C1945 | B34: Cordance | C34: 33=Pearl 54=Pebble 72=Driftwood 77=Chocolate | D34: 4 | E34: MU | F34: 45017 | G34: 0 | H34: 0 | I34: UR | J34: 100% Polyester | L34: N | P34: W | Q34: Cordance T/W is a unique texture with a distinctively vertical raised tufted cords also known as wales. This wide wale pattern, Cordance TW, has a soft hand and is the ideal fabric to make any piece of furniture extra cozy. Inherently plush, Cordance T/W is offered in four luscious colors: Chocolate, Driftwood, Pearl, and Pebble. Cordance T/W is made of 100% polyester.
A35: C1965 | B35: Nora | C35: 32=Ivory 52=Oyster 66=Truffle 84=Harbor | D35: 4 | E35: MU | F35: 45017 | G35: 0 | H35: 0 | I35: DR | J35: 100% Polyester | L35: N | P35: WS | Q35: A highly creative mix of soft chenille yarns woven with a variety of high and low novelty yarns define this multi textured base cloth. The combination of yarns and gentle interplay of color creates a wonderful surface interest base cloth that is highly usable for a wide variety of interior schemes.
A36: C1967 | B36: Lunar | C36: 33=Stone 55=Smoke 64=Taupe 68=Mocha 86=Navy | D36: 5 | E36: MU | F36: 45017 | G36: 0 | H36: 0 | I36: DR | J36: 97% Polyester, 3% Rayon | L36: P | P36: WS | Q36: A mélange woven chenille with a colorful warp creating a detailed background with a tweedy look & soft handle. It gives a luxurious feeling and looks extremely soft. This also enhances the seating comfort.
A37: C2029 | B37: Easy | C37: 07 = Brick 31 = Linen 58 = Stone 64 = Pebble 87 = Midnight | D37: 5 | E37: MU | F37: 45383 | G37: 0 | H37: 0 | I37: DR | J37: 100% Polyester | L37: N | P37: WS | Q37: Easy is a motion-friendly base cloth using multi-dimensional chenille in a high-low weave design. It has been paired with a padded, embossed backing for added visual dimension and texture in upholstery.
A38: C2032 | B38: Reyson | C38: 60 = Sand 64 = Taupe 74 = Sepia 78 = Bark 85 = Ocean | D38: 5 | E38: CH | F38: 45566 | G38: 0 | H38: 0 | I38: DR | J38: 100% Polyester | L38: N | P38: W | Q38: Reyson, a motion-friendly chenille, draws inspiration from the world of menswear and blending it with the comforting touch of chenille yarn. Its distinct weave pattern enhances the overall appeal, making it a compelling choice; combining style and affordability.
A39: C2035 | B39: Thane | C39: 31 = Linen 54 = Smoke 57 = Charcoal 78 = Chocolate | D39: 4 | E39: CH | F39: 45566 | G39: 0 | H39: 0 | I39: UR | J39: 100% Polyester | L39: P | P39: WS | Q39: Thane, is an irresistibly soft and plush printed knit base fabric. This medium pile construction delivers an unparalleled combination of comfort and performance like no other in the assortment.
A40: C2037 | B40: Tennant | C40: 51 = Porcelain 62 = Ceramic 66 = Mushroom 75 = Chestnut 78 = Otter | D40: 5 | E40: CH | F40: 45383 | G40: 0 | H40: 0 | I40: BU | J40: 100% Polyester | L40: P | P40: W | Q40: Tennant is a woven micro-denier base cloth that is extremely durable and soft. It is printed with natural leather imaging to give this new performance construction the look of hand rubbed leather.
A41: C2042 | B41: Duffey | C41: 32 = Oat 53 = Fog 60 = Dove 74 = Hazel | D41: 4 | E41: CH | F41: 45566 | G41: 0 | H41: 0 | I41: DR | J41: 100% Polyester | L41: N | P41: W | Q41: Duffy is a dobby woven fabric made with tonal, cationic textured yarns. Its small-scale weave offers subtle visual interest and a soft, yet smooth hand. The tonal coloring ensures easy coordination with other fabrics.
A42: C2043 | B42: Sheldon | C42: 57 = Granite 73 = Fawn 76 = Stone | D42: 3 | E42: CH | F42: 45566 | G42: 0 | H42: 0 | I42: DR | J42: 100% Polyester | L42: N | P42: WS | Q42: An ageless dobby woven base for all lifestyles. Created with beautiful heathered yarns and woven on a solid cotton-like dobby warp. Sheldon is a classic and very soft fabric for everyday living.
A43: C2049 | B43: Julien | C43: 18 = Spice 48 = Camel 53 = Fog 54 = Mineral | D43: 4 | E43: MU | F43: 45566 | G43: 1.1cm | H43: 1.3cm | I43: DR | J43: 100% Polyester | L43: N | P43: S | Q43: A houndstooth design, Julien is woven to emulate a tweed effect with sophisticated color variation and softly textured yarns. The pattern’s petite scaling paired with the timeless motif furthers its versatility in a variety of interior styles.
... A45: C2056 | B45: Seattle | C45: 15 = Brandy 31 = Porcelain 82 = Slate | D45: 3 | E45: MU | F45: 45566 | G45: 0 | H45: 0 | I45: DR | J45: 100% Polyester | L45: N | P45: WS | Q45: A plush, yarn dyed chenille, with the perfect amount of softness. Created with a chunky novelty heather slub chenille, which adds to the detailing and plays up the dimensional texture of the fabric.
A46: C2067 | B46: Axe | C46: 59 = Onyx 64 = Slate 74 = Mocha 86 = Midnight | D46: 4 | E46: CH | F46: 45748 | G46: 0 | H46: 0 | I46: DR | J46: 100% Polyester | L46: N | P46: W | Q46: Ideal for motion furniture, Axe, is a warp knit velvet with a subtle hobnail texture and a printed heathered effect for a refined menswear look. A woven backing enhances it's durability and stability.
A47: C2118 | B47: Cosdrew | C47: 69 = Mocha 32 = Ecru 64 = Sable 52 = Stone 56 = Steel | D47: 5 | E47: CH | F47: 46113 | G47: 0 | H47: 0 | I47: DR | J47: 100% Polyester | L47: N | P47: WS | Q47: Cosdrew features a soft chenille surface with understated woven texture. Its bonded backing adds structure and plush support, resulting in enhanced comfort when upholstered.
A48: C2119 | B48: Longmont | C48: 32 = Linen 62 = Pebble 52 = Nickel 55 = Stone | D48: 4 | E48: MU | F48: 46113 | G48: 0 | H48: 0 | I48: DR | J48: 100% Polyester | L48: P | P48: WS | Q48: Longmont is a performance-rated, piece-dyed chenille with a low pile and tightly woven structure that delivers a smooth, refined surface. The dense construction enhances durability, while a subtle two-tone effect adds depth without distracting from its clean, versatile look.
A49: C2120 | B49: San Marino | C49: 32 = Putty 61 = Fossil 53 = Shadow 86 = Indigo 29 = Jungle | D49: 5 | E49: MU | F49: 46113 | G49: 0 | H49: 0 | I49: DR | J49: 95% Polyester, 5% Linen | L49: N | P49: S | Q49: San Marino is a piece-dyed base fabric with a soft hand and elevated texture. Woven with a boucle weft and accented by a novelty linen yarn, it introduces subtle dimension and natural character. Durable and versatile, it delivers a clean, refined look suited for everyday upholstered living.
A50: C2121 | B50: Watari | C50: 71 = Flax 52 = Mineral 74 = Sandstone 67 = Flint 81 = Spa | D50: 5 | E50: MU | F50: 46113 | G50: 0 | H50: 0 | I50: DR | J50: 100% Polyester | L50: N | P50: WS | Q50: Watari features an understated broken herringbone weave that brings subtle structure and visual texture to the surface. Soft to the touch yet tailored in appearance, it offers a versatile body cloth suited for both casual and curated spaces.
A51: C2122 | B51: Taber | C51: 52 = Silver 32 = Linen 63 = Taupe 67 = Mushroom | D51: 4 | E51: MU | F51: 46113 | G51: 0 | H51: 0 | I51: DR | J51: 100% Polyester | L51: N | P51: WS | Q51: A versatile chenille with subtle texture and a soft, plush hand. The interplay of warp and weft yarns creates layered tonal depth, offering quiet dimension and an easy foundation across a range of silhouettes.
A52: D1490 | B52: i-Benavento | C52: 72 = Hemp 32 = Linen | D52: 4 | E52: MU | F52: 44652 | G52: 0 | H52: 0 | I52: DR | J52: 95% Polyester, 5% Nylon | L52: P | M52: I, PF | O52: X | P52: W | Q52: A plain weave, soft hand, and multi- colored filling yarns, merge to create a sophisticated, blended linen look in this versatile fabric. i-Benavento will retain its smooth fit and casual drape ensuring that you get the most out of your long-term furniture.
A53: D1494 | B53: Prospect | C53: 15 = Current 52 = Greystone | D53: 2 | E53: MU | F53: 42826 | G53: 7.36 | H53: 7.28 | I53: DR | J53: 100% Polyester | L53: N | P53: S | Q53: A 100% polyester jacquard featuring a color ribbon of chenille yarn intertwined with textural weave effects. Against a background of natural linen with slub yarn for extra visual and surface texture. A perfect correlate and a wonderful accent piece!
A54: D1563 | B54: i-Barnabas | C54: 32 = Oat 61 = Driftwood 63 = Mushroom 65 = Silt 52 = Fossil | D54: 5 | E54: MU | F54: 43191 | G54: 0 | H54: 0 | I54: DR | J54: 100% Polyester | L54: P | M54: I | N54: X | P54: W
A55: D1564 | B55: i-Hallandale | C55: 31 = Ivory 64 = Wicker 53 = Platinum 58 = Charcoal 87 = Admiral | D55: 5 | E55: CH | F55: 43191 | G55: 0 | H55: 0 | I55: DR | J55: 95% Polyester, 5% Nylon | K55: 100% Polyester | L55: P | M55: I, PF | N55: X | P55: W | Q55: i-Hallandale will let you create your own statement piece of furniture with this i-Clean performance fabric. Because it is i-Cleanable, you don’t have to fret over little hands or animal paws touching the rich pile of stain-resistant texture.
A56: D1604 | B56: i-Outlier | C56: 62 = Mushroom 54 = Charcoal 76 = Ash 79 = Godiva 58 = Slate | D56: 5 | E56: CH | F56: 43374 | G56: 0 | H56: 0 | I56: UR | J56: 100% Polyester | L56: P | M56: I, PF | N56: X | P56: W | Q56: A natural suede leather look, i-Outlier has a subtle grain printed texture on a soft velvet pattern. The two-tone coloration adds depth and character to this casually comfortable fabric. It instantly brings an air of relaxation to any environment.
A57: D1606 | B57: i-Halifax | C57: 62 = Antique 32 = Shell 54 = Dove 78 = Java 86 = Denim | D57: 5 | E57: CH | F57: 43374 | G57: 0 | H57: 0 | I57: UR | J57: 100% Polyester | L57: P | M57: I | N57: X | P57: W | Q57: This weft woven pile construction uses a higher pile, more casual construction, with a cross dyed yarn system, bringing two colors together in the same yarn. The look is inspired by True Grit Western Clothing.
A58: D1665 | B58: i-Tazlina | C58: 75 = Aurora 64 = Classic | D58: 2 | E58: MU | F58: 43556 | G58: 48 | H58: 36 | I58: DR | J58: 100% Polyester | L58: P | M58: I | P58: W
A59: D1693 | B59: Milo | C59: 14 = Russet 46 = Sunflower 62 = Camel 03 = Mauve 98 = Teal | D59: 5 | E59: MU | F59: 44652 | G59: 0 | H59: 0 | I59: DR | J59: 100% Polyester | L59: P | P59: WS | Q59: Milo is a beautiful full-faced chenille with a soft hand and rich, opulent colors, that bring any piece of furniture to life.
A60: D1706 | B60: Vector | C60: 84 = Waterfall 55 = Graphite 36 = Barley | D60: 3 | E60: MU | F60: 43739 | G60: 14.25 | H60: 14.125 | I60: DR | J60: 100% Polyester | L60: N | P60: WS | Q60: Vector is a contemporary design inspired by the textural shapes and patterns seen in tree bark. Lively organic shapes sit on a canvas-like, open textured ground. The harmonious color palette is on trend with the subtle hues found in nature.
A61: D1759 | B61: i-Saxton | C61: 56 = Graphite 86 = Navy 77 = Mink 64 = Marble 78 = Espresso | D61: 5 | E61: MU | F61: 43922 | G61: 0 | H61: 0 | I61: UR | J61: 100% Polyester | L61: N | M61: I | P61: W | Q61: i-Saxton is a textured cloth with added slub yarn printed on a hobnail warp knit velvet. The print gives the illusion of a woven texture, but with a soft, yet dimensional, hand. This fabric is made of 100% polyester and is stain and moisture resistant making it easy to clean.
A62: D1806 | B62: i-Catalyst | C62: 32 = Sand 54 = Platinum 57 = Ash 78 = Earth | D62: 4 | E62: MU | F62: 44287 | G62: 0 | H62: 0 | I62: UR | J62: 100% Polyester | L62: P | M62: I, PF | P62: W | Q62: This upscale leather look, i-Catalyst, was designed to have a luxurious soft hand giving it the perfect combination of comfort and texture. An allover print on a textured warp knit velvet creates this multi-dimensional look that is soft and casual. When you think suede, you imagine a soft leather that lends well to earthy spaces and natural interiors. Catalyst ITW secures that look with the patterned overprint and is further enhanced by the lush hand of a warp knit velvet base. Rated Heavy Duty for wear, this performance i-Clean fabric, i-Catalyst, makes it perfect for any style of furniture – from a motion recliner to a sectional to a classic club chair.
A63: D1807 | B63: Fairfax | C63: 32 = Oyster 53 = Ash 57 = Iron 64 = Almond 74 = Mocha 86 = Eclipse | D63: 6 | E63: MU | F63: 44287 | G63: 0.25 | H63: 0.5 | I63: DR | J63: 100% Polyester | L63: P | P63: WS | Q63: Fairfax is a contemperary herringbone weave featuring a subtle stria texture and wonderfully soft chenille yarn. Perfect for everything from sofas to accent chairs, Fairfax provides a ton of versatility!
A64: D1825 | B64: i-Raven Crest | C64: 35 = Pebble 58 = Ash 73 = Mushroom 74 = Chestnut | D64: 4 | E64: MU | F64: 44287 | G64: 0 | H64: 0 | I64: BU | J64: 100% Polyester | L64: P | M64: I, PF | P64: W | Q64: i-Raven Crest is a soft hand, lived-in polyurethane, printed woven suede leather-look. The casualness of this pattern allows it to work well on motion furniture. The muted coloration also adds both depth and character to this casually, comfortable fabric. Because it is an i-Clean performance fabric, i-Raven Crest offers the cleanability that customers all love in today’s stay-at-home world. Rated heavy duty, this is perfect for families! Made of 100% polyester, i-Raven Crest is extremely durable making it a tremendous, down home value.
A65: D1855 | B65: i-Rivers | C65: 52 = Platinum 53 = Fossil 58 = Twilight 59 = Smoke 64 = Sand 75 = Camel | D65: 6 | E65: MU | F65: 44470 | G65: 0 | H65: 0 | I65: BU | J65: 100% Polyester | K65: 58% Polyester, 35% Cotton, 7% Rayon | L65: N | M65: I | N65: X | P65: W | Q65: i-Rivers captures the relaxed look of suede with a soft knit construction and subtle tonal depth. Designed for reclining furniture, it offers lasting durability with i-Clean technology to help resist spills.
A66: D1905 | B66: York | C66: 72 = Barley 58 = Granite 54 = Quarry 74 = Bisque 31 = Cream | D66: 5 | E66: MU | F66: 44652 | G66: 0 | H66: 0 | I66: DR | J66: 100% Polyester | L66: N | P66: W | Q66: A prevalent design trend is all about texture and the exploration of achieving an added tactile quality to your home environment. The elevated look of York has a beautiful come and go slub yarn for that textural interest that delivers dimension and depth. A refined softness of the chenille hand appeals directly to the aesthetic sense and creates a sanctuary in your home. Not only is it beautiful, but York, made of 100% polyester, is a durable fabric that will let you live, create, and play in your home without any worries.
A67: D1919 | B67: Florentino | C67: 82 = Sky 57 = Onyx 34 = Linen | D67: 3 | E67: MU | F67: 44835 | G67: 13.86 | H67: 13.98 | I67: DR | J67: 100% Polyester | L67: N | P67: W | Q67: With its intricate floral pattern, Florentino provides a look that’s timeless. Vines, leaves and flowers meander in hushed tones over this soft, but sturdy cloth. It’s an elegant weave that will provide comfort and enchantment for years to come.
A68: D1970 | B68: Marteon | C68: 34=Natural 52=Whisper 56=Onyx 66=Porcini 96=Ocean | D68: 5 | E68: MU | F68: 45017 | G68: 0 | H68: 0 | I68: DR | J68: 50% Polyester, 50% Acrylic | L68: P | P68: WS | Q68: Chunky weave with a soft tonal blend and a boucle yarn. this durable, multi-tonal weave is in the texture created through a mix of bouclé yarns on warp & weft.
A69: D1988 | B69: Copenhagen | C69: 49 = Caramel 54 = Bluestone 72 = Driftwood | D69: 3 | E69: MU | F69: 45200 | G69: 36 | H69: 36.7 | I69: PS | J69: 100% Polyester | L69: P | P69: WS | Q69: This performance plaid is a fresh take on a classic check differentiated through scale, warm livable colorations and a chunky blend of yarns in the construction’s warp and weft.
A70: D2009 | B70: Promise | C70: 31 = Ecru 46 = Gold 52 = Oyster 59 = Thunder 72 = Khaki 83 = Powder | D70: 6 | E70: MU | F70: 45383 | G70: 0 | H70: 0 | I70: DR | J70: 100% Polyester | L70: N | P70: WS | Q70: A soft, casual woven constructed of yarn-dyed boucle. Both textural and refined, Promise provides an organic look and feel through it's dimensional and tonal novelty yarns.
A71: D2010 | B71: i-Rene | C71: 14 = Nutmeg 19 = Spice 25 = Moss 32 = Oat 52 = Ash 65 = Mushroom 81 = Bluestone | D71: 7 | E71: MU | F71: 45383 | G71: 0 | H71: 0 | I71: DR | J71: 100% Polyester | L71: N | M71: I | P71: WS | Q71: i-Rene uses finely textured polyester filament yarns to create a versatile, lifestyle plain woven fabric. It's soft hand and heathered palette give the fabric it's casual feel while paired with the cleanability of i-clean.
A72: D2013 | B72: Kerr | C72: 31 = Linen 54 = Tusk 95 = Teal | D72: 3 | E72: MU | F72: 45383 | G72: 0 | H72: 0 | I72: DR | J72: 100% Polyester | L72: N | P72: S | Q72: Kerr features a novelty space-dyed boucle in both the warp and fill to create a beautiful tweed fabric that has subtle color movement and lots of depth. The texture of this dimensional action plain will beautifully lend itself to any interior style.
A73: D2016 | B73: Coast | C73: 12 = Coral 52 = Moon 93 = Aqua | D73: 3 | E73: MU | F73: 45383 | G73: 28.46 | H73: 28.35 | I73: DR | J73: 100% Polyester | L73: N | P73: W | Q73: Coast is feature pattern that portrays various ocean coral varieties within a clean and modern woven design. The choice of a simple, two-color palette and delicate rendering, makes this pattern suitable for coastal spaces of any design style.
A74: D2027 | B74: i-Weekend | C74: 32 = Buff 51 = Dove Grey 67 = Sable 75 = Chestnut 98 = Ocean | D74: 5 | E74: MU | F74: 45383 | G74: 0 | H74: 0 | I74: UR | J74: 100% Polyester | L74: P | M74: I, PF | P74: W | Q74: i-Weekend is a plush, warp knit velvet with a refined pile and exquisitely soft hand. The fabric is piece dyed and overprinted to achieve its leather grain look and rich color. It is finished with a generous fleece backing which round out the fabric’s body and hand.
A75: D2030 | B75: Howell | C75: 32 = Sand 34 = Granite 53 = Ash | D75: 3 | E75: MU | F75: 45383 | G75: 0 | H75: 0 | I75: DR | J75: 73% Polyester, 27% Acrylic | L75: N | P75: W | Q75: A timeless twill weave, Howell uses unique novelty yarns to create a subtle blend of colors and a soft hand. This versatile base will effortlessly complement any motion or stationary frame.
A76: D2031 | B76: Lullaby | C76: 33 = Porcelain 58 = Steel 65 = Taupe 73 = Burlap 79 = Mink 93 = Mist | D76: 6 | E76: MU | F76: 45383 | G76: 0 | H76: 0 | I76: UR | J76: 100% Polyester | L76: P | P76: WS | Q76: Lullaby is a highly durable, performance fabric. It's fine, dense, 100% polyester chenille balances performance with a super soft hand and a contrasting stria weave creates texture and subtle visual interest.
A77: D2034 | B77: Doritt | C77: 32 = Sand 36 = Birch 54 = Charcoal 75 = Suede 78 = Teak | D77: 5 | E77: CH | F77: 45566 | G77: 0 | H77: 0 | I77: DR | J77: 100% Polyester | L77: P | P77: W | Q77: A dobby woven textured plain made with a blend of chenille and spun slub yarns. The tonal chenille and subtly irregular slub yarn combination create a look that is both soft to the touch and exhibits a more artisanal depth of color. The non-woven backing offers enhanced structure and stability.
A78: D2038 | B78: Picchu | C78: 30 = Snow 59 = Carbon 62 = Flax 72 = Brown Sugar 78 = Cocoa 85 = Navy | D78: 6 | E78: MU | F78: 45566 | G78: 0.063 | H78: 0.063 | I78: DR | J78: 100% Olefin | L78: P | M78: W*B | P78: W*B | Q78: Engineered with cleanability, Picchu, is a new bleach cleanable lifestyle plain. The expert combination of a heathered warp against solid fill yarns creates a softened, casual textile that will show off the subtle lines of upholstery.
A79: D2054 | B79: Amari | C79: 18 = Sienna 29 = Palmetto 31 - Natural 87 = Indigo | D79: 4 | E79: MU | F79: 45566 | G79: 0 | H79: 0 | I79: DR | J79: 100% Polyester | L79: N | P79: S | Q79: Amari is a soft, textured pattern featuring chenille yarns juxtaposed with a dry, nubby boucle. A dynamic weave effect is used to create visual interest, resulting in textile that is suited to any interior aesthetic.
A80: D2065 | B80: Magnolia | C80: 17 = Chestnut 24 = Sage | D80: 2 | E80: MU | F80: 45566 | G80: 0 | H80: 0 | I80: UR | J80: 100% Polyester | L80: P | P80: WS | Q80: A sumptuously soft and dimensional piece dyed corduroy body cloth, Magnolia is woven up the roll on a full count fine warp with a durable chenille weft and heavy stuffer pick to create loft.
A81: D2066 | B81: i-Kudos | C81: 59 = Lead 61 = Oyster 67 = Tawny 77 = Mocha 80 = Powder | D81: 5 | E81: MU | F81: 45566 | G81: 0 | H81: 0 | I81: UR | J81: 100% Polyester | L81: P | M81: I, PF | P81: W | Q81: A pet-friendly base cloth, i-Kudos pairs performance with cleanability. It is a warp knitted and has a subtle pile, giving it a velvet-like hand. The pattern is pieced dyed and then over printed to provide visual interest and is finished with a fleece backing for added softness in upholstery.
A82: D2068 | B82: i-Beverley | C82: 33 = Bone 60 = Pebble 71 = Mineral 76 = Coffee 93 = Ocean | D82: 5 | E82: CH | F82: 45748 | G82: 0 | H82: 0 | I82: DR | J82: 100% Polyester | L82: N | M82: I | P82: WS | Q82: i-Beverley features a dobby weave with a subtle tone-on-tone design, balancing texture and versatility. A blend of chenille and filament yarns adds dimension, while the i-Clean® finish provides stain resistance for easy maintenance. Durable and stylish, it’s ideal for both motion and stationary furniture.
A83: D2071 | B83: i-Rockport | C83: 19 = Salsa 31 = Linen 52 = Mushroom 54 = Grey 78 = Brownstone | D83: 5 | E83: MU | F83: 45748 | G83: 0 | H83: 0 | I83: UR | J83: 85% Polyester 12% Cotton, 3% Rayon | L83: N | M83: I | P83: WS | Q83: A durable, soft fabric, yarn-dye woven from finely spun yarns that give it a natural texture. Its unique weave structure enhances strength and stability, while a melange chenille yarn in the weft adds depth and subtle color variation. The result is a versatile fabric with a refined, organic look, ideal for upholstery and interiors.
A84: D2072 | B84: i-Nolina | C84: 31 = Natural 51 = Horizon 52 = Flint 57 = Graphite 75 = Toast | D84: 5 | E84: MU | F84: 45748 | G84: 0 | H84: 0 | I84: DR | J84: 100% Polyester | L84: N | M84: I | P84: W | Q84: A piece-dyed fabric with a basket weave structure, woven from fine chenille yarns for a soft, textured feel with a subtle bi-color effect. A filament warp adds stability, while a nonwoven backing provides weight and a crisp, tailored finish. Finished with i-Clean®performance technology, it's durable construction and refined look make it a versatile choice for upholstery.
A85: D2074 | B85: Gail | C85: 32 = Ecru 51 = Oyster 60 = Porcelain 78 = Fossil 80 = Lotus 86 = Navy | D85: 6 | E85: MU | F85: 45748 | G85: 0 | H85: 0 | I85: UR | J85: 100% Polyester | L85: P | M85: W*B | P85: W*B | Q85: Exclusively created for La-Z-Boy, this classic basket weave construction adds depth and richness to the color, while a two-toned novelty chenille yarn woven in both the weft and warp enhances its plush softness. Made from 100% solution-dyed yarns, it offers exceptional durability and easy cleanability with soap and water or diluted bleach for tough stains.
A86: D2075 | B86: Galloway | C86: 78 = Chocolate 65 = Shitake 38 = Pebble 86 = Navy | D86: 4 | E86: MU | F86: 45931 | G86: 0 | H86: 0 | I86: UR | J86: 100% Polyester | L86: N | P86: WS | Q86: Galloway combines a self-textured knit base with the subtle coloration of its print effect to create a tweed-like look. The result is a versatile fabric with natural texture and understated style.
A87: D2076 | B87: Kenly | C87: 38 = Sisal | D87: 1 | E87: MU | F87: 45931 | G87: 0.063 | H87: 0.063 | I87: DR | J87: 100% Olefin | L87: N | M87: W*B | P87: W*B | Q87: A chunky basketweave plain with a multi-yarn construction that showcases novelty yarns for unique depth and visual interest. Its natural, sisal-look paired with bleach-cleanable performance makes it a stylish yet practical choice.
A88: D2086 | B88: Spring Valley | C88: 06 = Blossom 31 = Muslin 75 = Jewel | D88: 3 | E88: MU | F88: 45748 | G88: 27 | H88: 24.89 | I88: DR | J88: 93% Polyester, 7% Linen | L88: N | P88: W | Q88: A blend of linen and polyester, Spring Valley, is a soft watercolor floral print featuring large, delicate floral shapes reminiscent of classic impressionist paintings. Its subtle, flowing design adds warmth and elegance to any space. Available in three versatile colorways to complement a range of interiors.
A89: D2090 | B89: Penelope | C89: 09 = Crimson | D89: 1 | E89: MU | F89: 45748 | G89: 2.9c | H89: 2.9c | I89: UR | J89: 52% Polyester, 48% Acrylic | L89: N | P89: W | Q89: Penelope is a sophisticated Jacquard fabric that combines a soft, luxurious texture with a modern chevron design. Crafted with chenille yarns in the weft and novelty yarns in the warp, it offers a perfect balance of style, function, and tactile softness.
A90: D2092 | B90: Ross | C90: 25 = Moss 32 = Natural 52 = Pebble 59 = Smoke 61 = Linen | D90: 5 | E90: MU | F90: 45748 | G90: 4.21 | H90: 12.6 | I90: UR | J90: 100% Polyester | L90: N | M90: W*B | P90: W*B | Q90: Ross features a classic weave that creates a versatile and reliable foundation for any space. Its plush softness and subtle texture come from a chenille yarn woven in the weft over a novelty multi-color warp, adding depth without overwhelming. Made from 100% solution-dyed yarns, it offers exceptional durability and easy cleanability with soap and water or diluted bleach for tough stains, making it a practical yet refined choice for everyday comfort.
A91: D2093 | B91: Artisia | C91: 76 = Truffle 74 = Dusty Rose 55 = Mushroom 51 = Silver 75 = Cappuccino 24 = Leaf 31 = Vellum | D91: 7 | E91: MU | F91: 45931 | G91: 0 | H91: 0 | I91: DR | J91: 97% Polyester, 3% Linen | L91: N | P91: S | Q91: Subtly textured, Artisia is a linen like fabric with a touch of chenille with a soft and natural hand Refined yet relaxed, Artisia is designed for the way we live, entertain, work, and play.
A92: D2094 | B92: Crete | C92: 78 = Chili 48 = Copper | D92: 2 | E92: MU | F92: 45931 | G92: 0 | H92: 0 | I92: UR | J92: 100% Polyester | L92: N | P92: S | Q92: A premium lifestyle fabric, Crete boasts rich texture created by the perfect blend of a fancy warp and plush chenille filling delivering both visual depth and a soft, inviting hand.
A93: D2095 | B93: Crocker | C93: 55 = Smoke 74 = Hazel 86 = Midnight 51 = Dove Grey 62 = Marble | D93: 5 | E93: MU | F93: 45931 | G93: 0 | H93: 0 | I93: DR | J93: 72% Polyester, 26% Acrylic, 2% Rayon | L93: N | P93: WS | Q93: Crocker is woven with multicolor chenille on a boucle warp, giving it a soft hand and rich texture. The interplay of these yarns adds depth and dimension, making it both stylish, inviting and perfect for everyday living.
A94: D2096 | B94: Defender | C94: 69 = Latte 31 = Bone 51 = Dove 64 = Linen | D94: 4 | E94: MU | F94: 45931 | G94: 0 | H94: 0 | I94: DR | J94: 100% Polyester | L94: P | M94: W*B | P94: W*B | Q94: A true essential, Defender is dobby woven on a novelty textured warp to create subtle surface diminsion and an inviting hand. Stain resistant and diluted bleach for the toughest stains make it an ideal choice for balancing everyday life with comfort and style.
A95: D2097 | B95: Donatello | C95: 16 = Harvest 27 = Forest 85 = Bluebird 12 = Canyon 32 = Linen | D95: 5 | E95: MU | F95: 45931 | G95: 0 | H95: 0 | I95: DR | J95: 100% Polyester | L95: M | P95: WS | Q95: A richly textural fabric woven on a dobby loom with a blend of boucle and chenille novelty yarns. Its interplay of color and texture creates a look that feels both modern and classic, offered in a versatile palette ranging from calming neutrals to nature-inspired hues.
A96: D2098 | B96: Gabby | C96: 10 = Gold 31 = Ecru 80 = Mist | D96: 3 | E96: MU | F96: 45931 | G96: 0 | H96: 0.87 | I96: NP | J96: 89% Polyester; 8% Acrylic; 3% Wool | L96: N | P96: WS | Q96: Gabby is a richly textural woven stripe that celebrates simple design elevated by craft. Heathered boucle yarns paired with a cotton-like warp create soft dimension and a layered stripe with casual yet refined appeal.
A97: D2099 | B97: i-Favorite | C97: 33 = Oyster 53 = Pewter 65 = Driftwood 31 = Parchment | D97: 4 | E97: MU | F97: 45931 | G97: 0 | H97: 0 | I97: DR | J97: 100% Polyester | L97: P | M97: I, PF | P97: S | Q97: i-Favorite is a piece-dyed woven with a soft, cotton-velvet-like hand and a heathered warp that adds subtle surface interest. Casual and comfortable, it features iClean performance for a pet-friendly fabric that’s as practical as it is inviting.
A98: D2100 | B98: i-George | C98: 62 = Taupe 52 = Shadow 31 = Sugar 70 = Sand 54 = Grey | D98: 5 | E98: MU | F98: 45931 | G98: 0 | H98: 0 | I98: DR | J98: 100% Polyester | L98: P | M98: I | P98: WS | Q98: Designed for modern living, i-George is a performance upholstery fabric that combines effortless style with everyday practicality. Woven with a very soft chenille weft on a novelty dobby print warp, the fabric offers a dimensional texture and an inviting hand that feels casual yet refined.
A99: D2101 | B99: Novan | C99: 62 = Flax 74 = Twine 37 = Porcelain 55 = Pebble | D99: 4 | E99: MU | F99: 45931 | G99: 0 | H99: 0 | I99: DR | J99: 100% Polyester | L99: N | P99: WS | Q99: Novan is a soft, timeless texture woven on a dobby loom with a novelty warp and tweed-heathered boucle weft. Balanced and versatile, its neutral palette layers seamlessly into interiors from modern to transitional to relaxed family spaces.
A100: D2102 | B100: Picasso | C100: 11 = Desert 61 = Flax 90 = Spa | D100: 3 | E100: MU | F100: 45931 | G100: 28.5 | H100: 19.7 | I100: UR | J100: 100% Polyester | L100: N | P100: WS | Q100: Artistic and expressive, Picasso jacquard design brings painterly sophistication into the home. Its motif features subtle brushstrokes forming abstract, distorted diamond shapes, creating a sense of movement and layered artistry.
A101: D2104 | B101: Shoreline | C101: 90 = Mist 32 = Buff 86 = Jeans 46 = Gold | D101: 4 | E101: MU | F101: 45931 | G101: 28.4 | H101: 16.7 | I101: DR | J101: 97% Polyester; 3% Acrylic | L101: N | P101: WS | Q101: Shoreline reflects the calm of sunlit horizons and sea-washed tones, bringing a touch of coastal elegance to the home. Soft to the touch yet crafted for durability, it offers family-friendly performance that makes it ideal for accent chairs, pillows, and statement upholstery alike.
A102: D2106 | B102: Tonda | C102: 63 = Flax 77 = Umber 56 = Storm 86 = Indigo 59 = Graphite | D102: 5 | E102: CH | F102: 46113 | G102: 0 | H102: 0 | I102: UR | J102: 100% Polyester | L102: P | P102: W | Q102: Tonda features a streamlined knit construction with a smooth, cushioned hand and resilient performance. Its subtle embossed surface and heathered tonal effect create quiet depth with a clean, modern sensibility. Designed for restorative spaces, it delivers comfort with intentional restraint.
A103: D2107 | B103: Westcott | C103: 65 = Quarry 31 = Natural 69 = Brindle 58 = Granite | D103: 4 | E103: CH | F103: 45931 | G103: 0 | H103: 0 | I103: DR | J103: 100% Polyester | L103: N | P103: W | Q103: Westcott combines fine-scale novelty and chenille yarns to create a plain that feels soft and organic. Tonal color variations add depth and dimension, giving it a natural, inviting look that works across a range of styles.
...

Sheet MASTER LEATHER
A1: All Active Leather SKU's as of April 2026 Market
A3: Leather Descriptions/Dot | K3: Product Line | Q3: Specialty Leather Descriptions
A4: Autentic (Tan) | B4: = A Pure, transparent dyes enhance natural markings such as wrinkles, scars and brands in each Authentic or Aniline hide. The dramatic color variations created are prized as hallmarks of quality and give each piece a distinctive look all its own. All Authentic leathers have a special protective topcoat that maintains the beauty and integrity of the natural characteristics of the hide. | K4: Select Leather Reclining | L4: = SLR Married leather with urethane/vinyl match on specific motion frames (Previously Select Motion) | Q4: A = Antimicrobial
Q5: C = Crypton
K6: Select Leather Stationary | L6: = SLS Maried leather with urethane/vinyl match on specific stationary frames (Previously Select Stationary) | Q6: I = iClean
Q8: Pillow Program
A9: Performance (Teal) | B9: =P The consistent overall color and subtle markings of Performance or protected leathers are created by a variety of techniques, such as embossing, corrective techniques and protective coatings, to improve resistance to soil and enhance their natural beauty. | K9: Custom Leather Match | L9: = CLM Custom Leather with urethane match available on select frames (Previously Custom Leather) | Q9: Pillows are NOT available in LL, LS, LM, RL, BU or UE cap codes
K11: Custom Leather Plus | L11: = CLP Custom Leather available on most frames | Q11: Key:
K12: Specialty Leather | L12: = SL Specialty Leather collection - Antimicrobial, Aniline and iClean | Q12: Immediate Drop
A13: Nubuck (Blue) | B13: =N Nubuck leathers are infused with pure, transparent dyes to give them subtle color variations without masking the natural character of the hide such as wrinkles, scars, brands, and other hallmarks of the trail. The result is a unique beauty that’s perfectly at home with today’s way of living. | Q13: Phase Outs
Q14: New Phase Outs
Q15: April 2026 Drops
A17: Series Number | B17: Pattern Name | C17: Product Line | D17: Intro Date | E17: Colors | F17: P/S=Postage Stamp, 12x12 | H17: Leather Description/ Dot | J17: Specialty Leather | K17: Cleaning Code | L17: Married Style(s) | O17: Notes | R17: Description(s)
A18: FL1907 | B18: Aline | C18: SL | D18: 44652 | E18: 54 = Light Grey 36 = Stonewash 84 = Haze 87 = Dark Blue 58 = Storm 77 = Chocolate | F18: 12x12, P/S | H18: A | J18: A | K18: L | R18: These semi-aniline hides are aniline dyed and then finished with a special feel agent added in the retannage to give the hides a superior touch. Because the feel agent is in the retannage it will not wear off over time. Special Effect: Along with the luxurious touch of Aline, a subtle two tone is added in the end to add to the visual depth and interest of this leather. The color pallet ranges from traditional colors to transitional to contemporary giving this article universal appeal across all types of styles. This tannage also provides an antimicrobial element due to special finishing. Please reference the marketing portion of our cover presentation for more detail!
A19: HL1906 | B19: Ankur | C19: SL | D19: 44652 | E19: 77 = Brown 73 = Oak 75 = Saddle 79 = Walnut | F19: 12x12, P/S | H19: A | J19: A | K19: L | R19: The dyeing process for Ankur is carried out in drums by means of aniline colorants which ensure a very high degree of light-fastness. High quality fats are used to maintain and enhance the natural softness of the hide. The hand of Ankur is achieved through a specific type of re-tanning with a long period of drum milling. Special Effect: After finishing, a special effect roller adds a two tone effect that simulates a genuine hand rubbed effect to the leather. This tannage also provides an antimicrobial element due to special finishing. Please reference the marketing portion of our cover presentation for more detail!
A20: FL1932 | B20: Athena | C20: SL | D20: 44835 | E20: 77 = Brown 63 = Ash 08 = Burgundy 55 = Grey 84 = Granite Grey 73 = Oak 59 = Carbon | F20: 12x12, P/S | H20: P | J20: I | K20: L | R20: Athena is elegant and sophisticated and has a soft fit that adapts very well to luxury furniture, with an uncluttered but rustic appearance. Athena brings an unprecedented softness using waxy technology. The more apparent grooves allow greater contrast between low and high relief, bringing a special shine. Being the first iClean™ leather, your environment will be luxurious and protected with Athena.
A21: DL2130 | B21: Atlantis | C21: CLP | D21: 46113 | E21: 86 = Marine 59 = Ash 73 = Russet 77 = Dark Brown | F21: P/S | H21: A | K21: L | R21: Atlantis is a 0.9–1.1mm semi-aniline leather featuring a natural grain with a light emboss. Its subtle two-tone effect and creamy hand create a refined surface with a rich, full-bodied feel. Atlantis brings together the heritage of leather with performance suited for modern living.
A22: LB2136 | B22: Bellingham | C22: SLR | D22: 46113 | E22: 79 = Moreno 59 = Coal | F22: 12x12 | H22: A | K22: L | L22: 826 Sammy | R22: A semi-aniline leather, Bellingham has a smooth, supple hand and refined medium sheen. At 1.0–1.2mm thickness, it showcases natural grain variation, while a subtle two-tone effect adds depth to the surface. The result is a polished, authentic leather with timeless character.
A23: LB1851 | B23: Camaraderie | C23: SLR | D23: 44652 | E23: 58 = Pewter 75 = Oak | F23: 12x12 | H23: P | K23: L | L23: 781 Emmons | R23: Comaraderie is a pigmented leather with a two tone sauvage effect and thickness of 1.0-1.2MM. This tannage features a very soft hand and excellent clarity in the finish.
A24: LB2141 | B24: Chic | C24: SLR | D24: 46113 | E24: 76 = Pecan 59 = Slate | F24: 12x12 | H24: A | K24: L | L24: A86 Ovation | R24: This semi-aniline leather features a natural grain with a distinctive oil pull-up effect, revealing beautiful highs and lows that create striking tonal movement. At 1.0–1.2mm thick with a fully protected finish, it offers lasting durability while maintaining a soft, supple hand. The result is a rich, dimensional leather that delivers elevated depth with a clean, contemporary edge.
A25: LB2062 | B25: Clifton | C25: SLR | D25: 45566 | E25: 19 = Chestnut 29 = Olive 78 = Walnut 79 = Dark Chocolate | F25: 12x12 | H25: A | K25: L | L25: 582 Maverick - Colors 78 & 79 717 Fulton - Colors 78 & 79 802 Cassian - Colors 78 & 79 810 Quinault - Colors 19 & 29 | R25: This article is a semi aniline with a natural grain and a thickness of 1.0-1.2mm. Clifton, hand rubbed at the tannery, it’s two-tone is rich in both color and depth and has medium sheen.
A26: BL9810 | B26: Cozy Match | C26: CLM | D26: 43922 | E26: 07 = Wine 09 = Pomegranate 31 = Oyster 36 = Marshmallow 50 = Licorice 51 = Dusty 54 = Putty 56 = Grey 76 = Walnut 78 = Tobacco 87 = Blueberry 90 = Seafoam 98 = Arctic Blue | F26: P/S | H26: P | K26: L | R26: Cozy Match is a soft, transparent, protected leather with a subtle two-tone effect that enhances the look of the color giving it depth and clarity.
A27: LB1590 | B27: Cranbrook | C27: SLR | D27: 43191 | E27: 58 = Shitake 79 = Chestnut | F27: 12x12 | H27: A | K27: L | L27: 519 Astor - Colors 58 & 79 | R27: Cranbrook is a semi-aniline dyed leather presenting a natural pebble grain appearance while showcasing a distinctive depth and clarity of color. Due to the higher quality of rawhide selection and supple characteristics, as well as a heavier gauge hand, this article of leather tailors extremely well.
A28: LB2063 | B28: Dean | C28: SLR | D28: 45566 | E28: 76 = Chestnut 79 = Shitake | F28: 12x12 | H28: A | K28: L | L28: 782 Kells 811 Acadia | O28: 811 - HG Top Stitching | R28: A semi-aniline, natural grain leather, Dean, has a thickness of 1.0-1.2mm providing nice drape and a soft, supple hand. Additionally, the leather is finished with a subtle, two-tone effect and an understated sheen in the topcoat.
A29: LB2063 | B29: Dean | C29: SLR | D29: 45767 | E29: 32 = Oyster 57 = Blue Grey 77 = Walnut | F29: 12x12 | H29: A | K29: L | L29: 800 Palmer 820 Norton | R29: A semi-aniline, natural grain leather, Dean, has a thickness of 1.0-1.2mm providing nice drape and a soft, supple hand. Additionally, the leather is finished with a subtle, two-tone effect and an understated sheen in the topcoat.
A30: LB1601 | B30: Delray | C30: SLR | D30: 43556 | E30: 75 = Harvest 79 = Dark Chocolate | F30: 12x12 | H30: A | K30: L | L30: 777 Randell | R30: Delray is the semi-aniline leather with natural grain and true hand-rub look. It has a very good hand and depth of color. The thickness of the leather is 1.0-1.2mm.
A31: LB1804 | B31: Elite | C31: SLR | D31: 44287 | E31: 74 = Cognac 59 = Charcoal 32 = Ice | F31: 12x12 | H31: P | K31: L | L31: 787 Lennon Recliner - Colors 32 & 59 762 Neo - Colors 59 & 74 | O31: 762 Neo - HG Top Stitching | R31: A beautiful semi aniline natural grain leather with a thickness of 1.1 – 1.2mm and slight savauge effects. This article has a super soft hand and normal sheen.
A32: LB2061 | B32: Gambit | C32: SLR | D32: 45566 | E32: 32 = Oyster 50 = Onyx 59 = Graphite 75 = Stone 78 = Otter | F32: 12x12 | H32: A | K32: L | L32: 747 Finley - Colors 50, 75 & 78 765 Rowan - Colors 32, 59 & 78 803 Cade - Colors 32 & 75 | R32: Gambit is a full-bodied semi-aniline with a medium grain and a thickness of 1.2-1.4mm. This article has a buttery, soft hand and is a semi-matte look with a gentle two-tone effect
A33: LB1728 | B33: Goshen | C33: SLR | D33: 43922 | E33: 56 = Grey 78 = Chestnut | F33: 12x12 | H33: A | K33: L | L33: 502 Joshua | O33: Comes standard with single-needle topstitching on the arms. | R33: Goshen features a two-tone color effect with a soft and waxy appearance, using a corrected grain, being as close as possible to semi aniline. The hand, feel and softness make this a comfortable and luxurious leather.
A34: FL1963 | B34: Gramado | C34: CLP | D34: 45017 | E34: 57 = Coal 73 = Russet 76 = Cedar 79 = Coffee | F34: P/S | H34: A | K34: L | O34: ```````` | R34: Transitional/Traditional This classic Semi-Aniline leather hits all the high notes – it’s creamy soft and smooth with an understated natural grain and a popular two-tone kela effect. With deep rich colors and a medium sheen that adds brightness and radiance, Gramado is elegant and versatile. It works well with any type of furniture including motion and recliners and has been designed for active households. Color palette/special texture Available in classic shades, Gramado features a subtle natural grain and soft, creamy hand. Natural markings have been minimized but will remain visible. Techno facts Hides are selected, cut thinner, and then tanned and dyed using state-of-the-art methods. Hides are lightly corrected, colored, and then overprinted with a kela effect. Then hides are embossed with a natural grain. A medium sheen topcoat is applied to finish the look and help resist everyday stains and spills.
A35: FL2026/LB2026 | B35: Grandview | C35: CLP SLR | D35: 45383 | E35: 51 = Dove Grey 59 = Otter 75 = Chestnut 98 = Ocean | F35: P/S, 12x12 | H35: A | K35: L | L35: 712 Sparrow - Colors 51, 59 & 75 | O35: Custom Leather - all colors Select Reclining - 51, 59 & 75 | R35: A semi-aniline natural grain leather, rich in color, with a distinct matte finish and sueded hand which emulates that of a nubuck. Grandview is drum dyed, buffed, milled, ironed and protected with a topcoat to preserve the look, hand and color of the article.
A36: FL1523 | B36: Great Smokies | C36: CLP | D36: 42826 | E36: 52 = Tin 57 = Smoke 73 = Gingerbread 75 = Pecan 79 = Chocolate | F36: P/S | H36: A | K36: L | R36: Great Smokies is corrected and embossed, with a waxy, soft hand. The slight crackled finish is achieved by tumbling, and the visual depth and two-tone coloration are courtesy of roller-coating. A medium-sheen topcoat finishes the look and helps protect against everyday stains and spills. Finally, hides are hot ironed for smoothness.
A37: LB2112 | B37: Highbrow | C37: SLR | D37: 45931 | E37: 75 = Mocha 78 = Mineral 58 = Blue Grey | F37: 12x12 | H37: A | K37: L | L37: 755 Dorian - Colors 75 & 78 807 Baron - Colors 58, 75 & 78 | O37: 807 Baron - HG Top Stitching | R37: Highbrow, a semi-aniline embodies timeless luxury. Showcasing a natural grain to hightlight the authentic beauty of the hide, the article has a luxuriously soft hand, exceptional drtage with just the right touch of sheen. A 1.1-1.3MM thickness ensures durability without sacrificing elegance.
A38: LB2112 | B38: Highbrow | C38: SLR | D38: 46113 | E38: 76 = Chestnut 68 = Slate | F38: 12x12 | H38: A | K38: L | L38: 757 Apollo - Colors 68 & 76 | O38: 757 Apollo - Decorative HG Top Stitching | R38: Highbrow, a semi-aniline embodies timeless luxury. Showcasing a natural grain to hightlight the authentic beauty of the hide, the article has a luxuriously soft hand, exceptional drtage with just the right touch of sheen. A 1.1-1.3MM thickness ensures durability without sacrificing elegance.
A39: LB1727 | B39: Intermingle | C39: SLR | D39: 43922 | E39: 55 = Grey 79 = Walnut | F39: 12x12 | H39: A | K39: L | L39: 724 Trouper | O39: Comes standard with tonal heavy-gauge single-needle topstitching on the arms, backs, chaises and footrests. | R39: Intermingle is semi-aniline leather, which is very slightly corrected and embossed. The printing, spraying, tipping and tumbling processes are used to achieve the look, color, hand and depth.
A40: DL1962 | B40: Jazz | C40: SL | D40: 45017 | E40: 36=Moonbeam 58=Charcoal 75=Cinnamon 78=Coffee 86=Midnight Blue | F40: 12x12, P/S | H40: P | J40: I | K40: L
A41: FL2003 | B41: Jesi | C41: CLP | D41: 45200 | E41: 07 = Rouge 59 = Otter 63 = Stone 72 = Barley 75 = Khaki 77 = Sepia | F41: P/S | H41: A | K41: L | R41: A semi-aniline, Jesi, has a timeless, natural aesthetic with subtle two-tone aniline-like characteristics that are created through innovative finishing techniques and rounded out with a soft, supple hand.
A42: LB1849 | B42: Lota | C42: SLR | D42: 44470 | E42: 64 = Pebble 78 = Espresso | F42: 12x12 | H42: P | K42: L | L42: LB1849 Lota on 786 Liam Recliner - Phase Out LB1849 Lota on 786 Liam Motion - Dropped | R42: Lota is a soft pigmented performance leather that is perfect for relaxing. The overall even surface of the leather, along with the clean, saturated colors, create an appealing high-end leather look.
A43: FL2078 | B43: Manchester | C43: SL | D43: 45767 | E43: 25 = Olive 29 = Envy 31 = Ivory 49 = Tan 76 = Toffee 86 = Midnight | F43: 12x12, P/S | H43: A | J43: I | K43: L | R43: Manchester features a stippled grain that mimics the look of antiqued leather, while its water-based finish adds protection and a subtle sheen. Offering the aesthetics of wax pull-up leather without the high price or finish sensitivity, this semi-aniline leather is protected with i-Clean® technology, ensuring resistance to liquids and stains for up to three years.
A44: BL2117 | B44: Majestic Match | C44: CLM | D44: 46113 | E44: 73 = Butternut 78 = Chocolate 58 = Coal 86 = Blue 63 = Stonewash | F44: P/S | H44: A | K44: L | R44: With a 1.2-1.4mm thickness, Majestic is a high-performance semi-aniline leather that delivers the depth and richness of an aniline look with a soft, wet hand feel. The distinctive savage kella effect creates two-tone variation and natural movement, finished in a refined semi-matte top-coat.
A45: DL1595 | B45: Montana | C45: CLP | D45: 43191 | E45: 57 = Charcoal 74 = Camel | F45: P/S | H45: N | K45: L | R45: Montana is a natural aniline tri tone leather. It is very lightly hand buffed creating additional softness. As with any hand buffed, the slight shading variations will enhance its natural qualities and overall elegant look.
A46: LB2064 | B46: Opulence | C46: SLR | D46: 45566 | E46: 74 = Stone 77 = Umber | F46: 12x12 | H46: A | K46: L | L46: 512 Pinnacle 709 Jasper | R46: Opulence is a semi-aniline article, with a pronounced grain achieved through a light embossing process during finishing. This leather has a subtle two-tone and a soft, supple hand attributed to its thickness of 1.0-1.2mm.
A47: LB1648 | B47: Prestige | C47: SLR | D47: 43556 | E47: 09 = Wine 79 = Chocolate | F47: 12x12 | H47: P | K47: L | L47: 776 Redwood | R47: Prestige features a soft hand and sophisticated appearance achieved through milling and ironing. The two-tone look is achieved through a spray process, and tumbling provides the look and feel of a semi-aniline while using a corrected grain.
A48: LB1648 | B48: Prestige | C48: SLR | D48: 43556 | E48: 54 = Grey 79 = Chocolate | F48: 12x12 | H48: P | K48: L | L48: 722 Roman | O48: Comes standard with heavy-gauge tonal topstitching on the arm borders and wings and double needle on the backs, seats, and top arms. | R48: Prestige features a soft hand and sophisticated appearance achieved through milling and ironing. The two-tone look is achieved through a spray process, and tumbling provides the look and feel of a semi-aniline while using a corrected grain.
A49: LB2137 | B49: Rhythmic | C49: SLR | D49: 46113 | E49: 77 = Mocha 58 = Charcoal | F49: 12x12 | H49: A | K49: L | L49: 828 Dutton | R49: This premium semi-aniline leather features a natural grain enhanced by a subtle wax effect for added depth and character. At 1.0–1.2mm thick, it offers a balanced combination of durability and softness with a protected finish. Its layered tonal variation creates a rich, classic look with enduring appeal.
A50: LB2113 | B50: Roberto | C50: SLR | D50: 45931 | E50: 79 = Slate 76 = Chocolate | F50: 12x12 | H50: A | K50: L | L50: 805 Ace - Colors 76, 79 530 Greyson - Colors 31, 76 & 79 | O50: 530 Greyson: HG Top Stitching 805 Ace: HG Top Stitching | R50: Roberto is a soft semi-aniline leather with a natural grain and gentle, spongy hand with just the right amount of drag. A subtle two-tone effect and matte finish give it a relaxed, refined look that’s effortlessly timeless.
A51: LB2113 | B51: Roberto | C51: SLR | D51: 46113 | E51: 31 = Ice | F51: 12x12 | H51: A | K51: L | L51: 530 Greyson - Colors 31, 76 & 79 | O51: 530 Greyson: HG Top Stitching | R51: Roberto is a soft semi-aniline leather with a natural grain and gentle, spongy hand with just the right amount of drag. A subtle two-tone effect and matte finish give it a relaxed, refined look that’s effortlessly timeless.
A52: LB1930 | B52: Salvo | C52: SLR | D52: 44835 | E52: 59 = Slate 77 = Caramel 56 = Blue Grey 32 = Ice | F52: 12x12 | H52: A | K52: L | L52: 757 Apollo - Colors 59, 77 & 56 530 Greyson - Colors 56, 77 & 32 | O52: 757 Apollo - Decorative Top Stitching 530 Greyson - HG Top Stitching | R52: Salvo is a richly colored, creamy soft leather that adds elegance to any style of furniture. Versatile and fashionable, Salvo features a subtle two-tone, a fine grain, and a chic low-sheen finish. Great for active households, Salvo works on any type of furniture including
A53: FL9419 | B53: Samba | C53: CLP | D53: 39601 | E53: 28 = Hunter 30 = White 32 = Ivory 50 = Ebony 53 = Gray 65 = Cobblestone 82 = Powder Blue 87 = Ultramarine 17 = Cognac 96 = Aqua 62 = Clay 26 = Sage 42 = Marigold 08 = Crimson | F53: P/S | H53: P | K53: L | O53: Some of the very light colors can be subject to color transfer from clothing. This is not a leather defect if it occurs. Blue and black denim jeans as well as heavy colored khaki can transfer color to lighter pigmented leather. | R53: Samba is top grain leather that has been buffed and embossed for consistency. This colorful eclectic transitional leather is fully protected pigmented leather, surface coated with a treatment for resistance to effects of everyday use while maintaining a wonderfully soft hand.
A54: LB2060 | B54: Sutton | C54: SLR SLS | D54: 45566 | E54: 32 = Ivory 54 = Greystone 77 = Cognac 87 = Navy | F54: 12x12 | H54: A | K54: L | L54: 715 Kodie - Colors 87 & 77 812 Armitage - Colors 32, 54 & 77 813 Clybourn - Colors 87 & 77 435 Mackenzie; 603 Wilmette; 613 Olson; 636 Shiloh; 638 Charlie - Colors 32, 54, 77, 87 | O54: 813 Clybourn - HG Top Stitching | R54: Sutton is a semi-aniline, natural grain article with a full hand and a thickness of 1.2-1.4mm. The special two-tone effect gives each hide unique depth. The combination of color intensity, subtle sheen and natural grain result in a beautiful premium leather.
A55: DL1596 | B55: Titan | C55: CLP | D55: 43191 | E55: 51 = Platinum 58 = Charcoal 65 = Clay 74 = Cinnamon 75 = Chocolate | F55: P/S | H55: A | K55: L | R55: Titan is a natural grain, creating a very soft two-tone, done with a kela and spray gun. It has a very slight tipping effect adding to its luster.
A56: LB1929 | B56: Topflight | C56: SLR | D56: 45017 | E56: 35 = Ivory 59 = Slate 76 = Camel 79 = Mineral | F56: 12x12 | H56: A | K56: L | L56: 759 Maddox - Colors 59 & 76 769 Ava - Colors 35 & 79 804 Belmont - Colors 76 & 79 | O56: 759 Maddox - HG Top Stitching | R56: Mild sheen, Fine and sophisticated colorways. Soft tender hand, vibrant colors with deep penetration. Semi-aniline, Natural grain, 1.1-1.2mm
A57: LB1646 | B57: Vacation | C57: SLR | D57: 43556 | E57: 63 = Beige 77 = Walnut | F57: 12x12 | H57: P | K57: L | L57: 704 Reed | R57: Vacation is a pigment dyed article with a printed two-tone sauvage featuring a mid-scale pebble grain, heavier weight, and a soft and supple hand.
A58: LB1520 | B58: Yellowstone | C58: SLR | D58: 43009 | E58: 56 = Charcoal 78 = Walnut | F58: 12x12 | H58: P | K58: L | L58: 521 James | O58: Comes standard with single-needle topstitching on the inside arms. | R58: Yellowstone is slightly corrected with a tri-tone effect. The thickness is on the heavier side at 1.2-1.4mm, yet features a very soft hand.
A60: Leather Classification Descriptions/General Information
A61: Cleaning & Maintenance Instructions: Leather is a natural material and, if properly cared for, will maintain its beauty and usefulness for many years.
A62: Direct exposure to strong light can cause any leather color to fade, so always protect leather from direct sunlight and other intense light sources. It is also advised that leather products be kept away from radiators or other generators of heat.
A64: Maintenance: Periodic dusting and vacuuming is recommended for normal maintenance of leather. For daily or weekly dusting use a soft clean lint free white cloth dampened with distilled water.
A67: Note: Always test-clean on a hidden area to confirm results. The use of any commercial leather cleaners or leather protection may cause damage to the protective finish. Lighter colors may require more frequency of maintenance than darker colors, depending on use.
A69: Shade Standards: This leather will have only slight shade variations due to the nature of the unique spray pattern.
A71: PERFORMANCE
A72: Description: Tough enough for everyday life, these top grain leathers are crafted to be rugged enough to withstand the challenges of homes with small children and pets.
A74: Characteristics: The consistent overall color and subtle markings of Performance or protected leathers are created by a variety of techniques, such as embossing, corrective techniques and protective coatings, to improve resistance to soil and enhance their natural beauty.
A77: Benefits: Luxurious, long lasting and easy to maintain, Performance leathers have a naturally soft and supple feel, yet can handle the rigors of day-to-day living. An occasional wiping with a clean damp cloth keeps Performance leathers looking their best for many years to come.
A80: Cleaning: For deeper cleaning of pigmented leather, use a solution of one-half mild soap such as Neutrogena or Dove and one-half distilled water on a slightly dampened sponge working up foam to clean. Avoid excessive rubbing with a cloth. Repeat this process as needed. Blot any remaining soap residue with a clean white soft cloth or paper towel dampened with clear distilled water. If stains or soiling persists consult a professional leather cleaning service.
A83: NUBUCK
... A108: The basic difference between Performance and Nubuck/Authentic is simply the way the leather is made for its use in the home. Performance leathers are typically top grain hides that have been buffed or sanded and may have a corrective process applied such as embossing. This process allows the leather to withstand more everyday wear. Whereas, Nubuck and Authentic leathers are normally left in their natural state so that wrinkles and animal characteristics are visible. These types of leathers are still very durable but are generally for a more formal setting in the home. All categories of La-Z-Boy leathers are finished with special protective coatings designed to enhance the hand of the particular article.

Sheet Dealer Swatch Inventory
A1: Cover | B1: Design Center (Large) | C1: Comfort Studio (Small) | D1: Ring Page | E1: Custom DC Single Swatch ONLY | F1: Cover Name | G1: Color Name | H1: Status
A2: B153808 | B2: X | C2: X | D2: X | F2: SEAMOUNT | G2: BURGUNDY | H2: ACTIVE
A3: B153853 | B3: X | C3: X | D3: X | F3: SEAMOUNT | G3: SILVER | H3: ACTIVE
A4: B153874 | B4: X | C4: X | D4: X | F4: SEAMOUNT | G4: SABLE | H4: ACTIVE
A5: B153876 | B5: X | C5: X | D5: X | F5: SEAMOUNT | G5: CAPPUCCINO | H5: ACTIVE
A6: B153885 | B6: X | C6: X | D6: X | F6: SEAMOUNT | G6: INDIGO | H6: ACTIVE
A7: B166257 | B7: X | C7: X | D7: X | F7: RODIGO | G7: STONE | H7: DROPPED
A8: B166276 | B8: X | C8: X | D8: X | F8: RODIGO | G8: MARSH | H8: DROPPED
A9: B166278 | B9: X | C9: X | D9: X | F9: RODIGO | G9: WALNUT | H9: DROPPED
A10: B166286 | B10: X | C10: X | D10: X | F10: RODIGO | G10: NAVY | H10: DROPPED
A11: B180852 | B11: X | C11: X | D11: X | F11: SOCIAL CLUB | G11: STONE | H11: ACTIVE
A12: B180857 | B12: X | C12: X | D12: X | F12: SOCIAL CLUB | G12: CHARCOAL | H12: ACTIVE
A13: B180868 | B13: X | C13: X | D13: X | F13: SOCIAL CLUB | G13: PEWTER | H13: ACTIVE
... A15: B180876 | B15: X | C15: X | D15: X | F15: SOCIAL CLUB | G15: COCOA | H15: ACTIVE
A16: B182725 | B16: X | D16: X | F16: BRINK | G16: LENTIL | H16: DROPPED
A17: B182786 | B17: X | D17: X | F17: BRINK | G17: SLATE | H17: ACTIVE
A18: BL211758 | D18: X | F18: MAJESTIC MATCH | G18: COAL | H18: ACTIVE
A19: BL211763 | D19: X | F19: MAJESTIC MATCH | G19: STONEWASH | H19: ACTIVE
A20: BL211773 | D20: X | F20: MAJESTIC MATCH | G20: BUTTERNUT | H20: ACTIVE
A21: BL211778 | D21: X | F21: MAJESTIC MATCH | G21: CHOCOLATE | H21: ACTIVE
A22: BL211786 | D22: X | F22: MAJESTIC MATCH | G22: BLUE | H22: ACTIVE
A23: BL981007 | D23: X | F23: COZY MATCH | G23: WINE | H23: ACTIVE
A24: BL981009 | D24: X | F24: COZY MATCH | G24: POMEGRANATE | H24: ACTIVE
A25: BL981031 | D25: X | F25: COZY MATCH | G25: OYSTER | H25: ACTIVE
A26: BL981036 | D26: X | F26: COZY MATCH | G26: MARSHMALLOW | H26: ACTIVE
A27: BL981050 | D27: X | F27: COZY MATCH | G27: LICORICE | H27: ACTIVE
A28: BL981051 | D28: X | F28: COZY MATCH | G28: DUSTY | H28: ACTIVE
A29: BL981054 | D29: X | F29: COZY MATCH | G29: PUTTY | H29: ACTIVE
... A35: BL981098 | D35: X | F35: COZY MATCH | G35: ARCTIC BLUE | H35: ACTIVE
A36: C137108 | B36: X | C36: X | D36: X | F36: SEASONS | G36: REDWOOD | H36: DROPPED
A37: C137128 | B37: X | C37: X | D37: X | F37: SEASONS | G37: LODEN | H37: DROPPED
A38: C137162 | B38: X | C38: X | D38: X | F38: SEASONS | G38: KHAKI | H38: DROPPED
A39: C137166 | B39: X | C39: X | D39: X | F39: SEASONS | G39: MOCHA | H39: DROPPED
A40: C137178 | B40: X | C40: X | D40: X | F40: SEASONS | G40: CHOCOLATE | H40: DROPPED
A41: C137187 | B41: X | C41: X | D41: X | F41: SEASONS | G41: CHARCOAL | H41: DROPPED
A42: C151631 | B42: X | D42: X | F42: MERIT | G42: DOVE | H42: DROPPED
A43: C151651 | B43: X | D43: X | F43: MERIT | G43: PLATINUM | H43: DROPPED
A44: C151657 | B44: X | D44: X | F44: MERIT | G44: CHARCOAL | H44: DROPPED
A45: C152534 | B45: X | C45: X | D45: X | F45: ROMA | G45: CREAM | H45: ACTIVE
A46: C152553 | B46: X | C46: X | D46: X | F46: ROMA | G46: STORM | H46: ACTIVE
A47: C152574 | B47: X | C47: X | D47: X | F47: ROMA | G47: MOCHA | H47: ACTIVE
A48: C152578 | B48: X | C48: X | D48: X | F48: ROMA | G48: ESPRESSO | H48: ACTIVE
A49: C152586 | B49: X | C49: X | D49: X | F49: ROMA | G49: NAVY | H49: ACTIVE
A50: C158431 | B50: X | C50: X | D50: X | F50: SAXON | G50: OYSTER | H50: ACTIVE
A51: C158448 | B51: X | C51: X | D51: X | F51: SAXON | G51: CHESTNUT | H51: ACTIVE
A52: C158450 | B52: X | C52: X | D52: X | F52: SAXON | G52: ONYX | H52: ACTIVE
A53: C158487 | B53: X | C53: X | D53: X | F53: SAXON | G53: INDIGO | H53: ACTIVE
A54: C158497 | B54: X | C54: X | D54: X | F54: SAXON | G54: MARINE | H54: ACTIVE
A55: C162508 | B55: X | C55: X | D55: X | F55: VANCE | G55: GARNET | H55: ACTIVE
A56: C162527 | B56: X | C56: X | D56: X | F56: VANCE | G56: SAGE | H56: ACTIVE
... A157: C205682 | B157: X | C157: X | D157: X | F157: SEATTLE | G157: SLATE | H157: ACTIVE
A158: C206759 | B158: X | D158: X | F158: AXE | G158: ONYX | H158: ACTIVE
A159: C206764 | B159: X | D159: X | F159: AXE | G159: SLATE | H159: ACTIVE
A160: C206774 | B160: X | D160: X | F160: AXE | G160: MOCHA | H160: ACTIVE
A161: C206786 | B161: X | D161: X | F161: AXE | G161: MIDNIGHT | H161: ACTIVE
A162: C211832 | B162: X | C162: X | D162: X | F162: COSDREW | G162: ECRU | H162: ACTIVE
A163: C211852 | B163: X | C163: X | D163: X | F163: COSDREW | G163: STONE | H163: ACTIVE
A164: C211856 | B164: X | C164: X | D164: X | F164: COSDREW | G164: STEEL | H164: ACTIVE
A165: C211864 | B165: X | C165: X | D165: X | F165: COSDREW | G165: SABLE | H165: ACTIVE
A166: C211869 | B166: X | C166: X | D166: X | F166: COSDREW | G166: MOCHA | H166: ACTIVE
A167: C211932 | B167: X | C167: X | D167: X | F167: LONGMONT | G167: LINEN | H167: ACTIVE
A168: C211952 | B168: X | C168: X | D168: X | F168: LONGMONT | G168: NICKEL | H168: ACTIVE
A169: C211955 | B169: X | C169: X | D169: X | F169: LONGMONT | G169: STONE | H169: ACTIVE
A170: C211962 | B170: X | C170: X | D170: X | F170: LONGMONT | G170: PEBBLE | H170: ACTIVE
A171: C212029 | B171: X | C171: X | D171: X | F171: SAN MARINO | G171: JUNGLE | H171: ACTIVE
A172: C212032 | B172: X | C172: X | D172: X | F172: SAN MARINO | G172: PUTTY | H172: ACTIVE
A173: C212053 | B173: X | C173: X | D173: X | F173: SAN MARINO | G173: SHADOW | H173: ACTIVE
... A186: D149072 | B186: X | C186: X | D186: X | F186: I-BENAVENTO | G186: HEMP | H186: DROPPED
A187: D149415 | B187: X | D187: X | F187: PROSPECT | G187: CURRANT | H187: ACTIVE
A188: D149452 | B188: X | D188: X | F188: PROSPECT | G188: GREYSTONE | H188: ACTIVE
A189: D156332 | B189: X | C189: X | D189: X | F189: I-BARNABAS | G189: OAT | H189: DROPPED
A190: D156352 | B190: X | C190: X | D190: X | F190: I-BARNABAS | G190: FOSSIL | H190: DROPPED
A191: D156361 | B191: X | C191: X | D191: X | F191: I-BARNABAS | G191: DRIFTWOOD | H191: DROPPED
A192: D156363 | B192: X | C192: X | D192: X | F192: I-BARNABAS | G192: MUSHROOM | H192: DROPPED
A193: D156365 | B193: X | C193: X | D193: X | F193: I-BARNABAS | G193: SILT | H193: DROPPED
A194: D156431 | B194: X | C194: X | D194: X | F194: I-HALLANDALE | G194: IVORY | H194: ACTIVE
A195: D156453 | B195: X | C195: X | D195: X | F195: I-HALLANDALE | G195: PLATINUM | H195: ACTIVE
A196: D156458 | B196: X | C196: X | D196: X | F196: I-HALLANDALE | G196: CHARCOAL | H196: ACTIVE
A197: D156464 | B197: X | C197: X | D197: X | F197: I-HALLANDALE | G197: WICKER | H197: ACTIVE
A198: D156487 | B198: X | C198: X | D198: X | F198: I-HALLANDALE | G198: ADMIRAL | H198: ACTIVE
A199: D160454 | B199: X | C199: X | D199: X | F199: I-OUTLIER | G199: CHARCOAL | H199: ACTIVE
A200: D160458 | B200: X | C200: X | D200: X | F200: I-OUTLIER | G200: SLATE | H200: ACTIVE
... A208: D160686 | B208: X | C208: X | D208: X | F208: I-HALIFAX | G208: DENIM | H208: ACTIVE
A209: D166564 | B209: X | D209: X | F209: I-TAZLINA | G209: CLASSIC | H209: DROPPED
A210: D166575 | B210: X | D210: X | F210: I-TAZLINA | G210: AURORA | H210: DROPPED
A211: D169303 | B211: X | D211: X | F211: MILO | G211: MAUVE | H211: ACTIVE
A212: D169314 | B212: X | D212: X | F212: MILO | G212: RUSSET | H212: ACTIVE
A213: D169346 | B213: X | D213: X | F213: MILO | G213: SUNFLOWER | H213: ACTIVE
A214: D169362 | B214: X | D214: X | F214: MILO | G214: CAMEL | H214: ACTIVE
A215: D169398 | B215: X | D215: X | F215: MILO | G215: TEAL | H215: ACTIVE
A216: D170636 | B216: X | C216: X | D216: X | F216: VECTOR | G216: BARLEY | H216: ACTIVE
A217: D170655 | B217: X | C217: X | D217: X | F217: VECTOR | G217: GRAPHITE | H217: ACTIVE
A218: D170684 | B218: X | C218: X | D218: X | F218: VECTOR | G218: WATERFALL | H218: ACTIVE
A219: D175956 | B219: X | C219: X | D219: X | F219: I-SAXTON | G219: GRAPHITE | H219: ACTIVE
A220: D175964 | B220: X | C220: X | D220: X | F220: I-SAXTON | G220: MARBLE | H220: ACTIVE
A221: D175977 | B221: X | C221: X | D221: X | F221: I-SAXTON | G221: MINK | H221: ACTIVE
A222: D175978 | B222: X | C222: X | D222: X | F222: I-SAXTON | G222: ESPRESSO | H222: ACTIVE
A223: D175986 | B223: X | C223: X | D223: X | F223: I-SAXTON | G223: NAVY | H223: ACTIVE
A224: D180632 | B224: X | C224: X | D224: X | F224: I-CATALYST | G224: SAND | H224: ACTIVE
A225: D180654 | B225: X | C225: X | D225: X | F225: I-CATALYST | G225: PLATINUM | H225: ACTIVE
...

Sheet Ring Pages - Complete Set
A1: The following swatches for the La-Z-Boy Major Upholstery Collection represent current offerings as of the April 2026 Market.
A2: MU | K2: Key:
K3: Immediate Drop
B4: **NOTE** Merchandising suggests that ring pages be replaced every three years for color accuracy. Replacement Swatches can be ordered through EPI. | K4: Phase Outs
K5: New Phase Outs
K6: April 2026 Drops
A8: Item Number | B8: Intro Date | C8: Date Last Updated | D8: S=Single, C=Correlate, W/F=Waterfall, P/S=Postage Stamp | E8: Pattern Name | F8: Cover1 | G8: Cover2 | H8: Cover3 | I8: Cover4 | J8: Cover5 | K8: Cover6 | L8: Cover7
A9: SCPZB153876 | B9: 43009 | D9: P/S | E9: Seamount | F9: B153876 | G9: B153874 | H9: B153808 | I9: B153853 | J9: B153885
A10: SCPZC152553 | B10: 42826 | D10: P/S | E10: Roma | F10: C152553 | G10: C152578 | H10: C152574 | I10: C152586 | J10: C152534
A11: SCPZC162532 | B11: 43374 | D11: P/S | E11: Vance | F11: C162532 | G11: C162527 | H11: C162586 | I11: C162552 | J11: C162576 | K11: C162508
A12: SCPZD156453 | B12: 43191 | C12: 44835 | D12: P/S | E12: i-Hallandale | F12: D156453 | G12: D156464 | H12: D156431 | I12: D156458 | J12: D156487
A13: SCPZD160462 | B13: 43374 | D13: P/S | E13: i-Outlier | F13: D160462 | G13: D160454 | H13: D160476 | I13: D160479 | J13: D160458
A14: SCPZD160662 | B14: 43374 | C14: 44835 | D14: P/S | E14: i-Halifax | F14: D160662 | G14: D160632 | H14: D160654 | I14: D160678 | J14: D160686
A15: SCPZD210765 | B15: 45931 | D15: P/S | E15: Westcott | F15: D210765 | G15: D210731 | H15: D210769 | I15: D210758
A16: SCPZE153755 | B16: 44835 | D16: P/S | E16: i-Northwest | F16: E153755 | G16: E153773 | H16: E153752
A17: SCPZE153767 | B17: 43009 | D17: P/S | E17: i-Northwest | F17: E153767 | G17: E153758 | H17: E153775 | I17: E153765 | J17: E153732
A18: SMPZB180857 | B18: 44287 | D18: P/S | E18: Social Club | F18: B180857 | G18: B180876 | H18: B180868 | I18: B180852 | J18: B180872
A19: SMPZB182786 | B19: 45931 | D19: P/S | E19: Brink | F19: B182786 | G19: B182725
A20: SMPZC158497 | B20: 43191 | C20: 45748 | D20: P/S | E20: Saxon | F20: C158497 | G20: C158448 | H20: C158431 | I20: C158450 | J20: C158487
A21: SMPZC170053 | B21: 43739 | C21: 44835 | D21: P/S | E21: Nico | F21: C170053 | G21: C170057 | H21: C170033
A22: SMPZC175432 | B22: 43922 | C22: 44835 | D22: P/S | E22: Kemet | F22: C175432 | G22: C175474 | H22: C175486
A23: SMPZC175773 | B23: 43922 | D23: P/S | E23: Bartaloni | F23: C175773 | G23: C175733 | H23: C175753 | I23: C175731
A24: SMPZC180974 | B24: 44287 | C24: 44835 | D24: P/S | E24: Donegal | F24: C180974 | G24: C180969 | H24: C180964 | I24: C180987
A25: SMPZC181257 | B25: 44287 | D25: P/S | E25: Damon | F25: C181257 | G25: C181233 | H25: C181286 | I25: C181254 | J25: C181262
A26: SMPZC185265 | B26: 44470 | D26: P/S | E26: Tiago | F26: C185265 | G26: C185255 | H26: C185252 | I26: C185276 | J26: C185286
A27: SMPZC186036 | B27: 44470 | D27: P/S | E27: Persia | F27: C186036 | G27: C186086 | H27: C186008 | I27: C186054 | J27: C186076
A28: SMPZC186186 | B28: 44652 | D28: P/S | E28: Sarah | F28: C186186 | G28: C186158 | H28: C186153 | I28: C186162
A29: SMPZC187233 | B29: 44652 | D29: P/S | E29: Lynx | F29: C187233 | G29: C187276 | H29: C187252 | I29: C187232
A30: SMPZC188232 | B30: 44652 | D30: P/S | E30: Lukas | F30: C188232 | G30: C188286 | H30: C188279 | I30: C188273
A31: SMPZC196584 | B31: 45017 | D31: P/S | E31: Nora | F31: C196584 | G31: C196552 | H31: C196566 | I31: C196532
A32: SMPZC196733A | B32: 45566 | D32: P/S | E32: Lunar | F32: C196733 | G32: C196764 | H32: C196768 | I32: C196755 | J32: C196786
A33: SMPZC202931 | B33: 45383 | D33: P/S | E33: Easy | F33: C202931 | G33: C202964 | H33: C202958 | I33: C202907 | J33: C202987
A34: SMPZC203264 | B34: 45566 | D34: P/S | E34: Reyson | F34: C203264 | G34: C203278 | H34: C203274 | I34: C203285 | J34: C203260
A35: SMPZC203531 | B35: 45566 | D35: P/S | E35: Thane | F35: C203531 | G35: C203578 | H35: C203557 | I35: C203554
A36: SMPZC204260 | B36: 45566 | D36: P/S | E36: Duffey | F36: C204260 | G36: C204232 | H36: C204274 | I36: C204253
A37: SMPZC204373 | B37: 45566 | D37: P/S | E37: Sheldon | F37: C204373 | G37: C204376 | H37: C204357
A38: SMPZC204953 | B38: 45566 | D38: P/S | E38: Julien | F38: C204953 | G38: C204948 | H38: C204954 | I38: C204918
A39: SMPZC205376 | B39: 45566 | D39: P/S | E39: Clarke | F39: C205376 | G39: C205314 | H39: C205387 | I39: C205329
A40: SMPZC205682 | B40: 45566 | D40: P/S | E40: Seattle | F40: C205682 | G40: C205615 | H40: C205631
A41: SMPZC206764 | B41: 45748 | D41: P/S | E41: Axe | F41: C206764 | G41: C206774 | H41: C206759 | I41: C206786
A42: SMPZC211869 | B42: 46113 | D42: P/S | E42: Cosdrew | F42: C211869 | G42: C211832 | H42: C211864 | I42: C211852 | J42: C211856
A43: SMPZC211932 | B43: 46113 | D43: P/S | E43: Longmont | F43: C211932 | G43: C211962 | H43: C211952 | I43: C211955
A44: SMPZC212032 | B44: 46113 | D44: P/S | E44: San Marino | F44: C212032 | G44: C212061 | H44: C212053 | I44: C212086 | J44: C212029
A45: SMPZC212171 | B45: 46113 | D45: P/S | E45: Watari | F45: C212171 | G45: C212152 | H45: C212174 | I45: C212167 | J45: C212181
A46: SMPZC212252 | B46: 46113 | D46: P/S | E46: Taber | F46: C212252 | G46: C212232 | H46: C212263 | I46: C212267
A47: SMPZD169314 | B47: 45931 | D47: P/S | E47: Milo | F47: D169314 | G47: D169346 | H47: D169362 | I47: D169303 | J47: D169398
A48: SMPZD175956 | B48: 43922 | D48: P/S | E48: i-Saxton | F48: D175956 | G48: D175986 | H48: D175977 | I48: D175964 | J48: D175978
A49: SMPZD180654 | B49: 44287 | D49: P/S | E49: i-Catalyst | F49: D180654 | G49: D180632 | H49: D180657 | I49: D180678
A50: SMPZD180732 | B50: 44287 | D50: P/S | E50: Fairfax | F50: D180732 | G50: D180764 | H50: D180774 | I50: D180753 | J50: D180757 | K50: D180786
A51: SMPZD182558 | B51: 44287 | D51: P/S | E51: i-Raven Crest | F51: D182558 | G51: D182573 | H51: D182535 | I51: D182574
A52: SMPZD185553A | B52: 46113 | D52: P/S | E52: i-Rivers | F52: D185553 | G52: D185575 | H52: D185559 | I52: D185564 | J52: D185552 | K52: D185558
A53: SMPZD190572 | B53: 44652 | D53: P/S | E53: York | F53: D190572 | G53: D190558 | H53: D190554 | I53: D190574 | J53: D190531
A54: SMPZD197034 | B54: 45017 | D54: P/S | E54: Marteon | F54: D197034 | G54: D197052 | H54: D197056 | I54: D197066 | J54: D197096
A55: SMPZD200931 | B55: 45383 | D55: P/S | E55: Promise | F55: D200931 | G55: D200952 | H55: D200972 | I55: D200946 | J55: D200983 | K55: D200959
A56: SMPZD201032 | B56: 45383 | D56: P/S | E56: i-Rene | F56: D201032 | G56: D201052 | H56: D201065 | I56: D201025 | J56: D201081 | K56: D201019 | L56: D201014
A57: SMPZD201331 | B57: 45383 | D57: P/S | E57: Kerr | F57: D201331 | G57: D201354 | H57: D201395
A58: SMPZD202798 | B58: 45383 | D58: P/S | E58: i-Weekend | F58: D202798 | G58: D202751 | H58: D202767 | I58: D202732 | J58: D202775
A59: SMPZD203454 | B59: 45566 | D59: P/S | E59: Doritt | F59: D203454 | G59: D203478 | H59: D203475 | I59: D203436 | J59: D203432
A60: SMPZD206524 | B60: 45566 | D60: P/S | E60: Magnolia | F60: D206524 | G60: D206517
A61: SMPZD206661 | B61: 45566 | C61: 46113 | D61: P/S | E61: i-Kudos | F61: D206661 | G61: D206667 | H61: D206677 | I61: D206680 | J61: D206659
A62: SMPZD206893 | B62: 45748 | D62: P/S | E62: i-Beverley | F62: D206893 | G62: D206833 | H62: D206860 | I62: D206871 | J62: D206876
A63: SMPZD207154 | B63: 45748 | D63: P/S | E63: i-Rockport | F63: D207154 | G63: D207131 | H63: D207152 | I63: D207178 | J63: D207119
A64: SMPZD207231 | B64: 45748 | D64: P/S | E64: i-Nolina | F64: D207231 | G64: D207252 | H64: D207257 | I64: D207251 | J64: D207275
A65: SMPZD207432 | B65: 45748 | D65: P/S | E65: Gail | F65: D207432 | G65: D207480 | H65: D207451 | I65: D207460 | J65: D207478 | K65: D207486
A66: SMPZD207578 | B66: 45931 | D66: P/S | E66: Galloway | F66: D207578 | G66: D207565 | H66: D207538 | I66: D207586
A67: SMPZD209232 | B67: 45748 | D67: P/S | E67: Ross | F67: D209232 | G67: D209261 | H67: D209252 | I67: D209259 | J67: D209225
A68: SMPZD209376 | B68: 45931 | D68: P/S | E68: Artisia | F68: D209376 | G68: D209374 | H68: D209355 | I68: D209351 | J68: D209375 | K68: D209324 | L68: D209331
A69: SMPZD209478 | B69: 45931 | D69: P/S | E69: Crete | F69: D209478 | G69: D209448
A70: SMPZD209555 | B70: 45931 | D70: P/S | E70: Crocker | F70: D209555 | G70: D209574 | H70: D209586 | I70: D209551 | J70: D209562
A71: SMPZD209669 | B71: 45931 | D71: P/S | E71: Defender | F71: D209669 | G71: D209631 | H71: D209651 | I71: D209664
A72: SMPZD209933 | B72: 45931 | D72: P/S | E72: i-Favorite | F72: D209933 | G72: D209953 | H72: D209965 | I72: D209931
A73: SMPZD210062 | B73: 45931 | D73: P/S | E73: i-George | F73: D210062 | G73: D210052 | H73: D210031 | I73: D210070 | J73: D210054
A74: SMPZD210162 | B74: 45931 | D74: P/S | E74: Novan | F74: D210162 | G74: D210174 | H74: D210137 | I74: D210155
A75: SMPZD210663 | B75: 46113 | D75: P/S | E75: Tonda | F75: D210663 | G75: D210677 | H75: D210656 | I75: D210686 | J75: D210659
A76: SMPZD211632 | B76: 45931 | D76: P/S | E76: Rome | F76: D211632 | G76: D211675 | H76: D211652 | I76: D211686
A77: SMPZD212331 | B77: 46113 | D77: P/S | E77: Ayla | F77: D212331 | G77: D212373 | H77: D212363 | I77: D212351 | J77: D212386
A78: SMPZD212459 | B78: 46113 | D78: P/S | E78: i-Westvale | F78: D212459 | G78: D212432 | H78: D212478 | I78: D212475
A79: SMPZD212573 | B79: 46113 | D79: P/S | E79: Playlist | F79: D212573 | G79: D212533 | H79: D212564 | I79: D212558
A80: SMPZD212678 | B80: 46113 | D80: P/S | E80: Prism | F80: D212678 | G80: D212633 | H80: D212674 | I80: D212653
A81: SMPZD212875 | B81: 46113 | D81: P/S | E81: Winslow | F81: D212875 | G81: D212869 | H81: D212856
A82: SMPZD212954 | B82: 46113 | D82: P/S | E82: Zinnamon | F82: D212954 | G82: D212934 | H82: D212931 | I82: D212952 | J82: D212970
A83: SMPZD214074 | B83: 46113 | D83: P/S | E83: i-Eugene | F83: D214074 | G83: D214063 | H83: D214060 | I83: D214032 | J83: D214083
A84: SMPZE165133 | B84: 43556 | C84: 44835 | D84: P/S | E84: i-Broderick | F84: E165133 | G84: E165163 | H84: E165152 | I84: E165181
A85: SMPZE165235 | B85: 43556 | C85: 44835 | D85: P/S | E85: i-Liv | F85: E165235 | G85: E165231 | H85: E165252 | I85: E165296
A86: SMPZE178562 | B86: 44105 | C86: 44835 | D86: P/S | E86: i-Machale | F86: E178562 | G86: E178553 | H86: E178530 | I86: E178586
A87: SMPZE182014 | B87: 44287 | D87: P/S | E87: Wheelie | F87: E182014 | G87: E182032 | H87: E182059 | I87: E182016 | J87: E182087 | K87: E182023
A88: SMPZE186650 | B88: 44652 | D88: P/S | E88: Vitani | F88: E186650 | G88: E186608 | H88: E186654 | I88: E186672 | J88: E186686 | K88: E186624
A89: SMPZE191734 | B89: 44835 | D89: P/S | E89: i-Adario | F89: E191734 | G89: E191765 | H89: E191752 | I89: E191753
A90: SMPZE203661 | B90: 45566 | D90: P/S | E90: Omni | F90: E203661 | G90: E203675 | H90: E203678 | I90: E203680 | J90: E203659
A91: SMPZE204062 | B91: 45566 | D91: P/S | E91: i-Gellar | F91: E204062 | G91: E204078 | H91: E204052 | I91: E204031 | J91: E204023
A92: SMPZE204132 | B92: 45748 | D92: P/S | E92: Lionel | F92: E204132 | G92: E204154 | H92: E204169 | I92: E204129 | J92: E204184 | K92: E204119
A93: SMPZJ204439 | B93: 45566 | D93: P/S | E93: Triangular | F93: J204439 | G93: J204459 | H93: J204462 | I93: J204487
A94: SMPZJ204632 | B94: 45566 | D94: P/S | E94: Keeline | F94: J204632 | G94: J204665 | H94: J204658 | I94: J204674
A95: SMPZJ208583 | B95: 45748 | D95: P/S | E95: Hassett | F95: J208583 | G95: J208535 | H95: J208575 | I95: J208559 | J95: J208517
A96: SMPZJ213422 | B96: 46113 | D96: P/S | E96: Sherwood | F96: J213422 | G96: J213436 | H96: J213467 | I96: J213482
A97: SMPZQ191232 | B97: 44835 | D97: P/S | E97: i-Blackhawk | F97: Q191232 | G97: Q191273 | H97: Q191257 | I97: Q191275
A98: SMPZQ194161 | B98: 44835 | D98: P/S | E98: i-Atherton | F98: Q194161 | G98: Q194154 | H98: Q194152 | I98: Q194164
A99: SMSZC167076 | B99: 43556 | D99: S | E99: Northern Exposure | F99: C167076
A100: SMSZD209009 | B100: 45748 | D100: S | E100: Penelope | F100: D209009
A101: SMSZE176315 | B101: 43922 | D101: S | E101: i-Esma | F101: E176315
...

Sheet Design Center
A1: The following swatches for the La-Z-Boy Design Center Collection represent current offerings as of the April 2026 Market.
A2: DC | J2: Specialty Fabric Descriptions | M2: Key:
J3: I = iClean | M3: Immediate Drop
J4: C = Conserve | M4: Phase Outs
J5: A = Antimicrobial | M5: New Phase Outs
J6: PF = Pet Friendly | M6: April 2026 Drops
J7: N = Nanobionic
J8: W*B = Bleach Cleanable
A10: Item Number | B10: Intro Date | C10: Date Last Updated | D10: S=Single, C=Correlate, W/F=Waterfall | E10: Pattern Name | F10: Specialty Fabric | G10: Comfort Studio | H10: Custom DC Single Swatch ONLY | I10: Cover1 | J10: Cover2 | K10: Cover3 | L10: Cover4 | M10: Cover5 | N10: Cover6 | O10: Cover7 | P10: Color Names
A11: SDSZJ208802 | B11: 45748 | D11: S | E11: Faircrest | I11: J208802 | P11: Blush
A12: SDSZD169303 | B12: 45931 | D12: S | E12: Milo | I12: D169303 | P12: Mauve
A13: SDSZJ201705 | B13: 45383 | D13: S | E13: Haze | I13: J201705 | P13: Terracotta
A14: SDSZQ208705 | B14: 45748 | D14: S | E14: Liliana | I14: Q208705 | P14: Rouge
A15: SDSZD208606 | B15: 45748 | D15: S | E15: Spring Valley | G15: X | I15: D208606 | P15: Blossom
A16: SDCZD208606 | B16: 45748 | D16: C | E16: Spring Valley | I16: D208606 | J16: J208907 | K16: Q208705 | L16: D209009 | M16: J208802 | P16: Blossom/Papaya/Rouge/Crimson/Blush
A17: SDSZC202907 | B17: 45383 | D17: S | E17: Easy | G17: X | I17: C202907 | P17: Brick
A18: SDSZJ208907 | B18: 45748 | D18: S | E18: Josephine | I18: J208907 | P18: Papaya
A19: SDSZC162508 | B19: 43374 | D19: S | E19: Vance | G19: X | I19: C162508 | P19: Garnet
A20: SDSZC186008 | B20: 44470 | D20: S | E20: Persia | G20: X | I20: C186008 | P20: Wine
A21: SDSZE186608 | B21: 44652 | D21: S | E21: Vitani | I21: E186608 | P21: Brick
A22: SDSZJ213308 | B22: 46137 | D22: S | E22: McCoy | I22: J213308 | P22: Mauve
A23: SDSZJ213508 | B23: 46137 | D23: S | E23: Anisette | I23: J213508 | P23: Wine
A24: SDSZJ213808 | B24: 46137 | D24: S | E24: Cabana | I24: J213808 | P24: Chai
A25: SDSZD209009 | B25: 45748 | D25: S | E25: Penelope | I25: D209009 | P25: Crimson
A26: SDSZD209810 | B26: 45931 | D26: S | E26: Gabby | I26: D209810 | P26: Gold
A27: SDSZD210211 | B27: 45931 | D27: S | E27: Picasso | G27: X | I27: D210211 | P27: Desert
A28: SDSZD201612 | B28: 45383 | D28: S | E28: Coast | G28: X | I28: D201612 | P28: Coral
A29: SDSZD209712 | B29: 45931 | D29: S | E29: Donatello | I29: D209712 | P29: Canyon
A30: SDSZC205314 | B30: 45566 | D30: S | E30: Clarke | G30: X | I30: C205314 | P30: Blush
A31: SDSZD169314 | B31: 45931 | D31: S | E31: Milo | I31: D169314 | P31: Russet
A32: SDSZD201014 | B32: 45383 | D32: S | E32: i-Rene | F32: I | G32: X | I32: D201014 | P32: Nutmeg
A33: SDSZE182014 | B33: 44287 | D33: S | E33: Wheelie | G33: X | I33: E182014 | P33: Copper
A34: SDSZJ204814 | B34: 45566 | D34: S | E34: Montebello | I34: J204814 | P34: Cognac
A35: SDSZC205615 | B35: 45566 | D35: S | E35: Seattle | G35: X | I35: C205615 | P35: Brandy
A36: SDSZD149415 | B36: 42826 | D36: S | E36: Prospect | I36: D149415 | P36: Currant
A37: SDSZE176315 | B37: 43922 | D37: S | E37: i-Esma | F37: I, C, PF | I37: E176315 | P37: Autumn
A38: SDSZQ197715 | B38: 45931 | D38: S | E38: Tinsley | F38: W*B | I38: Q197715 | P38: Autumn
A39: SDSZD209716 | B39: 45931 | D39: S | E39: Donatello | I39: D209716 | P39: Harvest
A40: SDSZE182016 | B40: 44287 | D40: S | E40: Wheelie | G40: X | I40: E182016 | P40: Spice
A41: SDSZQ199616 | B41: 45200 | D41: S | E41: Alora | I41: Q199616 | P41: Spice
A42: SDSZD206517 | B42: 45566 | D42: S | E42: Magnolia | I42: D206517 | P42: Chestnut
A43: SDCZD206517 | B43: 45566 | D43: C | E43: Magnolia | I43: D206517 | J43: C205314 | K43: C205615 | L43: D205418 | P43: Chestnut/Blush/Brandy/Sienna
A44: SDSZE171417 | B44: 43739 | D44: S | E44: i-Aryna | F44: I, C | I44: E171417 | P44: Aurora
A45: SDSZE181517 | B45: 44287 | D45: S | E45: i-Emarosa | F45: I, C | G45: X | I45: E181517 | P45: Poppy
A46: SDSZG171517 | B46: 43739 | D46: S | E46: i-Lockhart | F46: I | I46: G171517 | P46: Brick
A47: SDSZJ197417 | B47: 45017 | D47: S | E47: Parker | I47: J197417 | P47: Nutmeg
A48: SDSZJ208517 | B48: 45748 | D48: S | E48: Hassett | F48: W*B | I48: J208517 | P48: Apricot
A49: SDSZC204918 | B49: 45566 | D49: S | E49: Julien | G49: X | I49: C204918 | P49: Spice
A50: SDSZD205418 | B50: 45566 | D50: S | E50: Amari | G50: X | I50: D205418 | P50: Sienna
A51: SDSZD212718 | B51: 46113 | D51: S | E51: Stir Crazy | G51: X | I51: D212718 | P51: Rust
A52: SDSZJ182118 | B52: 44287 | D52: S | E52: Houston | I52: J182118 | P52: Spice
A53: SDSZJ204718 | B53: 45566 | D53: S | E53: Tamarindo | I53: J204718 | P53: Sienna
A54: SDSZD201019 | B54: 45383 | D54: S | E54: i-Rene | F54: I | G54: X | I54: D201019 | P54: Spice
A55: SDSZD207119 | B55: 45748 | D55: S | E55: i-Rockport | F55: I | G55: X | I55: D207119 | P55: Salsa
A56: SDSZE204119 | B56: 45748 | D56: S | E56: Lionel | I56: E204119 | P56: Acorn
A57: SDSZJ199519 | B57: 45200 | D57: S | E57: Marlin | F57: W*B | G57: X | I57: J199519 | P57: Persimmon
A58: SDSZJ211019 | B58: 45931 | D58: S | E58: Telluride | I58: J211019 | P58: Spice
A59: SDSZQ208719 | B59: 45748 | D59: S | E59: Liliana | I59: Q208719 | P59: Rust
A60: SDSZE205220 | B60: 45566 | D60: S | E60: Manorwood | G60: X | I60: E205220 | P60: Herb
A61: SDSZJ204820 | B61: 45566 | D61: S | E61: Montebello | I61: J204820 | P61: Pine
A62: SDSZJ208321 | B62: 45748 | D62: S | E62: i-Kitsilano | F62: I | I62: J208321 | P62: Fern
A63: SDSZJ213422 | B63: 46137 | D63: S | E63: Sherwood | F63: W*B | I63: J213422 | P63: Moss
A64: SDSZE182023 | B64: 44287 | D64: S | E64: Wheelie | G64: X | I64: E182023 | P64: Mist
A65: SDSZE204023 | B65: 45566 | D65: S | E65: I-Gellar | F65: I | I65: E204023 | P65: Moss
A66: SDCZJ192123 | B66: 44835 | D66: C | E66: Bala | I66: J192123 | J66: J192344 | K66: F157494 | L66: F157487 | P66: Earth/Honey/Spa/Marble
A67: SDSZJ192123 | B67: 44835 | D67: S | E67: Bala | G67: X | I67: J192123 | P67: Earth
A68: SDSZD206524 | B68: 45566 | D68: S | E68: Magnolia | I68: D206524 | P68: Sage
A69: SDCZD206524 | B69: 45566 | D69: C | E69: Magnolia | I69: D206524 | J69: E205220 | K69: C205329 | L69: D205429 | P69: Sage/Herb/Olive/Palmetto
A70: SDSZD209324 | B70: 45931 | D70: S | E70: Artisia | I70: D209324 | P70: Leaf
A71: SDSZE171424 | B71: 43739 | D71: S | E71: i-Aryna | F71: I, C | I71: E171424 | P71: Classic
A72: SDSZE186624 | B72: 44652 | D72: S | E72: Vitani | I72: E186624 | P72: Windsor Green
A73: SDSZJ192324 | B73: 44835 | D73: S | E73: Ellibee | I73: J192324 | P73: Eucalyptus
A74: SDSZQ208724 | B74: 45748 | D74: S | E74: Liliana | I74: Q208724 | P74: Sage
A75: SDSZD201025 | B75: 45383 | D75: S | E75: i-Rene | F75: I | G75: X | I75: D201025 | P75: Moss
A76: SDSZD209225 | B76: 45748 | D76: S | E76: Ross | F76: W*B | I76: D209225 | P76: Moss
A77: SDSZE204129 | B77: 45748 | D77: S | E77: Lionel | I77: E204129 | P77: Cypress
A78: SDSZJ213225 | B78: 46137 | D78: S | E78: Gillette | I78: J213225 | P78: Earth
A79: SDSZQ197726 | B79: 45931 | D79: S | E79: Tinsley | F79: W*B | I79: Q197726 | P79: Botany
A80: SDSZC162527 | B80: 43374 | D80: S | E80: Vance | G80: X | I80: C162527 | P80: Sage
A81: SDSZD209727 | B81: 45931 | D81: S | E81: Donatello | I81: D209727 | P81: Forest
A82: SDCZJ192127 | B82: 44835 | C82: 45383 | D82: C | E82: Bala | I82: J192127 | J82: E176494 | K82: D170684 | P82: Forest/Mist/Waterfall - Blue/Green
A83: SDSZJ192127 | B83: 44835 | D83: S | E83: Bala | G83: X | I83: J192127 | P83: Forest
A84: SDSZJ213827 | B84: 46137 | D84: S | E84: Cabana | I84: J213827 | P84: Herbal
A85: SDSZC205329 | B85: 45566 | D85: S | E85: Clarke | G85: X | I85: C205329 | P85: Olive
A86: SDSZC212029 | B86: 46137 | D86: S | E86: San Marino | G86: X | I86: C212029 | P86: Jungle
A87: SDSZD205429 | B87: 45566 | D87: S | E87: Amari | G87: X | I87: D205429 | P87: Palmetto
A88: SDSZJ199029 | B88: 45200 | D88: S | E88: Ajay | G88: X | I88: J199029 | P88: Pine
A89: SDSZE178530 | B89: 44105 | D89: S | E89: i-Machale | F89: I, A, PF | I89: E178530 | P89: Ivory
A90: SDSZJ204830 | B90: 45566 | D90: S | E90: Montebello | I90: J204830 | P90: Natural
A91: SDSZC158431 | B91: 43191 | D91: S | E91: Saxon | G91: X | I91: C158431 | P91: Oyster
A92: SDSZC175731 | B92: 43922 | D92: S | E92: Bartaloni | G92: X | I92: C175731 | P92: Oatmeal
A93: SDSZC202931 | B93: 45383 | D93: S | E93: Easy | G93: X | I93: C202931 | P93: Linen
A94: SDSZC203531 | B94: 45566 | D94: S | E94: Thane | G94: X | I94: C203531 | P94: Linen
A95: SDSZC205631 | B95: 45566 | D95: S | E95: Seattle | G95: X | I95: C205631 | P95: Porcelain
A96: SDSZD156431 | B96: 43191 | D96: S | E96: i-Hallandale | F96: I, PF | G96: X | I96: D156431 | P96: Ivory
A97: SDSZD190531 | B97: 44652 | C97: 44835 | D97: S | E97: York | G97: X | I97: D190531 | P97: Cream
A98: SDSZD200931 | B98: 45383 | D98: S | E98: Promise | G98: X | I98: D200931 | P98: Ecru
A99: SDSZD201331 | B99: 45383 | D99: S | E99: Kerr | G99: X | I99: D201331 | P99: Linen
A100: SDSZD205431 | B100: 45566 | D100: S | E100: Amari | G100: X | I100: D205431 | P100: Natural
A101: SDSZD207131 | B101: 45748 | D101: S | E101: i-Rockport | F101: I | G101: X | I101: D207131 | P101: Linen
...

Sheet 6x6 Fabric
A1: The following swatches for the 6x6 Inline Customer Swatches represent current offerings as of the April 2026 Market.
A2: 6I
F3: Key:
F4: Immediate Drop
F5: Phase Outs
F6: New Phase Outs
F7: April 2026 Drops
A9: Item Number | B9: Intro Date | C9: Date Last Updated | D9: S=Single, C=Correlate, W/F=Waterfall, P/S=Postage Stamp | E9: Pattern Name | F9: Color Name | G9: Cover
A10: SC6ZB153808 | B10: =VLOOKUP(E10,'MASTER FABRICS'!B:F,5,FALSE) -> 43009 | D10: 6x6 | E10: Seamount | F10: Burgundy | G10: B153808
A11: SC6ZB153853 | B11: =VLOOKUP(E11,'MASTER FABRICS'!B:F,5,FALSE) -> 43009 | D11: 6x6 | E11: Seamount | F11: Silver | G11: B153853
A12: SC6ZB153874 | B12: =VLOOKUP(E12,'MASTER FABRICS'!B:F,5,FALSE) -> 43009 | D12: 6x6 | E12: Seamount | F12: Sable | G12: B153874
A13: SC6ZB153876 | B13: =VLOOKUP(E13,'MASTER FABRICS'!B:F,5,FALSE) -> 43009 | D13: 6x6 | E13: Seamount | F13: Cappuccino | G13: B153876
A14: SC6ZB153885 | B14: =VLOOKUP(E14,'MASTER FABRICS'!B:F,5,FALSE) -> 43009 | D14: 6x6 | E14: Seamount | F14: Indigo | G14: B153885
A15: SM6ZB180852 | B15: =VLOOKUP(E15,'MASTER FABRICS'!B:F,5,FALSE) -> 44287 | D15: 6x6 | E15: Social Club | F15: Stone | G15: B180852
A16: SM6ZB180857 | B16: =VLOOKUP(E16,'MASTER FABRICS'!B:F,5,FALSE) -> 44287 | D16: 6x6 | E16: Social Club | F16: Charcoal | G16: B180857
A17: SM6ZB180868 | B17: =VLOOKUP(E17,'MASTER FABRICS'!B:F,5,FALSE) -> 44287 | D17: 6x6 | E17: Social Club | F17: Pewter | G17: B180868
A18: SM6ZB180872 | B18: =VLOOKUP(E18,'MASTER FABRICS'!B:F,5,FALSE) -> 44287 | D18: 6x6 | E18: Social Club | F18: Chalk | G18: B180872
A19: SM6ZB180876 | B19: =VLOOKUP(E19,'MASTER FABRICS'!B:F,5,FALSE) -> 44287 | D19: 6x6 | E19: Social Club | F19: Cocoa | G19: B180876
A20: SD6ZB182786 | B20: =VLOOKUP(E20,'MASTER FABRICS'!B:F,5,FALSE) -> 44287 | D20: 6x6 | E20: Brink | F20: Slate | G20: B182786
A21: SC6ZC152534 | B21: =VLOOKUP(E21,'MASTER FABRICS'!B:F,5,FALSE) -> 42826 | D21: 6x6 | E21: Roma | F21: Cream | G21: C152534
... A81: SM6ZC196584 | B81: =VLOOKUP(E81,'MASTER FABRICS'!B:F,5,FALSE) -> 45017 | D81: 6x6 | E81: Nora | F81: Harbor | G81: C196584
A82: SM6ZC196733 | B82: 45017 | D82: 6x6 | E82: Lunar | F82: Stone | G82: C196733
A83: SM6ZC196755 | B83: 45017 | D83: 6x6 | E83: Lunar | F83: Smoke | G83: C196755
A84: SM6ZC196764 | B84: 45017 | D84: 6x6 | E84: Lunar | F84: Taupe | G84: C196764
A85: SM6ZC196768A | B85: 45017 | D85: 6x6 | E85: Lunar | F85: Mocha | G85: C196768
A86: SM6ZC196786A | B86: 45017 | D86: 6x6 | E86: Lunar | F86: Navy | G86: C196786
A87: SM6ZC202931 | B87: 45383 | D87: 6x6 | E87: Easy | F87: Linen | G87: C202931
A88: SM6ZC202964 | B88: 45383 | D88: 6x6 | E88: Easy | F88: Pebble | G88: C202964
A89: SM6ZC202958 | B89: 45383 | D89: 6x6 | E89: Easy | F89: Stone | G89: C202958
A90: SM6ZC202907 | B90: 45383 | D90: 6x6 | E90: Easy | F90: Brick | G90: C202907
A91: SM6ZC202987 | B91: 45383 | D91: 6x6 | E91: Easy | F91: Midnight | G91: C202987
A92: SM6ZC203260 | B92: 45566 | D92: 6x6 | E92: Reyson | F92: Sand | G92: C203260
A93: SM6ZC203264 | B93: 45566 | D93: 6x6 | E93: Reyson | F93: Taupe | G93: C203264
... A145: SM6ZC212267 | B145: 46113 | D145: 6x6 | E145: Taber | F145: Mushroom | G145: C212267
A146: SM6ZD149415 | B146: =VLOOKUP(E146,'MASTER FABRICS'!B:F,5,FALSE) -> 42826 | D146: 6x6 | E146: Prospect | F146: Currant | G146: D149415
A147: SM6ZD149452 | B147: =VLOOKUP(E147,'MASTER FABRICS'!B:F,5,FALSE) -> 42826 | D147: 6x6 | E147: Prospect | F147: Greystone | G147: D149452
A148: SM6ZD156431 | B148: =VLOOKUP(E148,'MASTER FABRICS'!B:F,5,FALSE) -> 43191 | D148: 6x6 | E148: i-Hallandale | F148: Ivory | G148: D156431
A149: SM6ZD156453 | B149: =VLOOKUP(E149,'MASTER FABRICS'!B:F,5,FALSE) -> 43191 | D149: 6x6 | E149: i-Hallandale | F149: Platinum | G149: D156453
A150: SM6ZD156458 | B150: =VLOOKUP(E150,'MASTER FABRICS'!B:F,5,FALSE) -> 43191 | D150: 6x6 | E150: i-Hallandale | F150: Charcoal | G150: D156458
A151: SM6ZD156464 | B151: =VLOOKUP(E151,'MASTER FABRICS'!B:F,5,FALSE) -> 43191 | D151: 6x6 | E151: i-Hallandale | F151: Wicker | G151: D156464
A152: SM6ZD156487 | B152: =VLOOKUP(E152,'MASTER FABRICS'!B:F,5,FALSE) -> 43191 | D152: 6x6 | E152: i-Hallandale | F152: Admiral | G152: D156487
A153: SM6ZD160454 | B153: =VLOOKUP(E153,'MASTER FABRICS'!B:F,5,FALSE) -> 43374 | D153: 6x6 | E153: i-Outlier | F153: Charcoal | G153: D160454
A154: SM6ZD160458 | B154: =VLOOKUP(E154,'MASTER FABRICS'!B:F,5,FALSE) -> 43374 | D154: 6x6 | E154: i-Outlier | F154: Slate | G154: D160458
A155: SM6ZD160462 | B155: =VLOOKUP(E155,'MASTER FABRICS'!B:F,5,FALSE) -> 43374 | D155: 6x6 | E155: i-Outlier | F155: Mushroom | G155: D160462
A156: SM6ZD160476 | B156: =VLOOKUP(E156,'MASTER FABRICS'!B:F,5,FALSE) -> 43374 | D156: 6x6 | E156: i-Outlier | F156: Ash | G156: D160476
A157: SM6ZD160479 | B157: =VLOOKUP(E157,'MASTER FABRICS'!B:F,5,FALSE) -> 43374 | D157: 6x6 | E157: i-Outlier | F157: Godiva | G157: D160479
... A193: SM6ZD185564 | B193: =VLOOKUP(E193,'MASTER FABRICS'!B:F,5,FALSE) -> 44470 | D193: 6x6 | E193: i-Rivers | F193: Sand | G193: D185564
A194: SM6ZD185552 | B194: 46113 | D194: 6x6 | E194: i-Rivers | F194: Platinum | G194: D185552
A195: SM6ZD185558 | B195: 46113 | D195: 6x6 | E195: i-Rivers | F195: Twilight | G195: D185558
A196: SM6ZD190572 | B196: =VLOOKUP(E196,'MASTER FABRICS'!B:F,5,FALSE) -> 44652 | D196: 6x6 | E196: York | F196: Barley | G196: D190572
A197: SM6ZD190558 | B197: =VLOOKUP(E197,'MASTER FABRICS'!B:F,5,FALSE) -> 44652 | D197: 6x6 | E197: York | F197: Granite | G197: D190558
A198: SM6ZD190554 | B198: =VLOOKUP(E198,'MASTER FABRICS'!B:F,5,FALSE) -> 44652 | D198: 6x6 | E198: York | F198: Quarry | G198: D190554
A199: SM6ZD190574 | B199: =VLOOKUP(E199,'MASTER FABRICS'!B:F,5,FALSE) -> 44652 | D199: 6x6 | E199: York | F199: Bisque | G199: D190574
A200: SM6ZD190531 | B200: =VLOOKUP(E200,'MASTER FABRICS'!B:F,5,FALSE) -> 44652 | D200: 6x6 | E200: York | F200: Cream | G200: D190531
A201: SM6ZD191982 | B201: =VLOOKUP(E201,'MASTER FABRICS'!B:F,5,FALSE) -> 44835 | D201: 6x6 | E201: Florentino | F201: Sky | G201: D191982
A202: SM6ZD191957 | B202: =VLOOKUP(E202,'MASTER FABRICS'!B:F,5,FALSE) -> 44835 | D202: 6x6 | E202: Florentino | F202: Onyx | G202: D191957
A203: SM6ZD191934 | B203: =VLOOKUP(E203,'MASTER FABRICS'!B:F,5,FALSE) -> 44835 | D203: 6x6 | E203: Florentino | F203: Linen | G203: D191934
A204: SM6ZD197034 | B204: =VLOOKUP(E204,'MASTER FABRICS'!B:F,5,FALSE) -> 45017 | D204: 6x6 | E204: Marteon | F204: Natural | G204: D197034
A205: SM6ZD197052 | B205: =VLOOKUP(E205,'MASTER FABRICS'!B:F,5,FALSE) -> 45017 | D205: 6x6 | E205: Marteon | F205: Whisper | G205: D197052
A206: SM6ZD197056 | B206: =VLOOKUP(E206,'MASTER FABRICS'!B:F,5,FALSE) -> 45017 | D206: 6x6 | E206: Marteon | F206: Onyx | G206: D197056
A207: SM6ZD197066 | B207: =VLOOKUP(E207,'MASTER FABRICS'!B:F,5,FALSE) -> 45017 | D207: 6x6 | E207: Marteon | F207: Porcini | G207: D197066
A208: SM6ZD197096 | B208: =VLOOKUP(E208,'MASTER FABRICS'!B:F,5,FALSE) -> 45017 | D208: 6x6 | E208: Marteon | F208: Ocean | G208: D197096
A209: SM6ZD198849 | B209: 45200 | D209: 6x6 | E209: Copenhagen | F209: Caramel | G209: D198849
A210: SM6ZD198872 | B210: 45200 | D210: 6x6 | E210: Copenhagen | F210: Driftwood | G210: D198872
A211: SM6ZD198854 | B211: 45200 | D211: 6x6 | E211: Copenhagen | F211: Bluestone | G211: D198854
A212: SM6ZD200931 | B212: 45383 | D212: 6x6 | E212: Promise | F212: Ecru | G212: D200931
A213: SM6ZD200952 | B213: 45383 | D213: 6x6 | E213: Promise | F213: Oyster | G213: D200952
A214: SM6ZD200972 | B214: 45383 | D214: 6x6 | E214: Promise | F214: Khaki | G214: D200972
A215: SM6ZD200946 | B215: 45383 | D215: 6x6 | E215: Promise | F215: Gold | G215: D200946
A216: SM6ZD200983 | B216: 45383 | D216: 6x6 | E216: Promise | F216: Powder | G216: D200983
A217: SM6ZD200959 | B217: 45383 | D217: 6x6 | E217: Promise | F217: Thunder | G217: D200959
A218: SM6ZD201032 | B218: 45383 | D218: 6x6 | E218: i-Rene | F218: Oat | G218: D201032
A219: SM6ZD201052 | B219: 45383 | D219: 6x6 | E219: i-Rene | F219: Ash | G219: D201052
A220: SM6ZD201065 | B220: 45383 | D220: 6x6 | E220: i-Rene | F220: Mushroom | G220: D201065
... A378: SM6ZD214083 | B378: 46113 | D378: 6x6 | E378: i-Eugene | F378: Lake | G378: D214083
A379: SC6ZE153732 | B379: =VLOOKUP(E379,'MASTER FABRICS'!B:F,5,FALSE) -> 43009 | D379: 6x6 | E379: i-Northwest | F379: Stucco | G379: E153732
A380: SC6ZE153752 | B380: =VLOOKUP(E380,'MASTER FABRICS'!B:F,5,FALSE) -> 43009 | D380: 6x6 | E380: i-Northwest | F380: Dove | G380: E153752
A381: SC6ZE153755 | B381: =VLOOKUP(E381,'MASTER FABRICS'!B:F,5,FALSE) -> 43009 | D381: 6x6 | E381: i-Northwest | F381: Charcoal | G381: E153755
A382: SC6ZE153758 | B382: =VLOOKUP(E382,'MASTER FABRICS'!B:F,5,FALSE) -> 43009 | D382: 6x6 | E382: i-Northwest | F382: Ink | G382: E153758
A383: SC6ZE153765 | B383: =VLOOKUP(E383,'MASTER FABRICS'!B:F,5,FALSE) -> 43009 | D383: 6x6 | E383: i-Northwest | F383: Sable | G383: E153765
A384: SC6ZE153767 | B384: =VLOOKUP(E384,'MASTER FABRICS'!B:F,5,FALSE) -> 43009 | D384: 6x6 | E384: i-Northwest | F384: Mink | G384: E153767
A385: SC6ZE153773 | B385: =VLOOKUP(E385,'MASTER FABRICS'!B:F,5,FALSE) -> 43009 | D385: 6x6 | E385: i-Northwest | F385: Camel | G385: E153773
A386: SC6ZE153775 | B386: =VLOOKUP(E386,'MASTER FABRICS'!B:F,5,FALSE) -> 43009 | D386: 6x6 | E386: i-Northwest | F386: Whiskey | G386: E153775
A387: SM6ZE165133 | B387: =VLOOKUP(E387,'MASTER FABRICS'!B:F,5,FALSE) -> 43556 | D387: 6x6 | E387: i-Broderick | F387: Natural | G387: E165133
A388: SM6ZE165152 | B388: =VLOOKUP(E388,'MASTER FABRICS'!B:F,5,FALSE) -> 43556 | D388: 6x6 | E388: i-Broderick | F388: Charcoal | G388: E165152
A389: SM6ZE165163 | B389: =VLOOKUP(E389,'MASTER FABRICS'!B:F,5,FALSE) -> 43556 | D389: 6x6 | E389: i-Broderick | F389: Hemp | G389: E165163
A390: SM6ZE165181 | B390: =VLOOKUP(E390,'MASTER FABRICS'!B:F,5,FALSE) -> 43556 | D390: 6x6 | E390: i-Broderick | F390: Seaglass | G390: E165181
... A430: SM6ZE197286 | B430: =VLOOKUP(E430,'MASTER FABRICS'!B:F,5,FALSE) -> 45017 | D430: 6x6 | E430: Depiction | F430: Indigo | G430: E197286
A431: SM6ZE201452 | B431: 45383 | D431: 6x6 | E431: Tira | F431: Seashell | G431: E201452
A432: SM6ZE201478 | B432: 45383 | D432: 6x6 | E432: Tira | F432: Bark | G432: E201478
A433: SM6ZE201498 | B433: 45383 | D433: 6x6 | E433: Tira | F433: Dark Teal | G433: E201498
A434: SM6ZE203659 | B434: 45566 | D434: 6x6 | E434: Omni | F434: Slate | G434: E203659
A435: SM6ZE203661 | B435: 45566 | D435: 6x6 | E435: Omni | F435: Taupe | G435: E203661
A436: SM6ZE203675 | B436: 45566 | D436: 6x6 | E436: Omni | F436: Cashew | G436: E203675
A437: SM6ZE203678 | B437: 45566 | D437: 6x6 | E437: Omni | F437: Otter | G437: E203678
A438: SM6ZE203680 | B438: 45566 | D438: 6x6 | E438: Omni | F438: Mist | G438: E203680
A439: SM6ZE204023 | B439: 45566 | D439: 6x6 | E439: I-Gellar | F439: Moss | G439: E204023
A440: SM6ZE204031 | B440: 45566 | D440: 6x6 | E440: I-Gellar | F440: Cotton | G440: E204031
A441: SM6ZE204052 | B441: 45566 | D441: 6x6 | E441: I-Gellar | F441: Granite | G441: E204052
A442: SM6ZE204062 | B442: 45566 | D442: 6x6 | E442: I-Gellar | F442: Marble | G442: E204062
...

Sheet 3x5 Leather
A1: The following swatches for the 3x5 Inline Customer Swatches represent current offerings as of the April 2026 Market.
A2: 6C
F3: Key:
F4: Immediate Drop
F5: Phase Outs
F6: New Phase Outs
F7: April 2026 Drops
A9: Item Number | B9: Intro Date | C9: Date Last Updated | D9: S=Single, C=Correlate, W/F=Waterfall, P/S=Postage Stamp | E9: Pattern Name | F9: Color Name | G9: Cover
A10: SL6BL211758 | B10: 46137 | D10: 3x5 | E10: Majestic Match | F10: Coal | G10: BL211758
A11: SL6BL211763 | B11: 46137 | D11: 3x5 | E11: Majestic Match | F11: Stonewash | G11: BL211763
A12: SL6BL211773 | B12: 46137 | D12: 3x5 | E12: Majestic Match | F12: Butternut | G12: BL211773
A13: SL6BL211778 | B13: 46137 | D13: 3x5 | E13: Majestic Match | F13: Chocolate | G13: BL211778
A14: SL6BL211786 | B14: 46137 | D14: 3x5 | E14: Majestic Match | F14: Blue | G14: BL211786
A15: SL6BL981007 | B15: 43922 | D15: 3x5 | E15: Cozy Match | F15: Wine | G15: BL981007
A16: SL6BL981009 | B16: 43922 | D16: 3x5 | E16: Cozy Match | F16: Pomegranate | G16: BL981009
A17: SL6BL981031 | B17: 45383 | D17: 3x5 | E17: Cozy Match | F17: Oyster | G17: BL981031
A18: SL6BL981036 | B18: 43922 | D18: 3x5 | E18: Cozy Match | F18: Marshmallow | G18: BL981036
A19: SL6BL981050 | B19: 43922 | D19: 3x5 | E19: Cozy Match | F19: Licorice | G19: BL981050
A20: SL6BL981051 | B20: 43922 | D20: 3x5 | E20: Cozy Match | F20: Dusty | G20: BL981051
A21: SL6BL981054 | B21: 43922 | D21: 3x5 | E21: Cozy Match | F21: Putty | G21: BL981054
... A150: SL6LB214176 | B150: 46113 | D150: 3x5 | E150: Chic | F150: Pecan | G150: LB214176
A152: DROPPED
A153: SL6FL152352 | B153: 42826 | D153: 3x5 | E153: Great Smokies | F153: Tin | G153: FL152352
A154: SL6FL152357 | B154: 42826 | D154: 3x5 | E154: Great Smokies | F154: Smoke | G154: FL152357
A155: SL6FL152373 | B155: 42826 | D155: 3x5 | E155: Great Smokies | F155: Gingerbread | G155: FL152373
A156: SL6FL152375 | B156: 42826 | D156: 3x5 | E156: Great Smokies | F156: Pecan | G156: FL152375
A157: SL6FL152379 | B157: 42826 | D157: 3x5 | E157: Great Smokies | F157: Chocolate | G157: FL152379
A158: SL6FL196357 | B158: 45017 | D158: 3x5 | E158: Gramado | F158: Coal | G158: FL196357
A159: SL6FL196373 | B159: 45017 | D159: 3x5 | E159: Gramado | F159: Russet | G159: FL196373
A160: SL6FL196376 | B160: 45017 | D160: 3x5 | E160: Gramado | F160: Cedar | G160: FL196376
A161: SL6FL196379 | B161: 45017 | D161: 3x5 | E161: Gramado | F161: Coffee | G161: FL196379
A162: SL6FL941962 | B162: 44835 | D162: 3x5 | E162: Samba | F162: Clay | G162: FL941962
A163: SL6FL941942 | B163: 44835 | D163: 3x5 | E163: Samba | F163: Marigold | G163: FL941942
A164: SL6FL941908 | B164: 44835 | D164: 3x5 | E164: Samba | F164: Crimson | G164: FL941908
A165: SL6LB180432 | B165: 44652 | D165: 3x5 | E165: Elite | F165: Ice | G165: LB180432

Sheet 2x3 Leather
A1: The following swatches for the 2x3 Inline Customer Swatches represent current offerings as of the April 2026 Market.
A2: LR | F2: Key:
F3: Immediate Drop
A4: SC2 = Custom / Custom Plus | F4: Phase Outs
A5: SL2 = Specialty | F5: New Phase Outs
F6: April 2026 Drops
A8: Item Number 2x3 Swatch | B8: Intro Date | C8: Date Last Updated | D8: Line | E8: Pattern Name | F8: Color Name | G8: Cover1
A9: SC2BL211758 | B9: 46113 | D9: Custom | E9: Majestic Match | F9: Coal | G9: BL211758
A10: SC2BL211763 | B10: 46113 | D10: Custom | E10: Majestic Match | F10: Stonewash | G10: BL211763
A11: SC2BL211773 | B11: 46113 | D11: Custom | E11: Majestic Match | F11: Butternut | G11: BL211773
A12: SC2BL211778 | B12: 46113 | D12: Custom | E12: Majestic Match | F12: Chocolate | G12: BL211778
A13: SC2BL211786 | B13: 46113 | D13: Custom | E13: Majestic Match | F13: Blue | G13: BL211786
A14: SC2BL981007 | B14: 43922 | D14: Custom | E14: Cozy Match | F14: Wine | G14: BL981007
A15: SC2BL981009 | B15: 43922 | D15: Custom | E15: Cozy Match | F15: Pomegranate | G15: BL981009
A16: SC2BL981031 | B16: 45383 | D16: Custom | E16: Cozy Match | F16: Oyster | G16: BL981031
A17: SC2BL981036 | B17: 43922 | D17: Custom | E17: Cozy Match | F17: Marshmallow | G17: BL981036
A18: SC2BL981050 | B18: 43922 | D18: Custom | E18: Cozy Match | F18: Licorice | G18: BL981050
A19: SC2BL981051 | B19: 43922 | D19: Custom | E19: Cozy Match | F19: Dusty | G19: BL981051
A20: SC2BL981054 | B20: 43922 | D20: Custom | E20: Cozy Match | F20: Putty | G20: BL981054
... A53: SC2FL941950 | B53: 39601 | D53: Custom Plus | E53: Samba | F53: Ebony | G53: FL941950
A54: SC2FL941953 | B54: 39601 | C54: 43208 | D54: Custom Plus | E54: Samba | F54: Gray | G54: FL941953
A55: SC2FL941965 | B55: 39601 | D55: Custom Plus | E55: Samba | F55: Cobblestone | G55: FL941965
A56: SC2FL941982 | B56: 39601 | D56: Custom Plus | E56: Samba | F56: Powder Blue | G56: FL941982
A57: SC2FL941987 | B57: 39601 | D57: Custom Plus | E57: Samba | F57: Ultramarine | G57: FL941987
A58: SC2FL941996 | B58: 44835 | D58: Custom Plus | E58: Samba | F58: Aqua | G58: FL941996
A59: SL2HL190677 | B59: 45931 | D59: Specialty | E59: Ankur | F59: Brown | G59: HL190677
A60: SL2HL190673 | B60: 45931 | D60: Specialty | E60: Ankur | F60: Oak | G60: HL190673
A61: SL2HL190675 | B61: 45931 | D61: Specialty | E61: Ankur | F61: Saddle | G61: HL190675
A62: SL2HL190679 | B62: 45931 | D62: Specialty | E62: Ankur | F62: Walnut | G62: HL190679
A63: SL2FL190754 | B63: 45931 | D63: Specialty | E63: Aline | F63: Light Grey | G63: FL190754
A64: SL2FL190736 | B64: 45931 | D64: Specialty | E64: Aline | F64: Stonewash | G64: FL190736
A65: SL2FL190784 | B65: 45931 | D65: Specialty | E65: Aline | F65: Haze | G65: FL190784
A66: SL2FL190787 | B66: 45931 | D66: Specialty | E66: Aline | F66: Dark Blue | G66: FL190787
... A86: SL2FL207886 | B86: 45931 | D86: Specialty | E86: Manchester | F86: Midnight | G86: FL207886
A88: DROPPED
A89: SC2FL941908 | B89: 44835 | D89: Custom Plus | E89: Samba | F89: Crimson | G89: FL941908
A90: SC2FL941942 | B90: 44835 | D90: Custom Plus | E90: Samba | F90: Marigold | G90: FL941942
A91: SC2FL941962 | B91: 44835 | D91: Custom Plus | E91: Samba | F91: Clay | G91: FL941962
A92: SC2FL152352 | B92: 42826 | D92: Custom Plus | E92: Great Smokies | F92: Tin | G92: FL152352
A93: SC2FL152357 | B93: 42826 | D93: Custom Plus | E93: Great Smokies | F93: Smoke | G93: FL152357
A94: SC2FL152373 | B94: 42826 | D94: Custom Plus | E94: Great Smokies | F94: Gingerbread | G94: FL152373
A95: SC2FL152375 | B95: 42826 | D95: Custom Plus | E95: Great Smokies | F95: Pecan | G95: FL152375
A96: SC2FL152379 | B96: 42826 | D96: Custom Plus | E96: Great Smokies | F96: Chocolate | G96: FL152379
A97: SC2FL196357 | B97: 45017 | D97: Custom Plus | E97: Gramado | F97: Coal | G97: FL196357
A98: SC2FL196373 | B98: 45017 | D98: Custom Plus | E98: Gramado | F98: Russet | G98: FL196373
A99: SC2FL196376 | B99: 45017 | D99: Custom Plus | E99: Gramado | F99: Cedar | G99: FL196376
A100: SC2FL196379 | B100: 45017 | D100: Custom Plus | E100: Gramado | F100: Coffee | G100: FL196379

Sheet Custom Leather Plus
A1: The following swatches for the La-Z-Boy Custom Leather Plus represent current offerings as of the April 2026 Market.
A2: EX | J2: Key:
J3: Immediate Drop
A4: Custom Leather Plus (New Logo) | B4: Cover | C4: 000097-A | J4: Phase Outs
A5: Custom Leather Plus (French) | B5: Cover | C5: MS0380FR | J5: New Phase Outs
J6: April 2026 Drops
A8: Item Number | B8: Intro Dates | C8: Date Last Updated | D8: S=Single, C=Correlate, W/F=Waterfall, P/S=Postage Stamp | E8: Pattern Name | F8: Cover1 | G8: Cover2 | H8: Cover3 | I8: Cover4 | J8: Cover5 | K8: Cover6 | L8: Cover7
A9: SCPDL159574 | B9: 43191 | C9: 44652 | D9: P/S | E9: Montana | F9: DL159574 | G9: DL159557
A10: SCPDL159658 | B10: 43191 | D10: P/S | E10: Titan | F10: DL159658 | G10: DL159675 | H10: DL159674 | I10: DL159665 | J10: DL159651
A11: SCPDL213086 | B11: 46113 | D11: P/S | E11: Atlantis | F11: DL213086 | G11: DL213059 | H11: DL213073 | I11: DL213077
A12: SCPFL200359 | B12: 45200 | D12: P/S | E12: Jesi | F12: FL200359 | G12: FL200375 | H12: FL200363 | I12: FL200372 | J12: FL200377 | K12: FL200307
A13: SCPFL202651 | B13: 45383 | D13: P/S | E13: Grandview | F13: FL202651 | G13: FL202698 | H13: FL202659 | I13: FL202675
A14: SCPFL941917 | B14: 44835 | C14: 46113 | D14: P/S | E14: Samba | F14: FL941917 | G14: FL941996 | H14: FL941962 | I14: FL941926 | J14: FL941942 | K14: FL941908 | L14: FL941928
A15: SCPFL941950 | B15: 44835 | D15: P/S | E15: Samba | F15: FL941950 | G15: FL941953 | H15: FL941930 | I15: FL941987 | J15: FL941932 | K15: FL941965 | L15: FL941982
A17: Please remove the following flags from your Custom Leather Plus Collection
A18: SCPFL152379 | B18: 42826 | D18: P/S | E18: Great Smokies | F18: FL152379 | G18: FL152375 | H18: FL152373 | I18: FL152352 | J18: FL152357
A19: SCWFL196357 | B19: 45017 | D19: W/F | E19: Gramado | F19: FL196357 | G19: FL196379 | H19: FL196373 | I19: FL196376

Sheet Custom Leather
A1: The following swatches for the La-Z-Boy Custom Leather Match represent current offerings as of the April 2026 Market.
A2: EX | J2: Key:
J3: Immediate Drop
A4: Custom Leather (New Logo) | B4: Cover | C4: 000096-A | J4: Phase Outs
A5: Custom Leather (French) | B5: Cover | C5: MS0379FR | J5: New Phase Outs
J6: April 2026 Drops
A8: Item Number | B8: Intro Date | C8: Date Last Updated | D8: S=Single, C=Correlate, W/F=Waterfall, P/S=Postage Stamp | E8: Pattern | F8: Cover1 | G8: Cover2 | H8: Cover3 | I8: Cover4 | J8: Cover5 | K8: Cover6 | L8: Cover7
A9: SCPBL211773 | B9: 46113 | D9: P/S | E9: Majestic Match | F9: BL211773 | G9: BL211778 | H9: BL211758 | I9: BL211786 | J9: BL211763
A10: SCPBL981078 | B10: 43922 | D10: P/S | E10: Cozy Match | F10: BL981078 | G10: BL981007 | H10: BL981009 | I10: BL981076 | J10: BL981087
A11: SCPBL981056 | B11: 43922 | D11: P/S | E11: Cozy Match | F11: BL981056 | G11: BL981036 | H11: BL981051 | I11: BL981054 | J11: BL981050
A12: SCPBL981098 | B12: 45383 | D12: P/S | E12: Cozy Match | F12: BL981098 | G12: BL981090 | H12: BL981031
A16: Please remove the following flags from your Custom Leather Collection.

Sheet Specialty Leather Handle
A1: The following swatches for the La-Z-Boy Specialty Leather Collection represent current offerings as of the April 2026 Market.
A4: Specialty Leather 12x12 | B4: Cover | C4: MS0397
A5: Antimicrobial Leather Divider | B5: Divider | C5: MS0398
A6: Analine Leather Divider | B6: Divider | C6: MS0328
A7: iClean Leather Divider | B7: Divider | C7: MS0400
A9: Item Number 12x12 Swatch | B9: Intro Date | C9: Date Last Updated | D9: Pattern Name | E9: Color Name | F9: Cover1
A10: Specialty Leather Cover
A11: Antimicrobial Divider
A12: HL190677 | B12: 44652 | D12: Ankur | E12: Brown | F12: HL190677
A13: HL190673 | B13: 44652 | D13: Ankur | E13: Oak | F13: HL190673
A14: HL190675 | B14: 44652 | D14: Ankur | E14: Saddle | F14: HL190675
A15: HL190679 | B15: 44652 | D15: Ankur | E15: Walnut | F15: HL190679
A16: FL190754 | B16: 44652 | D16: Aline | E16: Light Grey | F16: FL190754
A17: FL190736 | B17: 44652 | D17: Aline | E17: Stonewash | F17: FL190736
A18: FL190784 | B18: 44652 | D18: Aline | E18: Haze | F18: FL190784
A19: FL190787 | B19: 44652 | D19: Aline | E19: Dark Blue | F19: FL190787
A20: FL190758 | B20: 44652 | D20: Aline | E20: Storm | F20: FL190758
A21: FL190777 | B21: 44652 | D21: Aline | E21: Chocolate | F21: FL190777
A22: Aniline Divider
A23: iClean Divider
A24: SL1DL196236 | B24: 45017 | D24: Jazz | E24: Moonbeam | F24: DL196236
A25: SL1DL196258 | B25: 45017 | D25: Jazz | E25: Charcoal | F25: DL196258
A26: SL1DL196275 | B26: 45017 | D26: Jazz | E26: Cinnamon | F26: DL196275
A27: SL1DL196278 | B27: 45017 | D27: Jazz | E27: Coffee | F27: DL196278
A28: SL1DL196286 | B28: 45017 | D28: Jazz | E28: Midnight Blue | F28: DL196286
A29: FL193208 | B29: 44835 | D29: Athena | E29: Burgundy | F29: FL193208
A30: FL193255 | B30: 44835 | D30: Athena | E30: Grey | F30: FL193255
A31: FL193259 | B31: 44835 | D31: Athena | E31: Carbon | F31: FL193259
A32: FL193263 | B32: 44835 | D32: Athena | E32: Ash | F32: FL193263
A33: FL193273 | B33: 44835 | D33: Athena | E33: Oak | F33: FL193273
A34: FL193277 | B34: 44835 | D34: Athena | E34: Brown | F34: FL193277
A35: FL193284 | B35: 44835 | D35: Athena | E35: Granite Grey | F35: FL193284
... A41: SL1FL207886A | B41: 46113 | D41: Manchester | E41: Midnight | F41: FL207886
A45: Please remove the following flags from your La-Z-Boy Specialty Leather swatch set:
A46: SL1FL207886 | B46: 45748 | D46: Manchester | E46: Midnight | F46: FL207886

Sheet Specialty Leather Ring Page
A1: The following swatches for the La-Z-Boy Specialty Leather represent current offerings as of the April 2026 Market.
J2: Key:
A3: Single ring pages can be ordered through EPI using the code in Column A. These offerings are not available as a set and market updates will not be sent out automatically. You can order a cover for the Specialty Ring Pages through EPI with code: MS0406 | J3: Immediate Drop
J4: Phase Outs
J5: New Phase Outs
A6: Specialty Leather Ring Page Cover | C6: MS0406 | J6: April 2026 Drops
A8: Item Number | B8: Intro Dates | C8: Date Last Updated | D8: S=Single, C=Correlate, W/F=Waterfall, P/S=Postage Stamp 2x3=20 | E8: Pattern Name | F8: Cover1 | G8: Cover2 | H8: Cover3 | I8: Cover4 | J8: Cover5 | K8: Cover6 | L8: Cover7
A9: SLPHL190677 | B9: 45931 | D9: P/S | E9: Ankur | F9: HL190677 | G9: HL190673 | H9: HL190675 | I9: HL190679
A10: SLPFL190754 | B10: 45931 | D10: P/S | E10: Aline | F10: FL190754 | G10: FL190736 | H10: FL190784 | I10: FL190787 | J10: FL190758 | K10: FL190777
A11: SLPDL196236 | B11: 45931 | D11: P/S | E11: Jazz | F11: DL196236 | G11: DL196278 | H11: DL196286 | I11: DL196275 | J11: DL196258
A12: SLPFL193277 | B12: 45931 | D12: P/S | E12: Athena | F12: FL193277 | G12: FL193263 | H12: FL193208 | I12: FL193255 | J12: FL193284 | K12: FL193273 | L12: FL193259
A13: SLPFL207825 | B13: 45931 | D13: P/S | E13: Manchester | F13: FL207849 | G13: FL207831 | H13: FL207876 | I13: FL207886 | J13: FL207829 | K13: FL207825
A16: Please remove the following flags from your Specialty Leather Ring Page Collection

Sheet Test Store Hangers
A1: THESE HANGERS ARE NOT AVAILABLE TO ORDER. THEY HAVE ONLY BEEN ADDED TO THE COVER INFORMATION LIST FOR INVOICING PURPOSES. WE ARE UTILIZING THESE HANGERS IN RETAIL TEST STORES ONLY.
A4: Autentic (Tan) | C4: '= A Pure, transparent dyes enhance natural markings such as wrinkles, scars and brands in each Authentic or Aniline hide. The dramatic color variations created are prized as hallmarks of quality and give each piece a distinctive look all its own. All Authentic leathers have a special protective topcoat that maintains the beauty and integrity of the natural characteristics of the hide. | L4: Key:
L5: Immediate Drop
L6: Phase Outs
L7: New Phase Outs
L8: April 2026 Drops
A9: Performance (Teal) | C9: =P The consistent overall color and subtle markings of Performance or protected leathers are created by a variety of techniques, such as embossing, corrective techniques and protective coatings, to improve resistance to soil and enhance their natural beauty.
L10: Specialty Fabric Descriptions
L11: I = iClean
L12: C = Conserve
A13: Nubuck (Blue) | C13: '=N Nubuck leathers are infused with pure, transparent dyes to give them subtle color variations without masking the natural character of the hide such as wrinkles, scars, brands, and other hallmarks of the trail. The result is a unique beauty that’s perfectly at home with today’s way of living. | L13: A = Antimicrobial
L14: PF = Pet Friendly
L15: N = Nanobionic
A17: Item Number | C17: Intro Date | D17: Date Last Updated | E17: S=Single, C=Correlate, W/F=Waterfall, P/S=Postage Stamp | F17: Pattern Name | G17: Line | H17: Specialty Fabric | I17: Performance | J17: Comfort Studio | K17: Custom DC Single Swatch ONLY | L17: Cover1 | M17: Color Names
A18: SRL1BL981007 | B18: 07 | C18: 45566 | E18: S | F18: Cozy Match | G18: Custom | I18: P | L18: BL981007 | M18: Wine
A19: SRL1FL200307 | B19: 07 | C19: 45566 | E19: S | F19: Jesi | G19: Custom Plus | I19: A | L19: FL200307 | M19: Rouge
A20: SRL1FL193208 | B20: 08 | C20: 45566 | E20: S | F20: Athena | G20: Specialty | H20: I | I20: P | L20: FL193208 | M20: Burgundy
A21: SRL1BL981009 | B21: 09 | C21: 45566 | E21: S | F21: Cozy Match | G21: Custom | I21: P | L21: BL981009 | M21: Pomegranate
A22: SRL1FL941917 | B22: 17 | C22: 45566 | E22: S | F22: Samba | G22: Custom Plus | I22: P | L22: FL941917 | M22: Cognac
A23: SRL1FL207825 | B23: 25 | C23: 45383 | E23: S | F23: Manchester | G23: Specialty | H23: I | I23: A | L23: FL207825 | M23: Olive
A24: SRL1FL941926 | B24: 26 | C24: 45566 | E24: S | F24: Samba | G24: Custom Plus | I24: P | L24: FL941926 | M24: Sage
A25: SRL1FL941928 | B25: 28 | C25: 45566 | E25: S | F25: Samba | G25: Custom Plus | I25: P | L25: FL941928 | M25: Hunter
A26: SRL1FL207829 | B26: 29 | C26: 45383 | E26: S | F26: Manchester | G26: Specialty | H26: I | I26: A | L26: FL207829 | M26: Envy
A27: SRL1FL941930 | B27: 30 | C27: 45566 | E27: S | F27: Samba | G27: Custom Plus | I27: P | L27: FL941930 | M27: White
A28: SRL1FL207831 | B28: 31 | C28: 45383 | E28: S | F28: Manchester | G28: Specialty | H28: I | I28: A | L28: FL207831 | M28: Ivory
A29: SRL1BL981031 | B29: 31 | C29: 45566 | E29: S | F29: Cozy Match | G29: Custom | I29: P | L29: BL981031 | M29: Oyster
A30: SRL1FL941932 | B30: 32 | C30: 45566 | E30: S | F30: Samba | G30: Custom Plus | I30: P | L30: FL941932 | M30: Ivory
A31: SRL1FL190736 | B31: 36 | C31: 45566 | E31: S | F31: Aline | G31: Specialty | H31: A | I31: A | L31: FL190736 | M31: Stonewash
A32: SRL1BL981036 | B32: 36 | C32: 45566 | E32: S | F32: Cozy Match | G32: Custom | I32: P | L32: BL981036 | M32: Marshmallow
A33: SRL1DL196236 | B33: 36 | C33: 45566 | E33: S | F33: Jazz | G33: Specialty | H33: I | I33: P | L33: DL196236 | M33: Moonbeam
A34: SRL1FL207849 | B34: 49 | C34: 45383 | E34: S | F34: Manchester | G34: Specialty | H34: I | I34: A | L34: FL207849 | M34: Tan
A35: SRL1BL981050 | B35: 50 | C35: 45566 | E35: S | F35: Cozy Match | G35: Custom | I35: P | L35: BL981050 | M35: Licorice
A36: SRL1FL941950 | B36: 50 | C36: 45566 | E36: S | F36: Samba | G36: Custom Plus | I36: P | L36: FL941950 | M36: Ebony
A37: SRL1BL981051 | B37: 51 | C37: 45566 | E37: S | F37: Cozy Match | G37: Custom | I37: P | L37: BL981051 | M37: Dusty
A38: SRL1FL202651 | B38: 51 | C38: 45566 | E38: S | F38: Grandview | G38: Custom Plus | I38: A | L38: FL202651 | M38: Dove Grey
A39: SRL1DL159651 | B39: 51 | C39: 45566 | E39: S | F39: Titan | G39: Custom Plus | I39: A | L39: DL159651 | M39: Platinum
A40: SRL1FL941953 | B40: 53 | C40: 45566 | E40: S | F40: Samba | G40: Custom Plus | I40: P | L40: FL941953 | M40: Gray
A41: SRL1FL190754 | B41: 54 | C41: 45566 | E41: S | F41: Aline | G41: Specialty | H41: A | I41: A | L41: FL190754 | M41: Light Grey
A42: SRL1BL981054 | B42: 54 | C42: 45566 | E42: S | F42: Cozy Match | G42: Custom | I42: P | L42: BL981054 | M42: Putty
A43: SRL1FL193255 | B43: 55 | C43: 45566 | E43: S | F43: Athena | G43: Specialty | H43: I | I43: P | L43: FL193255 | M43: Grey
A44: SRL1BL981056 | B44: 56 | C44: 45566 | E44: S | F44: Cozy Match | G44: Custom | I44: P | L44: BL981056 | M44: Grey
A45: SRL1DL159557 | B45: 57 | C45: 45566 | E45: S | F45: Montana | G45: Custom Plus | I45: N | L45: DL159557 | M45: Charcoal
A46: SRL1BL211758 | B46: 58 | C46: 46113 | E46: S | F46: Majestic Match | G46: Custom | I46: A | L46: BL211758 | M46: Coal
A47: SRL1FL190758 | B47: 58 | C47: 45566 | E47: S | F47: Aline | G47: Specialty | H47: A | I47: A | L47: FL190758 | M47: Storm
A48: SRL1DL196258 | B48: 58 | C48: 45566 | E48: S | F48: Jazz | G48: Specialty | H48: I | I48: P | L48: DL196258 | M48: Charcoal
A49: SRL1DL159658 | B49: 58 | C49: 45566 | E49: S | F49: Titan | G49: Custom Plus | I49: A | L49: DL159658 | M49: Charcoal
A50: SRL1DL213059 | B50: 59 | C50: 46113 | E50: S | F50: Atlantis | G50: Custom Plus | I50: A | L50: DL213059 | M50: Ash
A51: SRL1FL193259 | B51: 59 | C51: 45566 | E51: S | F51: Athena | G51: Specialty | H51: I | I51: P | L51: FL193259 | M51: Carbon
A52: SRL1FL202659 | B52: 59 | C52: 45566 | E52: S | F52: Grandview | G52: Custom Plus | I52: A | L52: FL202659 | M52: Otter
A53: SRL1FL200359 | B53: 59 | C53: 45566 | E53: S | F53: Jesi | G53: Custom Plus | I53: A | L53: FL200359 | M53: Otter
A54: SRL1BL211763 | B54: 63 | C54: 46113 | E54: S | F54: Majestic Match | G54: Custom | I54: A | L54: BL211763 | M54: Stonewash
A55: SRL1FL193263 | B55: 63 | C55: 45566 | E55: S | F55: Athena | G55: Specialty | H55: I | I55: P | L55: FL193263 | M55: Ash
A56: SRL1FL200363 | B56: 63 | C56: 45566 | E56: S | F56: Jesi | G56: Custom Plus | I56: A | L56: FL200363 | M56: Stone
A57: SRL1FL941965 | B57: 65 | C57: 45566 | E57: S | F57: Samba | G57: Custom Plus | I57: P | L57: FL941965 | M57: Cobblestone
A58: SRL1DL159665 | B58: 65 | C58: 45566 | E58: S | F58: Titan | G58: Custom Plus | I58: A | L58: DL159665 | M58: Clay
A59: SRL1FL200372 | B59: 72 | C59: 45566 | E59: S | F59: Jesi | G59: Custom Plus | I59: A | L59: FL200372 | M59: Barley
A60: SRL1BL211773 | B60: 73 | C60: 46113 | E60: S | F60: Majestic Match | G60: Custom | I60: A | L60: BL211773 | M60: Butternut
A61: SRL1DL213073 | B61: 73 | C61: 46113 | E61: S | F61: Atlantis | G61: Custom Plus | I61: A | L61: DL213073 | M61: Russet
A62: SRL1HL190673 | B62: 73 | C62: 45566 | E62: S | F62: Ankur | G62: Specialty | H62: A | I62: A | L62: HL190673 | M62: Oak
A63: SRL1FL193273 | B63: 73 | C63: 45566 | E63: S | F63: Athena | G63: Specialty | H63: I | I63: P | L63: FL193273 | M63: Oak
A64: SRL1DL159574 | B64: 74 | C64: 45566 | E64: S | F64: Montana | G64: Custom Plus | I64: N | L64: DL159574 | M64: Camel
A65: SRL1DL159674 | B65: 74 | C65: 45566 | E65: S | F65: Titan | G65: Custom Plus | I65: A | L65: DL159674 | M65: Cinnamon
A66: SRL1HL190675 | B66: 75 | C66: 45566 | E66: S | F66: Ankur | G66: Specialty | H66: A | I66: A | L66: HL190675 | M66: Saddle
A67: SRL1FL202675 | B67: 75 | C67: 45566 | E67: S | F67: Grandview | G67: Custom Plus | I67: A | L67: FL202675 | M67: Chestnut
A68: SRL1DL196275 | B68: 75 | C68: 45566 | E68: S | F68: Jazz | G68: Specialty | H68: I | I68: P | L68: DL196275 | M68: Cinnamon
A69: SRL1FL200375 | B69: 75 | C69: 45566 | E69: S | F69: Jesi | G69: Custom Plus | I69: A | L69: FL200375 | M69: Khaki
A70: SRL1DL159675 | B70: 75 | C70: 45566 | E70: S | F70: Titan | G70: Custom Plus | I70: A | L70: DL159675 | M70: Chocolate
A71: SRL1BL981076 | B71: 76 | C71: 45566 | E71: S | F71: Cozy Match | G71: Custom | I71: P | L71: BL981076 | M71: Walnut
A72: SRL1FL207876 | B72: 76 | C72: 45383 | E72: S | F72: Manchester | G72: Specialty | H72: I | I72: A | L72: FL207876 | M72: Toffee
A73: SRL1DL213077 | B73: 77 | C73: 46113 | E73: S | F73: Atlantis | G73: Custom Plus | I73: A | L73: DL213077 | M73: Dark Brown
A74: SRL1FL190777 | B74: 77 | C74: 45566 | E74: S | F74: Aline | G74: Specialty | H74: A | I74: A | L74: FL190777 | M74: Chocolate
A75: SRL1HL190677 | B75: 77 | C75: 45566 | E75: S | F75: Ankur | G75: Specialty | H75: A | I75: A | L75: HL190677 | M75: Brown
A76: SRL1FL193277 | B76: 77 | C76: 45566 | E76: S | F76: Athena | G76: Specialty | H76: I | I76: P | L76: FL193277 | M76: Brown
A77: SRL1FL200377 | B77: 77 | C77: 45566 | E77: S | F77: Jesi | G77: Custom Plus | I77: A | L77: FL200377 | M77: Sepia
A78: SRL1BL211778 | B78: 78 | C78: 46113 | E78: S | F78: Majestic Match | G78: Custom | I78: A | L78: BL211778 | M78: Chocolate
A79: SRL1BL981078 | B79: 78 | C79: 45566 | E79: S | F79: Cozy Match | G79: Custom | I79: P | L79: BL981078 | M79: Tobacco
A80: SRL1DL196278 | B80: 78 | C80: 45566 | E80: S | F80: Jazz | G80: Specialty | H80: I | I80: P | L80: DL196278 | M80: Coffee
A81: SRL1HL190679 | B81: 79 | C81: 45566 | E81: S | F81: Ankur | G81: Specialty | H81: A | I81: A | L81: HL190679 | M81: Walnut
A82: SRL1FL941982 | B82: 82 | C82: 45566 | E82: S | F82: Samba | G82: Custom Plus | I82: P | L82: FL941982 | M82: Powder Blue
A83: SRL1FL190784 | B83: 84 | C83: 45566 | E83: S | F83: Aline | G83: Specialty | H83: A | I83: A | L83: FL190784 | M83: Haze
A84: SRL1FL193284 | B84: 84 | C84: 45566 | E84: S | F84: Athena | G84: Specialty | H84: I | I84: P | L84: FL193284 | M84: Granite Grey
A85: SRL1BL211786 | B85: 86 | C85: 46113 | E85: S | F85: Majestic Match | G85: Custom | I85: A | L85: BL211786 | M85: Blue
A86: SRL1DL196286 | B86: 86 | C86: 45566 | E86: S | F86: Jazz | G86: Specialty | H86: I | I86: P | L86: DL196286 | M86: Midnight Blue
A87: SRL1DL213086 | B87: 86 | C87: 46113 | E87: S | F87: Atlantis | G87: Custom Plus | I87: A | L87: DL213086 | M87: Marine
A88: SRL1FL207886A | B88: 86 | C88: 46113 | E88: S | F88: Manchester | G88: Specialty | H88: I | I88: A | L88: FL207886 | M88: Midnight
A89: SRL1FL190787 | B89: 87 | C89: 45566 | E89: S | F89: Aline | G89: Specialty | H89: A | I89: A | L89: FL190787 | M89: Dark Blue
A90: SRL1BL981087 | B90: 87 | C90: 45566 | E90: S | F90: Cozy Match | G90: Custom | I90: P | L90: BL981087 | M90: Blueberry
A91: SRL1FL941987 | B91: 87 | C91: 45566 | E91: S | F91: Samba | G91: Custom Plus | I91: P | L91: FL941987 | M91: Ultramarine
A92: SRL1BL981090 | B92: 90 | C92: 45566 | E92: S | F92: Cozy Match | G92: Custom | I92: P | L92: BL981090 | M92: Seafoam
A93: SRL1FL941996 | B93: 96 | C93: 45566 | E93: S | F93: Samba | G93: Custom Plus | I93: P | L93: FL941996 | M93: Aqua
A94: SRL1BL981098 | B94: 98 | C94: 45566 | E94: S | F94: Cozy Match | G94: Custom | I94: P | L94: BL981098 | M94: Arctic Blue
A95: SRL1FL202698 | B95: 98 | C95: 45566 | E95: S | F95: Grandview | G95: Custom Plus | I95: A | L95: FL202698 | M95: Ocean
A97: Please remove the following flags from your La-Z-Boy Design Center Collection swatch set:
A98: SRL1FL941908 | B98: 08 | C98: 45566 | E98: S | F98: Samba | G98: Custom Plus | I98: P | L98: FL941908 | M98: Crimson
A99: SRL1FL941942 | B99: 42 | C99: 45566 | E99: S | F99: Samba | G99: Custom Plus | I99: P | L99: FL941942 | M99: Marigold
A100: SRL1FL152352 | B100: 52 | C100: 45566 | E100: S | F100: Great Smokies | G100: Custom Plus | I100: A | L100: FL152352 | M100: Tin
A101: SRL1FL152357 | B101: 57 | C101: 45566 | E101: S | F101: Great Smokies | G101: Custom Plus | I101: A | L101: FL152357 | M101: Smoke
A102: SRL1FL196357 | B102: 57 | C102: 45566 | E102: S | F102: Gramado | G102: Custom Plus | I102: A | L102: FL196357 | M102: Coal
A103: SRL1FL941962 | B103: 62 | C103: 45566 | E103: S | F103: Samba | G103: Custom Plus | I103: P | L103: FL941962 | M103: Clay
A104: SRL1FL152373 | B104: 73 | C104: 45566 | E104: S | F104: Great Smokies | G104: Custom Plus | I104: A | L104: FL152373 | M104: Gingerbread
...

Sheet Select Stationary Leather
A1: The following swatches for the La-Z-Boy Select Stationary Leather Collection represent current offerings as of the April 2026 Market.
A2: SI | G2: Key:
G3: Immediate Drop
A4: Select Stationary Leather (New Logo) | B4: Cover | C4: 000095-A | G4: Phase Outs
A5: Select Stationary Leather (French) | B5: Cover | C5: MS0378FR | G5: New Phase Outs
A6: Select Stationary Leather Divider | B6: Divider | C6: MS0386 | G6: April 2026 Drops
G7: April 2026 New Selects
A9: Item Number | B9: Intro Date | C9: Date Last Updated | D9: S=Single, C=Correlate, W/F=Waterfall, P/S=Postage Stamp | E9: Pattern Name | F9: Color Name | G9: Cover1 | H9: Left Corner Label | I9: Cover3 | J9: Cover4 | K9: Cover5 | L9: Cover6 | M9: Additional Comments
A10: SL1LB206032A | B10: 45931 | D10: 12x12 | E10: Sutton | F10: Ivory | G10: LB206032 | H10: 435 Mackenzie; 603 Wilmette; 613 Olson; 636 Shiloh; 638 Charlie
A11: SL1LB206054A | B11: 45931 | D11: 12x12 | E11: Sutton | F11: Greystone | G11: LB206054 | H11: 435 Mackenzie; 603 Wilmette; 613 Olson; 636 Shiloh; 638 Charlie
A12: SL1LB206077B | B12: 45931 | D12: 12x12 | E12: Sutton | F12: Cognac | G12: LB206077 | H12: 435 Mackenzie; 603 Wilmette; 613 Olson; 636 Shiloh; 638 Charlie
A13: SL1LB206087B | B13: 45931 | D13: 12x12 | E13: Sutton | F13: Navy | G13: LB206087 | H13: 435 Mackenzie; 603 Wilmette; 613 Olson; 636 Shiloh; 638 Charlie
A15: Please remove the following 12x12 Swatches from your Select Leather Stationary Collection

Sheet Select Reclining Leather
A1: The following swatches for the La-Z-Boy Select Reclining Leather Collection represent current offerings as of the April 2026 Market.
A2: HR
I3: Key:
A4: Select Reclining Leather (New Logo) | B4: Cover | C4: 000094-A | I4: Immediate Drop
A5: Select Reclining Leather (French) | B5: Cover | C5: MS0377FR | I5: Phase Outs
A6: Select Reclining Leather | B6: Divider | C6: MS0385 | I6: New Phase Outs
I7: April 2026 Drops
I8: April 2026 New Selects
A10: Item Number | B10: Intro Date | C10: Date Last Updated | D10: S=Single, C=Correlate, W/F=Waterfall, P/S=Postage Stamp | E10: Pattern Name | F10: Color Name | G10: Style | H10: Cover1 | I10: Comments
A11: SL1LB152056 | B11: 43009 | D11: 12x12 | E11: Yellowstone | F11: Charcoal | G11: 521 James | H11: LB152056
A12: SL1LB152078 | B12: 42826 | D12: 12x12 | E12: Yellowstone | F12: Walnut | G12: 521 James | H12: LB152078
A13: SL1LB159058-A | B13: 44835 | D13: 12x12 | E13: Cranbrook | F13: Shitake | G13: 519 Astor | H13: LB159058
A14: SL1LB159079-A | B14: 44835 | D14: 12x12 | E14: Cranbrook | F14: Chestnut | G14: 519 Astor | H14: LB159079
A15: SL1LB160175 | B15: 43556 | D15: 12x12 | E15: Delray | F15: Harvest | G15: 777 Randell | H15: LB160175
A16: SL1LB160179A | B16: 46113 | D16: 12x12 | E16: Delray | F16: Dk Chocolate | G16: 777 Randell | H16: LB160179
A17: SL1LB164809 | B17: 43556 | C17: 45383 | D17: 12x12 | E17: Prestige | F17: Wine | G17: 776 Redwood | H17: LB164809
A18: SL1LB164854 | B18: 43556 | D18: 12x12 | E18: Prestige | F18: Grey | G18: 722 Roman | H18: LB164854 | I18: heavy gauge top stitching
A19: SL1LB164879 | B19: 43556 | C19: 45383 | D19: 12x12 | E19: Prestige | F19: Chocolate | G19: 776 Redwood; 722 Roman - heavy top stitching only | H19: LB164879 | I19: heavy gauge top stitching
A20: SL1LB172755-A | B20: 43922 | D20: 12x12 | E20: Intermingle | F20: Grey | G20: 724 Trouper | H20: LB172755 | I20: heavy gauge top stitching
A21: SL1LB172779 | B21: 43739 | D21: 12x12 | E21: Intermingle | F21: Walnut | G21: 724 Trouper | H21: LB172779 | I21: heavy gauge top stitching
A22: SL1LB172856 | B22: 43922 | D22: 12x12 | E22: Goshen | F22: Grey | G22: 502 Joshua | H22: LB172856
A23: SL1LB172878 | B23: 43739 | D23: 12x12 | E23: Goshen | F23: Chestnut | G23: 502 Joshua | H23: LB172878
A24: SL1LB180459A | B24: 45200 | D24: 12x12 | E24: Elite | F24: Charcoal | G24: 762 Neo | H24: LB180459 | I24: heavy gauge top stitching
A25: SL1LB180474 | B25: 44287 | C25: 45931 | D25: 12x12 | E25: Elite | F25: Cognac | G25: 762 Neo | H25: LB180474 | I25: heavy gauge top stitching
A26: SL1LB184964 | B26: 44470 | D26: 12x12 | E26: Lota | F26: Pebble | G26: 786 Liam | H26: LB184964
A27: SL1LB184978 | B27: 44470 | D27: 12x12 | E27: Lota | F27: Espresso | G27: 786 Liam | H27: LB184978
A28: SL1LB185158A | B28: 45383 | D28: 12x12 | E28: Camaraderie | F28: Pewter | G28: 781 Emmons | H28: LB185158
A29: SL1LB185175A | B29: 45383 | D29: 12x12 | E29: Camaraderie | F29: Oak | G29: 781 Emmons | H29: LB185175
A30: SL1LB192935 | B30: 45017 | D30: 12x12 | E30: Topflight | F30: Ivory | G30: 769 Ava | H30: LB192935
A31: SL1LB192959 | B31: 45017 | D31: 12x12 | E31: Topflight | F31: Slate | G31: 759 Maddox | H31: LB192959 | I31: heavy gauge top stitching
A32: SL1LB192976 | B32: 45017 | D32: 12x12 | E32: Topflight | F32: Camel | G32: 759 Maddox | H32: LB192976 | I32: heavy gauge top stitching
A33: SL1LB192976A | B33: 45748 | D33: 12x12 | E33: Topflight | F33: Camel | G33: 804 Belmont | H33: LB192976
A34: SL1LB192979 | B34: 45017 | C34: 45748 | D34: 12x12 | E34: Topflight | F34: Mineral | G34: 769 Ava; 804 Belmont | H34: LB192979
A35: SL1LB193056 | B35: 44835 | C35: 45017 | D35: 12x12 | E35: Salvo | F35: Blue Grey | G35: 757 Apollo; 530 Greyson | H35: LB193056 | I35: decorative top stitching; heavy gauge top stitching
A36: SL1LB193059 | B36: 44835 | D36: 12x12 | E36: Salvo | F36: Slate | G36: 757 Apollo | H36: LB193059 | I36: decorative top stitching
A37: SL1LB193077 | B37: 44835 | C37: 45017 | D37: 12x12 | E37: Salvo | F37: Caramel | G37: 757 Apollo; 530 Greyson | H37: LB193077 | I37: decorative top stitching; heavy gauge top stitching
A38: SL1LB202651 | B38: 45383 | D38: 12x12 | E38: Grandview | F38: Dove Grey | G38: 712 Sparrow | H38: LB202651
A39: SL1LB202659 | B39: 45383 | D39: 12x12 | E39: Grandview | F39: Otter | G39: 712 Sparrow | H39: LB202659
A40: SL1LB202675 | B40: 45383 | D40: 12x12 | E40: Grandview | F40: Chestnut | G40: 712 Sparrow | H40: LB202675
A41: SL1LB206032 | B41: 45566 | D41: 12x12 | E41: Sutton | F41: Ivory | G41: 812 Armitage | H41: LB206032
A42: SL1LB206054 | B42: 45566 | D42: 12x12 | E42: Sutton | F42: Greystone | G42: 812 Armitage | H42: LB206054
A43: SL1LB206077 | B43: 45566 | D43: 12x12 | E43: Sutton | F43: Cognac | G43: 715 Kodie; 812 Armitage | H43: LB206077
A44: SL1LB206087 | B44: 45566 | D44: 12x12 | E44: Sutton | F44: Navy | G44: 715 Kodie | H44: LB206087
A45: SL1LB206077A | B45: 45748 | D45: 12x12 | E45: Sutton | F45: Cognac | G45: 813 Clybourn -heavy top stitching only | H45: LB206077 | I45: heavy gauge top stitching
A46: SL1LB206087A | B46: 45748 | D46: 12x12 | E46: Sutton | F46: Navy | G46: 813 Clybourn -heavy top stitching only | H46: LB206087 | I46: heavy gauge top stitching
A47: SL1LB206132 | B47: 45566 | C47: 45931 | D47: 12x12 | E47: Gambit | F47: Oyster | G47: 765 Rowan; 803 Cade | H47: LB206132
A48: SL1LB206150 | B48: 45566 | D48: 12x12 | E48: Gambit | F48: Onyx | G48: 747 Finley | H48: LB206150
A49: SL1LB206159 | B49: 45566 | D49: 12x12 | E49: Gambit | F49: Graphite | G49: 765 Rowan | H49: LB206159
A50: SL1LB206175 | B50: 45566 | C50: 45931 | D50: 12x12 | E50: Gambit | F50: Stone | G50: 747 Finley; 803 Cade | H50: LB206175
A51: SL1LB206178 | B51: 45566 | C51: 45931 | D51: 12x12 | E51: Gambit | F51: Otter | G51: 747 Finley; 765 Rowan | H51: LB206178
A52: SL1LB206219 | B52: 45566 | D52: 12x12 | E52: Clifton | F52: Chestnut | G52: 810 Quinault | H52: LB206219
A53: SL1LB206229 | B53: 45566 | D53: 12x12 | E53: Clifton | F53: Olive | G53: 810 Quinault | H53: LB206229
A54: SL1LB206278 | B54: 45566 | C54: 45931 | D54: 12x12 | E54: Clifton | F54: Walnut | G54: 582 Maverick; 717 Fulton; 802 Cassian | H54: LB206278
A55: SL1LB206279 | B55: 45566 | C55: 45931 | D55: 12x12 | E55: Clifton | F55: Dark Chocolate | G55: 582 Maverick; 717 Fulton; 802 Cassian; 810 Quinault | H55: LB206279
A56: SL1LB206376 | B56: 45566 | D56: 12x12 | E56: Dean | F56: Chestnut | G56: 782 Kells; 811 Acadia -heavy top stitching only | H56: LB206376 | I56: heavy gauge top stitching
A57: SL1LB206379 | B57: 45566 | D57: 12x12 | E57: Dean | F57: Shitake | G57: 782 Kells; 811 Acadia -heavy top stitching only | H57: LB206379 | I57: heavy gauge top stitching
A58: SL1LB206332 | B58: 45748 | C58: 45931 | D58: 12x12 | E58: Dean | F58: Oyster | G58: 800 Palmer; 820 Norton | H58: LB206332
A59: SL1LB206357 | B59: 45748 | C59: 45931 | D59: 12x12 | E59: Dean | F59: Blue Grey | G59: 800 Palmer; 820 Norton | H59: LB206357
A60: SL1LB206377 | B60: 45748 | C60: 45931 | D60: 12x12 | E60: Dean | F60: Walnut | G60: 800 Palmer; 820 Norton | H60: LB206377
A61: SL1LB206474 | B61: 45566 | C61: 45748 | D61: 12x12 | E61: Opulence | F61: Stone | G61: 512 Pinnacle; 709 Jasper | H61: LB206474
A62: SL1LB206477 | B62: 45566 | C62: 45748 | D62: 12x12 | E62: Opulence | F62: Umber | G62: 512 Pinnacle; 709 Jasper | H62: LB206477
A63: SL1LB211258 | B63: 45931 | D63: 12x12 | E63: Highbrow | F63: Blue Grey | G63: 807 Baron -heavy top stitching only | H63: LB211258 | I63: heavy gauge top stitching
A64: SL1LB211275 | B64: 45931 | D64: 12x12 | E64: Highbrow | F64: Mocha | G64: 755 Dorian; 807 Baron -heavy top stitching only | H64: LB211275 | I64: heavy gauge top stitching
A65: SL1LB211278 | B65: 45931 | D65: 12x12 | E65: Highbrow | F65: Mineral | G65: 755 Dorian; 807 Baron -heavy top stitching only | H65: LB211278 | I65: heavy gauge top stitching
A66: SL1LB211268 | B66: 46113 | D66: 12x12 | E66: Highbrow | F66: Slate | G66: 757 Apollo -decorative top stitching only | H66: LB211268 | I66: decorative top stitching
A67: SL1LB211276 | B67: 46113 | D67: 12x12 | E67: Highbrow | F67: Chestnut | G67: 757 Apollo -decorative top stitching only | H67: LB211276 | I67: decorative top stitching
A68: SL1LB211376 | B68: 45931 | C68: 46113 | D68: 12x12 | E68: Roberto | F68: Chocolate | G68: 530 Greyson -heavy top stitching only; 805 Ace -heavy top stitching only | H68: LB211376 | I68: heavy gauge top stitching
A69: SL1LB211379 | B69: 45931 | C69: 46113 | D69: 12x12 | E69: Roberto | F69: Slate | G69: 530 Greyson -heavy top stitching only; 805 Ace -heavy top stitching only | H69: LB211379 | I69: heavy gauge top stitching
A70: SL1LB211331 | B70: 46113 | D70: 12x12 | E70: Roberto | F70: Ice | G70: 530 Greyson -heavy top stitching only | H70: LB211331 | I70: heavy gauge top stitching
A71: SL1LB213659 | B71: 46113 | D71: 12x12 | E71: Bellingham | F71: Coal | G71: 826 Sammy | H71: LB213659
A72: SL1LB213679 | B72: 46113 | D72: 12x12 | E72: Bellingham | F72: Moreno | G72: 826 Sammy | H72: LB213679
A73: SL1LB213758 | B73: 46113 | D73: 12x12 | E73: Rhythmic | F73: Charcoal | G73: 828 Dutton | H73: LB213758
A74: SL1LB213777 | B74: 46113 | D74: 12x12 | E74: Rhythmic | F74: Mocha | G74: 828 Dutton | H74: LB213777
A75: SL1LB214159 | B75: 46113 | D75: 12x12 | E75: Chic | F75: Slate | G75: A86 Ovation | H75: LB214159
A76: SL1LB214176 | B76: 46113 | D76: 12x12 | E76: Chic | F76: Pecan | G76: A86 Ovation | H76: LB214176
A79: Please remove the following 12x12 swatches from your Select Leather Reclining Collection
A80: SL1LB160179 | B80: 43556 | C80: 45017 | D80: 12x12 | E80: Delray | F80: Dk Chocolate | G80: 777 Randell | H80: LB160179
A81: SL1LB164663 | B81: 43556 | D81: 12x12 | E81: Vacation | F81: Beige | G81: 704 Reed | H81: LB164663
A82: SL1LB164677 | B82: 43556 | D82: 12x12 | E82: Vacation | F82: Walnut | G82: 704 Reed | H82: LB164677
A83: SL1LB180432 | B83: 44652 | D83: 12x12 | E83: Elite | F83: Ice | G83: 787 Lennon | H83: LB180432
A84: SL1LB180459 | B84: 44652 | D84: 12x12 | E84: Elite | F84: Charcoal | G84: 787 Lennon | H84: LB180459
A85: SL1LB193032 | B85: 45017 | D85: 12x12 | E85: Salvo | F85: Ice | G85: 530 Greyson | H85: LB193032 | I85: heavy gauge top stitching

Sheet Select Fabrics 12 x 12
A1: The following swatches for the Select Fabric 12x12 represent current offerings as of the April 2026 Market.
A2: CS | G2: Key:
G3: Immediate Drop
G4: Phase Outs
G5: New Phase Outs
G6: April 2026 Drops
G7: April 2026 New Selects
A9: Item Number | B9: Intro Date | C9: Date Last Updated | D9: S=Single, C=Correlate, W/F=Waterfall, P/S=Postage Stamp | E9: Pattern Name | F9: Color Name | G9: Style | H9: Cover1 | I9: Cover2 | J9: Cover3 | K9: Cover4 | L9: Cover5 | M9: Cover6 | N9: Comments | O9: Phase Out Note
A10: SK1ZE153732 | B10: 43009 | D10: 12x12 | E10: i-Northwest | F10: Stucco | G10: 724 Trouper | H10: E153732 | N10: heavy gauge stitching
A11: SK1ZE153752 | B11: 44835 | D11: 12x12 | E11: i-Northwest | F11: Dove | G11: 724 Trouper | H11: E153752 | N11: heavy gauge stitching
A12: SK1ZE153755 | B12: 44835 | D12: 12x12 | E12: i-Northwest | F12: Charcoal | G12: 724 Trouper | H12: E153755 | N12: heavy gauge stitching
A13: SK1ZE153758 | B13: 43009 | D13: 12x12 | E13: i-Northwest | F13: Ink | G13: 724 Trouper | H13: E153758 | N13: heavy gauge stitching
A14: SK1ZE153765 | B14: 43009 | D14: 12x12 | E14: i-Northwest | F14: Sable | G14: 724 Trouper | H14: E153765 | N14: heavy gauge stitching
A15: SK1ZE153767 | B15: 43009 | D15: 12x12 | E15: i-Northwest | F15: Mink | G15: 724 Trouper | H15: E153767 | N15: heavy gauge stitching
A16: SK1ZE153773 | B16: 44835 | D16: 12x12 | E16: i-Northwest | F16: Camel | G16: 724 Trouper | H16: E153773 | N16: heavy gauge stitching
A17: SK1ZE153775 | B17: 43009 | D17: 12x12 | E17: i-Northwest | F17: Whiskey | G17: 724 Trouper | H17: E153775 | N17: heavy gauge stitching
A19: DROPPED
A20: SK1ZD126759 | B20: 45017 | D20: 12x12 | E20: Denver | F20: Tar | G20: 724 Trouper | H20: D126759 | N20: heavy gauge stitching
A21: SK1ZD126738 | B21: 45017 | D21: 12x12 | E21: Denver | F21: Silt | G21: 724 Trouper | H21: D126738 | N21: heavy gauge stitching
A22: SK1ZD126768 | B22: 45017 | D22: 12x12 | E22: Denver | F22: Marble | G22: 724 Trouper | H22: D126768 | N22: heavy gauge stitching
A23: SK1ZD126772 | B23: 45017 | D23: 12x12 | E23: Denver | F23: Fawn | G23: 724 Trouper | H23: D126772 | N23: heavy gauge stitching
A24: SK1ZD126778 | B24: 45017 | D24: 12x12 | E24: Denver | F24: Canyon | G24: 724 Trouper | H24: D126778 | N24: heavy gauge stitching

Sheet Cut and Sewn Fabric Waterfalls
A1: The following swatches for the Cut & Sewn Fabric Waterfall Cards represent current offerings as of the April 2026 Market.
A2: KW | I2: Key:
I3: Immediate Drop
I4: Phase Outs
I5: New Phase Outs
I6: April 2026 Drops
I7: April 2026 New Selects
A9: Item Number | B9: Intro Date | C9: Date Last Updated | D9: W/F=Waterfall | E9: Pattern Name | H9: Style | I9: Cover1 | J9: Cover2 | K9: Cover3 | L9: Cover4 | M9: Cover5 | N9: Cover6 | O9: Cover7 | P9: Cover11 | Q9: Cover12 | R9: Cover13 | S9: Cover14 | T9: Cover15 | U9: Cover16 | V9: Cover17 | W9: Notes
A10: SKWFZB1538 | B10: 43009 | C10: 45383 | D10: W/F | E10: Seamount | H10: 766 Morrison; 403 Vail | I10: B153876 | J10: B153874 | K10: B153808 | L10: B153853 | M10: B153885
A11: SKWFZB1808 | B11: 44287 | C11: 45931 | D11: W/F | E11: Social Club | H11: 418 Leah; 761 Joel; 800 Palmer; 820 Norton; 899 Bennett | I11: B180857 | J11: B180876 | K11: B180868 | L11: B180852 | M11: B180872
A12: SKWFZC1525 | B12: 42826 | C12: 45200 | D12: W/F | E12: Roma | H12: 777 Randell; 722 Roman | I12: C152553 | J12: C152578 | K12: C152574 | L12: C152586 | M12: C152534
A13: SKWFZC1625 | B13: 43374 | D13: W/F | E13: Vance | H13: 709 Jasper | I13: C162532 | J13: C162527 | K13: C162586 | L13: C162552 | M13: C162576 | N13: C162508
A14: SKWFZC1700 | B14: 43739 | C14: 46113 | D14: W/F | E14: Nico | H14: 765 Rowan; 893 Colby | I14: C170053 | J14: C170057 | K14: C170033
A15: SKWFZC1754 | B15: 43922 | C15: 45200 | D15: W/F | E15: Kemet | H15: 761 Joel; 582 Maverick | I15: C175432 | J15: C175474 | K15: C175486
A16: SKWFZC1757-B | B16: 45748 | D16: W/F | E16: Bartaloni | H16: 435 Mackenzie; 706 Jay | I16: C175773 | J16: C175733 | K16: C175753 | L16: C175731
A17: SKWFZC1809 | B17: 44287 | C17: 46113 | D17: W/F | E17: Donegal | H17: 704 Reed; 706 Jay | I17: C180974 | J17: C180969 | K17: C180964 | L17: C180987
A18: SKWFZC1812 | B18: 44287 | C18: 46113 | D18: W/F | E18: Damon | H18: 491 Natalie; 582 Maverick | I18: C181257 | J18: C181233 | K18: C181286 | L18: C181254 | M18: C181262
A19: SKWFZC1852 | B19: 44470 | C19: 45017 | D19: W/F | E19: Tiago | H19: 786 Liam; 502 Joshua | I19: C185265 | J19: C185255 | K19: C185252 | L19: C185276 | M19: C185286
A20: SKWFZC1860 | B20: 44470 | D20: W/F | E20: Persia | H20: 403 Vail | I20: C186036 | J20: C186086 | K20: C186008 | L20: C186054 | M20: C186076
A21: SKWFZC1882 | B21: 44652 | D21: W/F | E21: Lukas | H21: 734 Collage | I21: C188232 | J21: C188286 | K21: C188279 | L21: C188273
A22: SKWFZC1965 | B22: 45017 | C22: 45383 | D22: W/F | E22: Nora | H22: 769 Ava; 694 Meyer; 712 Sparrow | I22: C196584 | J22: C196552 | K22: C196566 | L22: C196532
A23: SKWFZC1967B | B23: 46113 | D23: W/F | E23: Lunar | H23: 827 Parsens | I23: C196733 | J23: C196764 | K23: C196768 | L23: C196755 | M23: C196786
A24: SKWFZC2029 | B24: 45383 | C24: 45931 | D24: W/F | E24: Easy | H24: 502 Joshua; 800 Palmer; 820 Norton | I24: C202931 | J24: C202964 | K24: C202958 | L24: C202907 | M24: C202987
A25: SKWFZC2032 | B25: 45566 | C25: 46113 | D25: W/F | E25: Reyson | H25: 734 Collage | I25: C203264 | J25: C203278 | K25: C203274 | L25: C203285 | M25: C203260
A26: SKWFZC2035 | B26: 45566 | D26: W/F | E26: Thane | H26: 717 Fulton | I26: C203531 | J26: C203578 | K26: C203557 | L26: C203554
A27: SKWFZC2042 | B27: 45566 | C27: 46113 | D27: W/F | E27: Duffey | H27: 411 Laurel; 603 Wilmette; 700 Wynne | I27: C204260 | J27: C204232 | K27: C204274 | L27: C204253
A28: SKWFZC2043 | B28: 45566 | D28: W/F | E28: Sheldon | H28: 620 Piper; 700 Wynne | I28: C204373 | J28: C204376 | K28: C204357
A29: SKWFZC2067 | B29: 45748 | D29: W/F | E29: Axe | H29: 725 Sherman | I29: C206764 | J29: C206774 | K29: C206759 | L29: C206786
A30: SKWFZC2118 | B30: 46113 | D30: W/F | E30: Cosdrew | H30: 519 Astor; 827 Parsens | I30: C211869 | J30: C211832 | K30: C211864 | L30: C211852 | M30: C211856
A31: SKWFZC2119 | B31: 46113 | D31: W/F | E31: Longmont | H31: 677 Lauren; 678 Fleetwood | I31: C211932 | J31: C211962 | K31: C211952 | L31: C211955
A32: SKWFZC2121 | B32: 46113 | D32: W/F | E32: Watari | H32: 435 Mackenzie; 828 Dutton | I32: C212171 | J32: C212152 | K32: C212174 | L32: C212167 | M32: C212181
A33: SKWFZC2122 | B33: 46113 | D33: W/F | E33: Taber | H33: 677 Lauren; 678 Fleetwood | I33: C212252 | J33: C212232 | K33: C212263 | L33: C212267
A34: SKWFZD1564-B | B34: 44470 | C34: 44835 | D34: W/F | E34: i-Hallandale | H34: 593 Kennedy | I34: D156453 | J34: D156464 | K34: D156431 | L34: D156458 | M34: D156487
A35: SKWFZD1604 | B35: 43374 | C35: 46113 | D35: W/F | E35: i-Outlier | H35: 562 Clayton Lift Chair; 725 Sherman; 727 Brooks; 776 Redwood; 826 Sammy | I35: D160462 | J35: D160454 | K35: D160476 | L35: D160479 | M35: D160458
A36: SKWFZD1606 | B36: 43374 | C36: 45200 | D36: W/F | E36: i-Halifax | H36: 512 Pinnacle; 793 Jean | I36: D160662 | J36: D160632 | K36: D160654 | L36: D160678 | M36: D160686
A37: SKWFZD1759 | B37: 43922 | C37: 45931 | D37: W/F | E37: i-Saxton | H37: 512 Pinnacle | I37: D175956 | J37: D175986 | K37: D175977 | L37: D175964 | M37: D175978
A38: SKWFZD1806 | B38: 44287 | C38: 45017 | D38: W/F | E38: i-Catalyst | H38: 519 Astor | I38: D180654 | J38: D180632 | K38: D180657 | L38: D180678
A39: SKWFZD1807 | B39: 44287 | C39: 45383 | D39: W/F | E39: Fairfax | H39: 494 Collins; 799 Harbor Town; 665 Alani | I39: D180732 | J39: D180764 | K39: D180774 | L39: D180753 | M39: D180757 | N39: D180786
A40: SKWFZE1652 | B40: 45200 | D40: W/F | E40: i-Liv | H40: 762 Neo | I40: E165231 | J40: E165235 | K40: E165252 | L40: E165296
A41: SKWFZD1825 | B41: 44287 | C41: 45931 | D41: W/F | E41: i-Raven Crest | H41: 502 Joshua; 762 Neo; 786 Liam | I41: D182558 | J41: D182573 | K41: D182535 | L41: D182574
A42: SKWFZD1855A | B42: 46113 | D42: W/F | E42: i-Rivers | H42: 755 Dorian; 757 Apollo; 759 Maddox; 777 Randell; 805 Ace | I42: D185553 | J42: D185575 | K42: D185559 | L42: D185564 | M42: D185552 | N42: D185558
A43: SKWFZD1905 | B43: 44652 | C43: 46113 | D43: W/F | E43: York | H43: 494 Collins; 755 Dorian; 787 Lennon | I43: D190572 | J43: D190558 | K43: D190554 | L43: D190574 | M43: D190531
A44: SKWFZD1970 | B44: 45017 | C44: 45748 | D44: W/F | E44: Marteon | H44: 613 Olson; 636 Shiloh; 638 Charlie;769 Ava | I44: D197034 | J44: D197052 | K44: D197056 | L44: D197066 | M44: D197096
A45: SKWFZD2009 | B45: 45383 | D45: W/F | E45: Promise | H45: 632 Tahoe; 715 Kodie; 681 Bexley | I45: D200931 | J45: D200952 | K45: D200972 | L45: D200946 | M45: D200983 | N45: D200959
A46: SKWFZD2010 | B46: 45383 | C46: 46113 | D46: W/F | E46: i-Rene | H46: 606 Noah; 712 Sparrow; 765 Rowan; 813 Clybourn | I46: D201032 | J46: D201052 | K46: D201065 | L46: D201025 | M46: D201081 | N46: D201019 | O46: D201014
A47: SKWFZD2027 | B47: 45383 | C47: 45748 | D47: W/F | E47: i-Weekend | H47: 759 Maddox; 715 Kodie; 804 Belmont | I47: D202798 | J47: D202751 | K47: D202767 | L47: D202732 | M47: D202775
A48: SKWFZD2034 | B48: 45566 | D48: W/F | E48: Doritt | H48: 802 Cassian | I48: D203454 | J48: D203478 | K48: D203475 | L48: D203436 | M48: D203432
A49: SKWFZD2066 | B49: 45748 | C49: 45931 | D49: W/F | E49: i-Kudos | H49: 521 James; 802 Cassian; 805 Ace | I49: D206661 | J49: D206667 | K49: D206677 | L49: D206680 | M49: D206659
A50: SKWFZD2068 | B50: 45748 | D50: W/F | E50: i-Beverley | H50: 803 Cade; 813 Clybourn | I50: D206893 | J50: D206833 | K50: D206860 | L50: D206871 | M50: D206876
A51: SKWFZD2071 | B51: 45748 | C51: 46113 | D51: W/F | E51: i-Rockport | H51: 681 Bexley; 794 Billie; 810 Quinault; 828 Dutton | I51: D207154 | J51: D207131 | K51: D207152 | L51: D207178 | M51: D207119
A52: SKWFZD2092 | B52: 45748 | D52: W/F | E52: Ross | H52: 803 Cade | I52: D209232 | J52: D209261 | K52: D209252 | L52: D209259 | M52: D209225
A53: SKWFZD2072 | B53: 45748 | C53: 45931 | D53: W/F | E53: i-Nolina | H53: 757 Apollo; 804 Belmont; 807 Baron; 812 Armitage | I53: D207231 | J53: D207252 | K53: D207257 | L53: D207251 | M53: D207275
A54: SKWFZD2074 | B54: 45748 | C54: 45931 | D54: W/F | E54: Gail | H54: 613 Olson; 636 Shiloh; 638 Charlie; 811 Acadia | I54: D207432 | J54: D207480 | K54: D207451 | L54: D207460 | M54: D207478 | N54: D207486
A55: SKWFZD2075 | B55: 45931 | D55: W/F | E55: Galloway | H55: 709 Jasper | I55: D207578 | J55: D207565 | K55: D207538 | L55: D207586
A56: SKWFZD2093 | B56: 45931 | D56: W/F | E56: Artisia | H56: 613 Olson; 636 Shiloh; 638 Charlie | I56: D209376 | J56: D209374 | K56: D209355 | L56: D209351 | M56: D209375 | N56: D209324 | O56: D209331
A57: SKWFZD2095 | B57: 45931 | C57: 46113 | D57: W/F | E57: Crocker | H57: 521 James; 717 Fulton | I57: D209555 | J57: D209574 | K57: D209586 | L57: D209551 | M57: D209562
A58: SKWFZD2096 | B58: 45931 | C58: 46113 | D58: W/F | E58: Defender | H58: 747 Finley ; 811 Acadia | I58: D209669 | J58: D209631 | K58: D209651 | L58: D209664
A59: SKWFZD2099 | B59: 45931 | C59: 46113 | D59: W/F | E59: i-Favorite | H59: 494 Collins; 694 Meyer; 747 Finley; 782 Kells; A86 Ovation | I59: D209933 | J59: D209953 | K59: D209965 | L59: D209931
A60: SKWFZD2100 | B60: 45931 | D60: W/F | E60: i-George | H60: 727 Brooks | I60: D210062 | J60: D210052 | K60: D210031 | L60: D210070 | M60: D210054
A61: SKWFZD2101 | B61: 45931 | D61: W/F | E61: Novan | H61: 663 Paxton; 665 Alani | I61: D210162 | J61: D210174 | K61: D210137 | L61: D210155
A62: SKWFZD2107 | B62: 45931 | D62: W/F | E62: Westcott | H62: 781 Emmons; 807 Baron | I62: D210765 | J62: D210731 | K62: D210769 | L62: D210758
A63: SKWFZD2116 | B63: 46113 | D63: W/F | E63: Rome | H63: 418 Leah; 766 Morrison | I63: D211632 | J63: D211675 | K63: D211652 | L63: D211686
A64: SKWFZD2123 | B64: 46113 | D64: W/F | E64: Ayla | H64: 782 Kells | I64: D212331 | J64: D212373 | K64: D212363 | L64: D212351 | M64: D212386
A65: SKWFZD2124 | B65: 46113 | D65: W/F | E65: i-Westvale | H65: 632 Tahoe; 724 Trouper; A86 Ovation | I65: D212459 | J65: D212432 | K65: D212478 | L65: D212475
A66: SKWFZD2125 | B66: 46113 | D66: W/F | E66: Playlist | H66: 530 Greyson | I66: D212573 | J66: D212533 | K66: D212564 | L66: D212558
A67: SKWFZD2128 | B67: 46113 | D67: W/F | E67: Winslow | H67: 828 Dutton | I67: D212875 | J67: D212869 | K67: D212856
A68: SKWFZD2129 | B68: 46113 | D68: W/F | E68: Zinnamon | H68: 593 Kennedy; 759 Maddox; 826 Sammy | I68: D212954 | J68: D212934 | K68: D212931 | L68: D212952 | M68: D212970
A69: SKWFZD2140 | B69: 46113 | D69: W/F | E69: i-Eugene | H69: 512 Pinnacle | I69: D214074 | J69: D214063 | K69: D214060 | L69: D214032 | M69: D214083
A70: SKWFZE1537-A | B70: 44835 | C70: 46113 | D70: W/F | E70: i-Northwest | H70: 724 Trouper; 766 Morrison | I70: E153767 | J70: E153758 | K70: E153775 | L70: E153765 | M70: E153732 | P70: E153755 | Q70: E153773 | R70: E153752
A71: SKWFZE1917 | B71: 44835 | C71: 45931 | D71: W/F | E71: i-Adario | H71: 632 Tahoe; 810 Quinault | I71: E191734 | J71: E191765 | K71: E191752 | L71: E191753
A72: SKWFZE2036 | B72: 45931 | D72: W/F | E72: Omni | H72: 807 Baron | I72: E203661 | J72: E203675 | K72: E203678 | L72: E203680 | M72: E203659
A73: SKWFZE2040 | B73: 45566 | D73: W/F | E73: i-Gellar | H73: 812 Armitage | I73: E204062 | J73: E204078 | K73: E204052 | L73: E204031 | M73: E204023
A76: DROPPED
A77: SKWFZB1662A | B77: 45383 | D77: W/F | E77: Rodigo | H77: 704 Reed | I77: B166257 | J77: B166278 | K77: B166286 | L77: B166276
A78: SKWFZC1371 | B78: 42278 | C78: 45383 | D78: W/F | E78: Seasons | H78: 519 Astor | I78: C137166 | J78: C137162 | K78: C137178 | L78: C137128 | M78: C137187 | N78: C137108
A79: SKWFZC1516 | B79: 42826 | C79: 45931 | D79: W/F | E79: Merit | H79: 694 Meyer; 765 Rowan | I79: C151651 | J79: C151631 | K79: C151657 | W79: Waterfall Cards for Phase Out covers will NOT be updated at EPI.
A80: SKWFZC1659-A | B80: 43922 | C80: 45748 | D80: W/F | E80: McKittrick | H80: 774 Robin; 411 Laurel; 418 Leah | I80: C165967 | J80: C165972 | K80: C165962 | L80: C165986 | M80: C165992
A81: SKWFZC1945 | B81: 45017 | D81: W/F | E81: Cordance | H81: 759 Maddox | I81: C194533 | J81: C194572 | K81: C194577 | L81: C194554
A82: SKWFZC2037 | B82: 45383 | C82: 45931 | D82: W/F | E82: Tennant | H82: 519 Astor; 709 Jasper; 717 Fulton; 722 Roman; 725 Sherman | I82: C203751 | J82: C203762 | K82: C203766 | L82: C203775 | M82: C203778
A83: SKWFZD1490 | B83: 44652 | C83: 45568 | D83: W/F | E83: i-Benavento | H83: 787 Lennon | I83: D149072 | J83: D149032 | W83: Waterfall Cards for Phase Out covers will NOT be updated at EPI.
A84: SKWFZD1855 | B84: 44470 | C84: 45931 | D84: W/F | E84: i-Rivers | H84: 755 Dorian; 757 Apollo; 759 Maddox; 805 Ace | I84: D185553 | J84: D185575 | K84: D185559 | L84: D185564
A85: SKWFZD2030 | B85: 45383 | D85: W/F | E85: Howell | H85: 781 Emmons; 899 Bennett | I85: D203032 | J85: D203034 | K85: D203053
A86: SKWFZD2031 | B86: 45383 | C86: 45748 | D86: W/F | E86: Lullaby | H86: 782 Kells | I86: D203158 | J86: D203193 | K86: D203133 | L86: D203173 | M86: D203179 | N86: D203165
A87: SKWFZD2038 | B87: 45566 | D87: W/F | E87: Picchu | H87: 787 Lennon; 593 Kennedy; 782 Kells; 811 Acadia | I87: D203830 | J87: D203862 | K87: D203872 | L87: D203859 | M87: D203878 | N87: D203885
A88: SKWFZRE9947-B | B88: 41730 | C88: 45017 | D88: W/F | E88: Palance | H88: 521 James | I88: RE994769 | J88: RE994756 | K88: RE994767

Sheet Cut and Sewn Leather Waterfalls
A1: The following swatches for the Cut & Sewn Leather Waterfall Cards represent current offerings as of the April 2026 market.
A2: LW | M2: Key:
M3: Immediate Drop
M4: Phase Outs
M5: New Phase Outs
M6: April 2026 Drops
M7: April 2026 New Selects
A9: Item Number | B9: Intro Date | C9: Date Last Updated | D9: W/F=Waterfall | E9: Pattern | H9: Style | I9: Cover1 | J9: Cover2 | K9: Cover3 | L9: Cover4 | M9: Cover5 | N9: Cover6 | O9: Cover7
A10: SLWFLB1520 | B10: 43009 | D10: W/F | E10: Yellowstone | H10: 521 James | I10: LB152078 | J10: LB152056
A11: SLWFLB1590-A | B11: 44835 | D11: W/F | E11: Cranbrook | H11: 519 Astor | I11: LB159079 | J11: LB159058
A12: SLWFLB1601-A | B12: 43556 | D12: W/F | E12: Delray | H12: 777 Randell | I12: LB160175 | J12: LB160179
A13: SLWFLB1648 | B13: 43556 | C13: 45383 | D13: W/F | E13: Prestige | H13: 776 Redwood | I13: LB164879 | J13: LB164809
A14: SLWFLB1648-A | B14: 43556 | D14: W/F | E14: Prestige | H14: 722 Roman | I14: LB164879 | J14: LB164854
A15: SLWFLB1727-A | B15: 43922 | D15: W/F | E15: Intermingle | H15: 724 Trouper | I15: LB172755 | J15: LB172779
A16: SLWFLB1728 | B16: 43922 | D16: W/F | E16: Goshen | H16: 502 Joshua | I16: LB172878 | J16: LB172856
A17: SLWFLB1804B | B17: 45200 | D17: W/F | E17: Elite | H17: 762 Neo | I17: LB180474 | J17: LB180459
A18: SLWFLB1849 | B18: 44470 | D18: W/F | E18: Lota | H18: 786 Liam | I18: LB184964 | J18: LB184978
A19: SLWFLB1851 | B19: 44652 | C19: 45383 | D19: W/F | E19: Camaraderie | H19: 781 Emmons | I19: LB185158 | J19: LB185175
A20: SLWFLB1929A | B20: 45474 | D20: W/F | E20: Topflight | H20: 769 Ava | I20: LB192979 | J20: LB192935
A21: SLWFLB1929B | B21: 45017 | C21: 45474 | D21: W/F | E21: Topflight | H21: 759 Maddox | I21: LB192976 | J21: LB192959
A22: SLWFLB1929C | B22: 45748 | D22: W/F | E22: Topflight | H22: 804 Belmont | I22: LB192976 | J22: LB192979
A23: SLWFLB1930-A | B23: 44835 | D23: W/F | E23: Salvo | H23: 757 Apollo | I23: LB193059 | J23: LB193077 | K23: LB193056
A24: SLWFLB1930B | B24: 45017 | D24: W/F | E24: Salvo | H24: 530 Greyson | I24: LB193056 | J24: LB193077 | K24: LB193032
A25: SLWFLB2026 | B25: 45383 | D25: W/F | E25: Grandview | H25: 712 Sparrow | I25: LB202651 | J25: LB202659 | K25: LB202675
A26: SLWFLB2060 | B26: 45566 | C26: 45748 | D26: W/F | E26: Sutton | H26: 715 Kodie; 813 Clybourn | I26: LB206077 | J26: LB206087
A27: SLWFLB2060A | B27: 45566 | D27: W/F | E27: Sutton | H27: 812 Armitage | I27: LB206032 | J27: LB206054 | K27: LB206077
A28: SLWFLB2060B | B28: 45931 | D28: W/F | E28: Sutton | H28: 435 Mackenzie; 603 Wilmette; 613 Olson; 636 Shiloh; 638 Charlie | I28: LB206032 | J28: LB206054 | K28: LB206077 | L28: LB206087
A29: SLWFLB2061 | B29: 45566 | D29: W/F | E29: Gambit | H29: 747 Finley | I29: LB206150 | J29: LB206175 | K29: LB206178
A30: SLWFLB2061A | B30: 45566 | D30: W/F | E30: Gambit | H30: 765 Rowan | I30: LB206132 | J30: LB206159 | K30: LB206178
A31: SLWFLB2061B | B31: 45931 | D31: W/F | E31: Gambit | H31: 803 Cade | I31: LB206132 | J31: LB206175
A32: SLWFLB2062 | B32: 45566 | C32: 45931 | D32: W/F | E32: Clifton | H32: 582 Maverick; 717 Fulton; 802 Cassian | I32: LB206278 | J32: LB206279
A33: SLWFLB2062A | B33: 45566 | D33: W/F | E33: Clifton | H33: 810 Quinault | I33: LB206219 | J33: LB206229 | K33: LB206279
A34: SLWFLB2063 | B34: 45566 | D34: W/F | E34: Dean | H34: 782 Kells; 811 Acadia | I34: LB206376 | J34: LB206379
A35: SLWFLB2063A | B35: 45748 | C35: 45931 | D35: W/F | E35: Dean | H35: 800 Palmer; 820 Norton | I35: LB206377 | J35: LB206332 | K35: LB206357
A36: SLWFLB2064 | B36: 45566 | C36: 45748 | D36: W/F | E36: Opulence | H36: 512 Pinnacle; 709 Jasper | I36: LB206474 | J36: LB206477
A37: SLWFLB2112 | B37: 45931 | D37: W/F | E37: Highbrow | H37: 807 Baron | I37: LB211275 | J37: LB211278 | K37: LB211258
A38: SLWFLB2112A | B38: 45931 | D38: W/F | E38: Highbrow | H38: 755 Dorian | I38: LB211275 | J38: LB211278
A39: SLWFLB2112B | B39: 46113 | D39: W/F | E39: Highbrow | H39: 757 Apollo | I39: LB211268 | J39: LB211276
A40: SLWFLB2113 | B40: 45931 | D40: W/F | E40: Roberto | H40: 805 Ace | I40: LB211379 | J40: LB211376
A41: SLWFLB2113B | B41: 46113 | D41: W/F | E41: Roberto | H41: 530 Greyson | I41: LB211331 | J41: LB211376 | K41: LB211379
A42: SLWFLB2136 | B42: 46113 | D42: W/F | E42: Bellingham | H42: 826 Sammy | I42: LB213679 | J42: LB213659
A43: SLWFLB2137 | B43: 46113 | D43: W/F | E43: Rhythmic | H43: 828 Dutton | I43: LB213777 | J43: LB213758
A44: SLWFLB2141 | B44: 46113 | D44: W/F | E44: Chic | H44: A86 Ovation | I44: LB214176 | J44: LB214159
A46: DROPPED
A47: SLWFLB1646 | B47: 43556 | D47: W/F | E47: Vacation | H47: 704 Reed | I47: LB164677 | J47: LB164663
A48: SLWFLB1804-A | B48: 44652 | D48: W/F | E48: Elite | H48: 787 Lennon | I48: LB180459 | J48: LB180432

Sheet All Resid. Val Packs
A1: April 2026
A3: iClean
A4: Available Covers | G4: Available Styles | J4: Key:
A5: Pattern # | B5: Pattern Name | D5: Pattern # | E5: Pattern Name | G5: Style # | H5: Name | J5: Add to Val Pack
A6: D1563 | B6: i-Barnabas | D6: E1714 | E6: i-Aryna | G6: n/a | H6: n/a | J6: Remove From Val Pack
A7: D1564 | B7: i-Hallandale | D7: E1763 | E7: i-Esma | J7: Replace with New Ring Page
A8: D1604 | B8: i-Outlier | D8: E1764 | E8: i-Leilani
A9: D1606 | B9: i-Halifax | D9: E1785 | E9: i-Machale
A10: D1665 | B10: i-Tazlina | D10: E1790 | E10: i-Oshae
A11: D1759 | B11: i-Saxton | D11: E1815 | E11: i-Emarosa
A12: D1806 | B12: i-Catalyst | D12: E1917 | E12: i-Adario
A13: D1825 | B13: i-Raven Crest | D13: E2040 | E13: i-Gellar
A14: D1855 | B14: i-Rivers | D14: F1574 | E14: i-Colantino
A15: D2010 | B15: i-Rene | D15: G1664 | E15: i-Barber
A16: D2027 | B16: i-Weekend | D16: G1696 | E16: i-Shady Side
A17: D2066 | B17: i-Kudos | D17: G1715 | E17: i-Lockhart
A18: D2068 | B18: i-Beverley | D18: H1571 | E18: i-Savane
A19: D2071 | B19: i-Rockport | D19: H1572 | E19: i-Adril
... A26: E1651 | B26: i-Broderick | D26: Q1941 | E26: i-Atherton
A27: E1652 | B27: i-Liv
A29: Conserve
A30: Available Covers | G30: Available Styles
A31: Pattern # | B31: Pattern Name | D31: Pattern # | E31: Pattern Name | G31: Style # | H31: Name
A32: E1651 | B32: i-Broderick | D32: E1815 | E32: i-Emarosa | G32: n/a | H32: n/a
A33: E1652 | B33: i-Liv | D33: E1917 | E33: i-Adario
A34: E1714 | B34: i-Aryna | D34: G1696 | E34: i-Shady Side
A35: E1763 | B35: i-Esma | D35: Q1992 | E35: Fascinate
A36: E1764 | B36: i-Leilani
A38: Health & Wellness
A39: Available Covers | G39: Available Styles
A40: Pattern # | B40: Pattern Name | D40: Pattern # | E40: Pattern Name | G40: Style # | H40: Name
A41: E1785 | B41: i-Machale | D41: Q1912 | E41: i-Blackhawk | G41: n/a | H41: n/a
A42: E1790 | B42: i-Oshae | D42: Q1941 | E42: i-Atherton
A43: N1791 | B43: i-Pipers Brook
A45: Pet Friendly
A46: Available Covers | G46: Available Styles
A47: Pattern # | B47: Pattern Name | D47: Pattern # | E47: Pattern Name | G47: Style # | H47: Name
A48: D1564 | B48: i-Hallandale | D48: D2124 | E48: i-Westvale | G48: n/a | H48: n/a
A49: D1604 | B49: i-Outlier | D49: E1537 | E49: i-Northwest
A50: D1806 | B50: i-Catalyst | D50: E1763 | E50: i-Esma
A51: D1825 | B51: i-Raven Crest | D51: E1764 | E51: i-Lelaini
A52: D2027 | B52: i-Weekend | D52: E1785 | E52: i-Machale
A53: D2066 | B53: i-Kudos | D53: Q1912 | E53: i-Blackhawk
A54: D2099 | B54: i-Favorite | D54: Q1941 | E54: i-Atherton
A56: Stationary, Sectional & Sleeper
A57: Available Covers | G57: Available Styles
A58: Pattern # | B58: Pattern Name | D58: Pattern # | E58: Pattern Name | G58: Style # | H58: Name | J58: Style # | K58: Name
A59: B1808 | B59: Social Club | D59: D1905 | E59: York | G59: 411 | H59: Laurel | J59: 593 | K59: Kennedy
A60: C1659 | B60: McKittrick | D60: D1970 | E60: Marteon | G60: 418 | H60: Leah | J60: 613 | K60: Olson
A61: C1757 | B61: Bartaloni | D61: D2010 | E61: i-Rene | G61: 435 | H61: Mackenzie | J61: 620 | K61: Piper
A62: C1945 | B62: Cordance | D62: D2038 | E62: Picchu | G62: 636 | H62: Shiloh | J62: 694 | K62: Meyer + Sec
A63: C1965 | B63: Nora | D63: D2068 | E63: i-Beverley | G63: 494 | H63: Collins + Sec | J63: 606 | K63: Noah
A64: C2042 | B64: Duffey | D64: D2074 | E64: Gail | G64: 603 | H64: Wilmette + Sec | J64: 638 | K64: Charlie + Sec
A65: C2043 | B65: Sheldon | D65: D2093 | E65: Artisia
A66: C2121 | B66: Watari | D66: D2099 | E66: i-Favorite
A67: D1564 | B67: i-Hallandale | D67: D2116 | E67: Rome
A68: D1807 | B68: Fairfax | D68: D2129 | E68: Zinnamon
A70: Recliner
A71: Available Covers | G71: Available Styles
A72: Pattern # | B72: Pattern Name | D72: Pattern # | E72: Pattern Name | G72: Style # | H72: Name | J72: Style # | K72: Name
A73: B1538 | B73: Seamount | D73: D1759 | E73: i-Saxton | G73: 725 | H73: Sherman | J73: 766 | K73: Morrison
A74: B1808 | B74: Social Club | D74: D2009 | E74: Promise | G74: 403 | H74: Vail | J74: 715 | K74: Kodie
A75: C1625 | B75: Vance | D75: D2027 | E75: i-Weekend | G75: 709 | H75: Jasper | J75: 786 | K75: Liam
A76: C1754 | B76: Kemet | D76: D2034 | E76: Doritt | G76: 761 | H76: Joel | J76: 803 | K76: Cade
A77: C1852 | B77: Tiago | D77: D2066 | E77: i-Kudos | G77: 802 | H77: Cassian
A78: C1860 | B78: Persia | D78: D2068 | E78: i-Beverley
A79: C2067 | B79: Axe | D79: D2075 | E79: Galloway
A80: D1564 | B80: i-Hallandale | D80: D2092 | E80: Ross
A81: D1604 | B81: i-Outlier | D81: D2116 | E81: Rome
A82: D1606 | B82: i-Halifax
A84: Nanobionic Lift Chair
A85: Available Covers | G85: Available Styles
A86: Pattern # | B86: Pattern Name | D86: Pattern # | E86: Pattern Name | G86: Style # | H86: Name | J86: Style # | K86: Name
A87: D1604 | B87: i-Outlier | D87: Q1912 | E87: i-Blackhawk | G87: 512 | H87: Pinnacle | J87: 562 | K87: Clayton
A88: D1606 | B88: i-Halifax | D88: Q1941 | E88: i-Atherton | G88: 519 | H88: Astor | J88: 793 | K88: Jean
A89: D1806 | B89: i-Catalyst | G89: 786 | H89: Liam | J89: 794 | K89: Billie
A90: D1825 | B90: i-Raven Crest
A91: D2071 | B91: i-Rockport
A93: Motion
A94: Available Covers | G94: Available Styles
A95: Pattern # | B95: Pattern Name | D95: Pattern # | E95: Pattern Name | G95: Style # | H95: Name | J95: Style # | K95: Name
A96: B1538 | B96: Seamount | D96: D2027 | E96: i-Weekend | G96: 512 | H96: Pinnacle | J96: 803 | K96: Cade
A97: B1808 | B97: Social Club | D97: D2034 | E97: Doritt | G97: 706 | H97: Jay | J97: 759 | K97: Maddox
A98: C1754 | B98: Kemet | D98: D2066 | E98: i-Kudos | G98: 761 | H98: Joel | J98: 802 | K98: Cassian
A99: C1757 | B99: Bartaloni | D99: D2068 | E99: i-Beverley | G99: 727 | H99: Brooks | J99: 521 | K99: James
A100: C1809 | B100: Donegal | D100: D2092 | E100: Ross | G100: 766 | H100: Morrison
A101: C1945 | B101: Cordance | D101: D2095 | E101: Crocker
A102: D1604 | B102: i-Outlier | D102: D2100 | E102: i-George
A103: D1606 | B103: i-Halifax | D103: D2116 | E103: Rome
A104: D1759 | B104: i-Saxton | D104: D2140 | E104: i-Eugene

Sheet Fringe and Cord
A1: The following swatches for the La-Z-Boy Fringe and Cord Collection represent current offerings as of the October 2025 Market.
A2: SFC
A3: Trim/Cords | I3: Key:
I4: Immediate Drop
I5: Phase Outs
I6: New Phase Outs
I7: April 2026 Drops
I8: April 2026 New Selects
A10: Item Number | B10: Product Line | C10: Intro Date | D10: Date Last Updated | E10: S=Single, C=Correlate, W/F=Waterfall, P/S=Postage Stamp | F10: Cover1 | G10: Cover2 | H10: Cover3 | I10: Cover4 | J10: Cover5 | K10: Cover6
A12: Dropped

Sheet Invoicing Breakdown
A1: October 24 New Cover Invoicing Breakdown | F1: April 26 New Cover Invoicing Breakdown and Timeline | O1: October 26 New Cover Invoicing Breakdown and Timeline
A2: Name | B2: Cost | C2: Updates | D2: Total Invoiced | F2: Swatch Set | G2: # of Updates | H2: Cost | I2: Total Invoiced | L2: Furniture Galleries | M2: Comfort Studios & General Dealers | O2: Swatch Set | P2: # of Updates | Q2: Cost | R2: Total Invoiced | U2: Furniture Galleries | V2: Comfort Studios & General Dealers
A3: Major Upholstery | B3: 12 | C3: 25 | D3: =SUM(B3*C3) -> 300 | F3: Major Upholstery | G3: 23 | H3: 12.5 | I3: =SUM(H3*G3) -> 287.5 | L3: June 2026 | M3: January 2027-No charge for qualifying dealers* Invoicing will be for both Spring and Fall 2025 updates | O3: Major Upholstery | Q3: 12.5 | R3: =SUM(Q3*P3) -> 0 | U3: December 2026 | V3: January 2027-No charge for qualifying dealers* Invoicing will be for both Spring and Fall 2025 updates
A4: Select Reclining | B4: 13 | C4: 17 | D4: =SUM(B4*C4) -> 221 | F4: Select Reclining | G4: 10 | H4: 13.5 | I4: =SUM(H4*G4) -> 135 | L4: June 2026 | M4: January 2027-No charge for qualifying dealers* Invoicing will be for both Spring and Fall 2025 updates | O4: Select Reclining | Q4: 13.5 | R4: =SUM(Q4*P4) -> 0 | U4: December 2026 | V4: January 2027-No charge for qualifying dealers* Invoicing will be for both Spring and Fall 2025 updates
A5: Custom Leather | B5: 33 | C5: 0 | D5: =SUM(B5*C5) -> 0 | F5: Custom Leather | G5: 1 | H5: 34.5 | I5: =SUM(H5*G5) -> 34.5 | L5: June 2026 | M5: January 2027-No charge for qualifying dealers* Invoicing will be for both Spring and Fall 2025 updates | O5: Custom Leather | Q5: 34.5 | R5: =SUM(Q5*P5) -> 0 | U5: December 2026 | V5: January 2027-No charge for qualifying dealers* Invoicing will be for both Spring and Fall 2025 updates
A6: Custom Leather Plus | B6: 33 | C6: 0 | D6: =SUM(B6*C6) -> 0 | F6: Custom Leather Plus | G6: 1 | H6: 34.5 | I6: =SUM(H6*G6) -> 34.5 | L6: June 2026 | M6: January 2027-No charge for qualifying dealers* Invoicing will be for both Spring and Fall 2025 updates | O6: Custom Leather Plus | Q6: 34.5 | R6: =SUM(Q6*P6) -> 0 | U6: December 2026 | V6: January 2027-No charge for qualifying dealers* Invoicing will be for both Spring and Fall 2025 updates
A7: Select Stationary | B7: 13 | C7: 0 | D7: =SUM(B7*C7) -> 0 | F7: Select Stationary | G7: 0 | H7: 13.5 | I7: =SUM(H7*G7) -> 0 | L7: June 2026 | M7: June 2026 | O7: Select Stationary | Q7: 13.5 | R7: =SUM(Q7*P7) -> 0 | U7: December 2026 | V7: December 2026
A8: Specialty Leather | B8: 19 | C8: 0 | D8: =SUM(B8*C8) -> 0 | F8: Specialty Leather | G8: 1 | H8: 20 | I8: =SUM(H8*G8) -> 20 | L8: June 2026 | M8: June 2026 | O8: Specialty Leather | Q8: 20 | R8: =SUM(Q8*P8) -> 0 | U8: December 2026 | V8: December 2026
A9: Recliner VP | B9: 12 | C9: 2 | D9: =SUM(B9*C9) -> 24 | F9: Recliner VP | G9: 2 | H9: 12.5 | I9: =SUM(H9*G9) -> 25 | L9: June 2026 | M9: June 2026 | O9: Recliner VP | Q9: 12.5 | R9: =SUM(Q9*P9) -> 0 | U9: December 2026 | V9: December 2026
A10: Motion VP | B10: 12 | C10: 2 | D10: =SUM(B10*C10) -> 24 | F10: Motion VP | G10: 3 | H10: 12.5 | I10: =SUM(H10*G10) -> 37.5 | L10: June 2026 | M10: June 2026 | O10: Motion VP | Q10: 12.5 | R10: =SUM(Q10*P10) -> 0 | U10: December 2026 | V10: December 2026
A11: Stationary Sofa and Sleeper VP | B11: 12 | C11: 5 | D11: =SUM(B11*C11) -> 60 | F11: Stationary Sofa and Sleeper VP | G11: 3 | H11: 12.5 | I11: =SUM(H11*G11) -> 37.5 | L11: June 2026 | M11: June 2026 | O11: Stationary Sofa and Sleeper VP | Q11: 12.5 | R11: =SUM(Q11*P11) -> 0 | U11: December 2026 | V11: December 2026
A12: iClean VP | B12: 12 | C12: 2 | D12: =SUM(B12*C12) -> 24 | F12: iClean VP | G12: 3 | H12: 12.5 | I12: =SUM(H12*G12) -> 37.5 | L12: June 2026 | M12: June 2026 | O12: iClean VP | Q12: 12.5 | R12: =SUM(Q12*P12) -> 0 | U12: December 2026 | V12: December 2026
A13: Pet Friendly VP | B13: 12 | C13: 1 | D13: =SUM(B13*C13) -> 12 | F13: Pet Friendly VP | G13: 1 | H13: 12.5 | I13: =SUM(H13*G13) -> 12.5 | L13: June 2026 | M13: June 2026 | O13: Pet Friendly VP | Q13: 12.5 | R13: =SUM(Q13*P13) -> 0 | U13: December 2026 | V13: December 2026
A14: Lift Chair VP | B14: 12 | C14: 1 | D14: =SUM(B14*C14) -> 12 | F14: Lift Chair VP | G14: 0 | H14: 12.5 | I14: =SUM(H14*G14) -> 0 | L14: June 2026 | M14: June 2026 | O14: Lift Chair VP | Q14: 12.5 | R14: =SUM(Q14*P14) -> 0 | U14: December 2026 | V14: December 2026
... A17: Large Design Center | B17: 12 | C17: 93 | D17: =SUM(B17*C17) -> 1116 | F17: Large Design Center | G17: 80 | H17: 12.5 | I17: =SUM(H17*G17) -> 1000 | L17: June 2026 | M17: June 2026 | O17: Large Design Center | Q17: 12.5 | R17: =SUM(Q17*P17) -> 0 | U17: December 2026 | V17: December 2026
F18: Small Design Center | G18: 55 | H18: 12.5 | I18: =SUM(H18*G18) -> 687.5 | L18: June 2026 | M18: June 2026 | O18: Small Design Center | Q18: 12.5 | R18: =SUM(Q18*P18) -> 0 | U18: December 2026 | V18: December 2026
A19: Small Design Center | B19: 12 | C19: 51 | D19: =SUM(B19*C19) -> 612 | F19: Retail Test Store Hanger | G19: 10 | H19: 36.5 | I19: =SUM(H19*G19) -> 365 | L19: June 2026 | M19: June 2026 | O19: Retail Test Store Hanger | Q19: 36.5 | R19: =SUM(Q19*P19) -> 0 | U19: December 2026 | V19: December 2026
M20: *Qualifying dealers=Purchased a minimum of 200 units NOB for 2025 calendar year | V20: *Qualifying dealers=Purchased a minimum of 200 units NOB for 2025 calendar year
F23: If you have questions regarding Swatch Invoicing, please refer to the Swatch Guidelines (housed on the Marketing Hub) and/or reach out to your Account Representative.

Sheet Swatch Icon Descriptions
A1: Swatch Icon Descriptions
A3: Pet Friendly | D3: Performance
A11: iClean | D11: Conserve
A18: Antimicrobial | D18: Nanobionic
A26: Bleach Cleanable

Sheet SupportData
A1: Fabric Numbering System
A3: GRADE
A4: Single Alpha Digit "A" through "S" signifies price.
A5: a. Alpha digit "V" following grade indicates pattern is vinyl.
A6: b. Alpha digit "L" following grade indicates pattern is leather.
A8: PATTERN
A9: Numerical four digit assigned by pattern
A11: COLOR
A12: Two numerical digits
A13: c. First digit indicates color family.
A14: d. Second digit is assigned for La-Z-Boy internal use.
A16: Color Family:
... A31: 59 super dark gray

Sheet Swatch SKU Numbering
N2: New Logic after 4/1/2024
N4: 6x6
N5: ALL covers - SM6Z + cover SKU
N7: 3x5
N8: All leathers - SL6 + cover SKU
H38: LIFT CHAIR VAL PACK COVER INSERT | I38: Cover | J38: MS0367 000091-A
H39: MOTION VAL PACK COVER INSERT | I39: Cover | J39: MS0360 000089-A
H40: RECLINER VAL PACK COVER INSERT | I40: Cover | J40: MS0359 000088-A
H41: RECLINER VAL PACK (CAN) COVER INSERT | I41: Cover | J41: MS0359CA
H42: STATIONARY & SLEEP SOFA VAL PACK COVER INSERT | I42: Cover | J42: MS0330 000090-A
H43: Health & Wellness VAL PACK COVER INSERT | I43: Cover | J43: MS0401
H44: ANTIMICROBIAL DIVIDER *The current Anti Cover will become the Anti Divider* | I44: Divider | J44: MS0387
H45: NANOBIONIC DIVIDER | I45: Divider | J45: MS0402
